Workbook
Name Lifestyle_upgrade_every_5y_Max: 'Lifestyle Strategy'!$M$6
Name Lifestyle_upgrade_every_5y_Min: 'Lifestyle Strategy'!$M$5
Name Lifestyle_upgrade_every_5y_Mostlikely: 'Lifestyle Strategy'!$M$7
Name Lifestyle_upgrade_every_5y_Triangular_Distribution: 'Lifestyle Strategy'!$M$4
Name Post_retirement_Lifestyle_Upgrade_every_5y_Max: 'Lifestyle Strategy'!$M$19
Name Post_retirement_Lifestyle_Upgrade_every_5y_Min: 'Lifestyle Strategy'!$M$18
Name Post_retirement_Lifestyle_Upgrade_every_5y_Mostlikely: 'Lifestyle Strategy'!$M$20

Sheet Pre-Retirement_cal
A1: Emily's Basic Information | D1: Employee Contribution | I1: Total Contribution | K1: Total Profit | M1: Corpus at Retirement | P1: Expected Corpus for Post Retirement | R1: Sustainable Post Retirement ? | U1: Key Feature Selected
A2: Salary | B2: 70000 | D2: Starting rate | E2: 0.03 | M2: Pre Ret. | N2: Post Ret. | O2: Total Corpus | BY2: Yes
A3: Hike Rise | B3: 0.035 | D3: Increase every year | E3: 2 | I3: =TEXT(($I$7)/1000000,"[$$-en-US]0.00")&"M" -> $0.89M | K3: =TEXT(($K$7)/1000000, "[$$-en-US]0.00") & "M" -> $3.95M | M3: =TEXT(($M$7)/1000000, "[$$-en-US]0.00") & "M" -> $4.84M | N3: =TEXT(($N$7)/1000000, "[$$-en-US]0.00") & "M" -> $2.12M | O3: =TEXT(($O$7)/1000000, "[$$-en-US]0.00") & "M" -> $6.94M | P3: =TEXT(($P$7)/1000000, "[$$-en-US]0.00") & "M" -> $4.18M | R3: =IF(O7>=P7, "Yes", "No") -> Yes | U3: Has_Partner_Contributed | V3: =IF($V$10 = $X$8, "Random",IF($V$10 =$U$8,"Yes","No")) -> Random | W3: Has_Double_Promotion | X3: =IF($V$10 = $X$8, "Random",IF($V$10 =$U$8,"Yes","No")) -> Random | Y3: Has_Partner | Z3: =IF($V$10 = $X$8, "Random",IF($V$10 =$U$8,"Yes","No")) -> Random | BY3: No
A4: Salary std. dev | B4: 0.007 | D4: Increase percentage | E4: =IF(X4="Random", IF(RANDBETWEEN(0,1)=1,0.01,0), IF(X4="Yes",0.01,0)) -> 0.01 | U4: Has_Children | V4: =IF($V$10=$X$8,"Random",IF($V$10=$W$8, "Yes","No")) -> Random | W4: Has_Increase_in_Contribution | X4: =IF($V$10 = $X$8, "Random",IF($V$10 =$U$8,"Yes","No")) -> Random | Y4: Has_Invested_Post_Retirement | Z4: =IF($V$10 = $X$8, "Random",IF($V$10 =$U$8,"Yes","No")) -> Random | BY4: Random
A5: Double Promotion Year | B5: =IF($B$7="No",0,RANDBETWEEN(5,30)) -> 10 | D5: Max rate | E5: 0.12 | U5: Has_Purchase_New_Home | V5: =IF($V$10=$X$8,"Random",IF($V$10=$W$8, "Yes","No")) -> Random | W5: Has_Lumpsum_Deposit | X5: =IF($V$10 = $X$8, "Random",IF($V$10 =$U$8,"Yes","No")) -> Random
A6: ACC Levy | B6: 0.0167 | D6: Lumpsum Every Year | E6: 5 | U6: Has_Unforeseen Withdrawal | V6: =IF($V$10=$X$8,"Random",IF($V$10=$W$8, "Yes","No")) -> Random | W6: Has_Lifestyle_Upgrade | X6: =IF($V$10=$X$8, "Random", IF( $V$10=W8, "Yes","No")) -> Random
A7: Double Promotion Year_Considered | B7: =IF(X3="Random",IF(RANDBETWEEN(0,1) = 0, "No", "Yes"),X3) -> Yes | D7: Lumpsum Amount | E7: =IF(X5="Random", IF(RANDBETWEEN(0,1)=1,10000,0), IF(X5="Yes",10000,0)) -> 10000 | I7: =SUM($Q$13:$Q$48) -> 890363.13 | K7: =$M$7-$I$7 -> 3951835.5 | M7: =BU51 -> 4842198.6 | N7: =BV51 -> 2119069.3 | O7: =BW51 -> 6936178 | P7: =BX51 -> 4175484.2
U8: Best Scenario | V8: Neutral Scenario | W8: Worst Scenario | X8: Random
A9: Pre Retirement Fund Calculation
U10: Selected Scenario | V10: Random
A12: Index | B12: Year | C12: Age | D12: Gross Salary | E12: Salary Hike Value | F12: Salary Hike % | G12: Income Tax | H12: ACC Levy | I12: Net Salary | J12: Employee Contribution Rate % | K12: Employer Contribution Rate % | L12: Partner Contribution | M12: Employee Contribution | N12: Employer Contribution | O12: Partner Contribution | P12: Lump Sum Added | Q12: Total Contribution | R12: Harboursafe Contribution | S12: Harboursafe Return | T12: Harbour safe return_value | U12: Harboursafe_corpus | V12: Horizon Contribution | W12: Horizon Return | X12: Horizon return value | Y12: Horizon Corpus | Z12: SkyHigh Contribution | AA12: SkyHigh Return | AB12: SkyHigh return value | AC12: SkyHigh corpus | AD12: Foreign_Equities Contribution | AE12: Foreign_Equities Return | AF12: Foreign return value | AG12: Bitcoin Contribution | AH12: Bitcoin Return | AI12: Bitcoin return value | AJ12: Bitcoin Corpus | AK12: FIF Tax (NZD) | AL12: FIF Tax % of Foreign Value | AM12: Foreign corpus | AN12: Foreign corpus after FIF tax | AO12: Rent | AP12: Groceries | AQ12: Travel | AR12: Utilities | AS12: Insurance | AT12: Leisure | AU12: Misc | AV12: Owns Home_EMI | AW12: Children Expense | AX12: Total Spent | AY12: Unforeseen Withdrawal | AZ12: Requested Withdrawal | BA12: Withdrawal Shortfall | BB12: Final Corpus Fund Value | BC12: Corpus Amount in Millions | BQ12: Post Retirement Fund Calculation
B13: 0 | C13: 30 | D13: =B2 -> 70000 | E13: 0 | F13: 0 | G13: ='Tax rate cal'!C10 -> 13220.5 | H13: =$B$6*D13 -> 1169 | I13: =D13-G13-H13 -> 55610.5 | J13: =MIN($E$2 + INT(B13/$E$3)*$E$4, $E$5) -> 0.03 | K13: 0.03 | L13: =IF(O13 = 0,0,'Lifestyle Strategy'!$Q$9) -> 0 | M13: =I13*J13 -> 1668.315 | N13: =I13*K13 -> 1668.315 | O13: =IF(AND('Lifestyle Strategy'!$Q$2="Yes", B13 >='Lifestyle Strategy'!$Q$3), I13 * 'Lifestyle Strategy'!$Q$9, 0 ) -> 0 | P13: =IF(B13<10,0,IF(MOD(B13, $E$6) = 0, $E$7, 0)) -> 0 | Q13: =M13+N13+O13+P13 -> 3336.63 | R13: =IF(B13<=5, Q13*'Fund Allocation Strategy'!$B$2, IF(B13<=10, Q13*'Fund Allocation Strategy'!$B$3, IF(B13<=15, Q13*'Fund Allocation Strategy'!$B$4, IF(B13<=20, Q13*'Fund Allocation Strategy'!$B$5, IF(B13<=25, Q13*'Fund Allocation Strategy'!$B$6, IF(B13<=30, Q13*'Fund Allocation Strategy'!$B$7, Q13*'Fund Allocation Strategy'!$B$8)))))) -> 166.8315 | S13: =_xlfn.NORM.INV(RAND(),'Fund Allocation Strategy'!$B$11,'Fund Allocation Strategy'!$C$11) -> 0.037283263 | T13: =R13*S13*0.5 -> 3.1100114 | U13: =R13+T13 -> 169.94151 | V13: =IF(B13<=5, Q13*'Fund Allocation Strategy'!$C$2, IF(B13<=10, Q13*'Fund Allocation Strategy'!$C$3, IF(B13<=15, Q13*'Fund Allocation Strategy'!$C$4, IF(B13<=20, Q13*'Fund Allocation Strategy'!$C$5, IF(B13<=25, Q13*'Fund Allocation Strategy'!$C$6, IF(B13<=30, Q13*'Fund Allocation Strategy'!$C$7, Q13*'Fund Allocation Strategy'!$C$8)))))) -> 166.8315 | W13: =_xlfn.NORM.INV(RAND(),'Fund Allocation Strategy'!$B$12,'Fund Allocation Strategy'!$C$12) -> 0.070556951 | X13: =V13*W13*0.5 -> 5.885561 | Y13: =V13+X13 -> 172.71706 | Z13: =IF(B13<=5, Q13*'Fund Allocation Strategy'!$D$2, IF(B13<=10, Q13*'Fund Allocation Strategy'!$D$3, IF(B13<=15, Q13*'Fund Allocation Strategy'!$D$4, IF(B13<=20, Q13*'Fund Allocation Strategy'!$D$5, IF(B13<=25, Q13*'Fund Allocation Strategy'!$D$6, IF(B13<=30, Q13*'Fund Allocation Strategy'!$D$7, Q13*'Fund Allocation Strategy'!$D$8)))))) -> 1501.4835 | AA13: =_xlfn.NORM.INV(RAND(),'Fund Allocation Strategy'!$B$13,'Fund Allocation Strategy'!$C$13) -> 0.10192759 | AB13: =Z13*AA13*0.5 -> 76.5213 | AC13: =Z13+AB13 -> 1578.0048 | AD13: =IF(B13<=5, Q13*'Fund Allocation Strategy'!$E$2, IF(B13<=10, Q13*'Fund Allocation Strategy'!$E$3, IF(B13<=15, Q13*'Fund Allocation Strategy'!$E$4, IF(B13<=20, Q13*'Fund Allocation Strategy'!$E$5, IF(B13<=25, Q13*'Fund Allocation Strategy'!$E$6, IF(B13<=30, Q13*'Fund Allocation Strategy'!$E$7, Q13*'Fund Allocation Strategy'!$E$8)))))) -> 1000.989 | AE13: =_xlfn.NORM.INV(RAND(), 'Fund Allocation Strategy'!$B$14, 'Fund Allocation Strategy'!$C$14) + _xlfn.NORM.INV(RAND(), 'Fund Allocation Strategy'!$D$14,'Fund Allocation Strategy'!$E$14) -> 0.11676117 | AF13: =AD13*AE13*0.5 -> 58.438323 | AG13: =IF(B13<=5, Q13*'Fund Allocation Strategy'!$F$2, IF(B13<=10, Q13*'Fund Allocation Strategy'!$F$3, IF(B13<=15, Q13*'Fund Allocation Strategy'!$F$4, IF(B13<=20, Q13*'Fund Allocation Strategy'!$F$5, IF(B13<=25, Q13*'Fund Allocation Strategy'!$F$6, IF(B13<=30, Q13*'Fund Allocation Strategy'!$F$7, Q13*'Fund Allocation Strategy'!$F$8)))))) -> 500.4945 | AH13: =_xlfn.NORM.INV(RAND(),'Fund Allocation Strategy'!$B$15,'Fund Allocation Strategy'!$C$15) -> 0.20108929 | AI13: =AG13*AH13*0.5 -> 50.322042 | AJ13: =AG13+AI13 -> 550.81654 | AK13: =IF(AM13<50000,0, AM13*0.015) -> 0 | AL13: =IF(AM13<50000,0,0.015) -> 0 | AM13: =AD13+AF13 -> 1059.4273 | AN13: =AM13-AK13 -> 1059.4273 | AO13: =IF(AV13 = 0, I13 * ( 'Lifestyle Strategy'!$B$2 + ('Lifestyle Strategy'!$C$2 - 'Lifestyle Strategy'!$B$2) * _xlfn.BETA.INV(RAND(), 'Lifestyle Strategy'!$F$2, 'Lifestyle Strategy'!$G$2) ),IF(AV13 = "", "",0)) -> 12527.189 | AP13: =I13 * ( 'Lifestyle Strategy'!$B$3 + ('Lifestyle Strategy'!$C$3 - 'Lifestyle Strategy'!$B$3) * _xlfn.BETA.INV(RAND(), 'Lifestyle Strategy'!$F$3, 'Lifestyle Strategy'!$G$3) ) * IF(MOD(B13,5)=0, 1 + 'Lifestyle Strategy'!$M$4, 1 + 0.025) -> 7143.0299 | AQ13: =I13 * ( 'Lifestyle Strategy'!$B$4 + ('Lifestyle Strategy'!$C$4 - 'Lifestyle Strategy'!$B$4) * _xlfn.BETA.INV(RAND(), 'Lifestyle Strategy'!$F$4, 'Lifestyle Strategy'!$G$4) ) * IF(MOD(B13,5)=0, 1 + 'Lifestyle Strategy'!$M$4, 1 + 0.025) -> 3780.9441 | AR13: =I13 * ( 'Lifestyle Strategy'!$B$5 + ('Lifestyle Strategy'!$C$5 - 'Lifestyle Strategy'!$B$5) * _xlfn.BETA.INV(RAND(), 'Lifestyle Strategy'!$F$5, 'Lifestyle Strategy'!$G$5) ) * IF(MOD(B13,5)=0, 1 + 'Lifestyle Strategy'!$M$4, 1 + 0.025) -> 2710.2138 | AS13: =I13 * ( 'Lifestyle Strategy'!$B$6 + ('Lifestyle Strategy'!$C$6 - 'Lifestyle Strategy'!$B$6) * _xlfn.BETA.INV(RAND(), 'Lifestyle Strategy'!$F$6, 'Lifestyle Strategy'!$G$6) ) * IF(MOD(B13,5)=0, 1 + 'Lifestyle Strategy'!$M$4, 1 + 0.025) -> 3129.2604 | AT13: =I13 * ( 'Lifestyle Strategy'!$B$7 + ('Lifestyle Strategy'!$C$7 - 'Lifestyle Strategy'!$B$7) * _xlfn.BETA.INV(RAND(), 'Lifestyle Strategy'!$F$7, 'Lifestyle Strategy'!$G$7) ) * IF(MOD(B13,5)=0, 1 + 'Lifestyle Strategy'!$M$4, 1 + 0.025) -> 6621.749 | AU13: =I13 * ( 'Lifestyle Strategy'!$B$8 + ('Lifestyle Strategy'!$C$8 - 'Lifestyle Strategy'!$B$8) * _xlfn.BETA.INV(RAND(), 'Lifestyle Strategy'!$F$8, 'Lifestyle Strategy'!$G$8) ) * IF(MOD(B13,5)=0, 1 + 'Lifestyle Strategy'!$M$4, 1 + 0.025) -> 2029.8467 | AV13: =IF('Lifestyle Strategy'!$B$14 = "Yes", IF(AND(B13>='Lifestyle Strategy'!$B$15, B13<'Lifestyle Strategy'!$B$16), 'Lifestyle Strategy'!$B$25, IF(B13>='Lifestyle Strategy'!$B$16, "", 0) ), 0 ) -> 0 | AW13: =IF('Lifestyle Strategy'!$Q$4="No", 0, IF(AND(B13>='Lifestyle Strategy'!$Q$5, B13<'Lifestyle Strategy'!$Q$6), 'Lifestyle Strategy'!$Q$8 * (1.025^(B13-'Lifestyle Strategy'!$Q$5)) * (1.12^INT((B13-'Lifestyle Strategy'!$Q$5)/5)), 0 ) ) -> 0 | AX13: =IF(AO13 = "",0,AO13)+AP13+AQ13+AR13+AS13+AT13+AU13+AW13+IF(AV13 = "",0,AV13) -> 37942.233 | AY13: =IF(B13='Lifestyle Strategy'!$Q$10, MIN(AN13, 'Lifestyle Strategy'!$Q$11), 0) -> 0 | AZ13: =IF(B13='Lifestyle Strategy'!$Q$10, 'Lifestyle Strategy'!$Q$11, 0) -> 0 | BA13: =IF(B13='Lifestyle Strategy'!$Q$10, MAX(AZ13 - AY13, 0), 0) -> 0 | BB13: =U13+Y13+AC13+AJ13+AN13-AY13 -> 3530.9072 | BC13: =TEXT(BB13/1000000, "[$$-en-US]0.00") & "M" -> $0.00M
B14: 1 | C14: 31 | D14: =IF(B14<>$B$5,D13*(1+_xlfn.NORM.INV(RAND(),$B$3,$B$4)),D13*(1+_xlfn.NORM.INV(RAND(),$B$3,$B$4))+D13*(1+_xlfn.NORM.INV(RAND(),$B$3,$B$4))) -> 72057.192 | E14: =D14-D13 -> 2057.1917 | F14: =E14/D13 -> 0.029388454 | G14: ='Tax rate cal'!C11 -> 13643.17 | H14: =$B$6*D14 -> 1203.3551 | I14: =D14-G14-H14 -> 57210.667 | J14: =MIN($E$2 + INT(B14/$E$3)*$E$4, $E$5) -> 0.03 | K14: 0.03 | L14: =IF(O14 = 0,0,'Lifestyle Strategy'!$Q$9) -> 0 | M14: =I14*J14 -> 1716.32 | N14: =I14*K14 -> 1716.32 | O14: =IF(AND('Lifestyle Strategy'!$Q$2="Yes", B14 >='Lifestyle Strategy'!$Q$3), I14 * 'Lifestyle Strategy'!$Q$9, 0 ) -> 0 | P14: =IF(B14<10,0,IF(MOD(B14, $E$6) = 0, $E$7, 0)) -> 0 | Q14: =M14+N14+O14+P14 -> 3432.64 | R14: =IF(B14<=5, Q14*'Fund Allocation Strategy'!$B$2, IF(B14<=10, Q14*'Fund Allocation Strategy'!$B$3, IF(B14<=15, Q14*'Fund Allocation Strategy'!$B$4, IF(B14<=20, Q14*'Fund Allocation Strategy'!$B$5, IF(B14<=25, Q14*'Fund Allocation Strategy'!$B$6, IF(B14<=30, Q14*'Fund Allocation Strategy'!$B$7, Q14*'Fund Allocation Strategy'!$B$8)))))) -> 171.632 | S14: =_xlfn.NORM.INV(RAND(),'Fund Allocation Strategy'!$B$11,'Fund Allocation Strategy'!$C$11) -> 0.03690931 | T14: =U13*S14+(R14*S14*0.5) -> 9.4398332 | U14: =U13+R14+T14 -> 351.01334 | V14: =IF(B14<=5, Q14*'Fund Allocation Strategy'!$C$2, IF(B14<=10, Q14*'Fund Allocation Strategy'!$C$3, IF(B14<=15, Q14*'Fund Allocation Strategy'!$C$4, IF(B14<=20, Q14*'Fund Allocation Strategy'!$C$5, IF(B14<=25, Q14*'Fund Allocation Strategy'!$C$6, IF(B14<=30, Q14*'Fund Allocation Strategy'!$C$7, Q14*'Fund Allocation Strategy'!$C$8)))))) -> 171.632 | W14: =_xlfn.NORM.INV(RAND(),'Fund Allocation Strategy'!$B$12,'Fund Allocation Strategy'!$C$12) -> 0.07018111 | X14: =Y13*W14 + (V14*W14*0.5) -> 18.144137 | Y14: =Y13+V14+X14 -> 362.4932 | Z14: =IF(B14<=5, Q14*'Fund Allocation Strategy'!$D$2, IF(B14<=10, Q14*'Fund Allocation Strategy'!$D$3, IF(B14<=15, Q14*'Fund Allocation Strategy'!$D$4, IF(B14<=20, Q14*'Fund Allocation Strategy'!$D$5, IF(B14<=25, Q14*'Fund Allocation Strategy'!$D$6, IF(B14<=30, Q14*'Fund Allocation Strategy'!$D$7, Q14*'Fund Allocation Strategy'!$D$8)))))) -> 1544.688 | AA14: =_xlfn.NORM.INV(RAND(),'Fund Allocation Strategy'!$B$13,'Fund Allocation Strategy'!$C$13) -> 0.10439445 | AB14: =AC13*AA14+(Z14*AA14*0.5) -> 245.36337 | AC14: =AC13+Z14+AB14 -> 3368.0562 | AD14: =IF(B14<=5, Q14*'Fund Allocation Strategy'!$E$2, IF(B14<=10, Q14*'Fund Allocation Strategy'!$E$3, IF(B14<=15, Q14*'Fund Allocation Strategy'!$E$4, IF(B14<=20, Q14*'Fund Allocation Strategy'!$E$5, IF(B14<=25, Q14*'Fund Allocation Strategy'!$E$6, IF(B14<=30, Q14*'Fund Allocation Strategy'!$E$7, Q14*'Fund Allocation Strategy'!$E$8)))))) -> 1029.792 | AE14: =_xlfn.NORM.INV(RAND(), 'Fund Allocation Strategy'!$B$14, 'Fund Allocation Strategy'!$C$14) + _xlfn.NORM.INV(RAND(), 'Fund Allocation Strategy'!$D$14,'Fund Allocation Strategy'!$E$14) -> 0.17614828 | AF14: =AM13*AE14+(AD14*AE14*0.5) -> 277.31435 | AG14: =IF(B14<=5, Q14*'Fund Allocation Strategy'!$F$2, IF(B14<=10, Q14*'Fund Allocation Strategy'!$F$3, IF(B14<=15, Q14*'Fund Allocation Strategy'!$F$4, IF(B14<=20, Q14*'Fund Allocation Strategy'!$F$5, IF(B14<=25, Q14*'Fund Allocation Strategy'!$F$6, IF(B14<=30, Q14*'Fund Allocation Strategy'!$F$7, Q14*'Fund Allocation Strategy'!$F$8)))))) -> 514.896 | AH14: =_xlfn.NORM.INV(RAND(),'Fund Allocation Strategy'!$B$15,'Fund Allocation Strategy'!$C$15) -> 0.19820668 | AI14: =AI13*AH14+(AG14*AH14*0.5) -> 61.002079 | AJ14: =AJ13+AG14+AI14 -> 1126.7146 | AK14: =IF(AM14<50000,0, AM14*0.015) -> 0 | AL14: =IF(AM14<50000,0,0.015) -> 0 | AM14: =AM13+AD14+AF14 -> 2366.5337 | AN14: =AM14-AK14 -> 2366.5337 | AO14: =IF(AV14 = 0, I14 * ( 'Lifestyle Strategy'!$B$2 + ('Lifestyle Strategy'!$C$2 - 'Lifestyle Strategy'!$B$2) * _xlfn.BETA.INV(RAND(), 'Lifestyle Strategy'!$F$2, 'Lifestyle Strategy'!$G$2) ),IF(AV14 = "", "",0)) -> 0 | AP14: =I14 * ( 'Lifestyle Strategy'!$B$3 + ('Lifestyle Strategy'!$C$3 - 'Lifestyle Strategy'!$B$3) * _xlfn.BETA.INV(RAND(), 'Lifestyle Strategy'!$F$3, 'Lifestyle Strategy'!$G$3) ) * IF(MOD(B14,5)=0, 1 + 'Lifestyle Strategy'!$M$4, 1 + 0.025) -> 7770.0435 | AQ14: =I14 * ( 'Lifestyle Strategy'!$B$4 + ('Lifestyle Strategy'!$C$4 - 'Lifestyle Strategy'!$B$4) * _xlfn.BETA.INV(RAND(), 'Lifestyle Strategy'!$F$4, 'Lifestyle Strategy'!$G$4) ) * IF(MOD(B14,5)=0, 1 + 'Lifestyle Strategy'!$M$4, 1 + 0.025) -> 5217.8035 | AR14: =I14 * ( 'Lifestyle Strategy'!$B$5 + ('Lifestyle Strategy'!$C$5 - 'Lifestyle Strategy'!$B$5) * _xlfn.BETA.INV(RAND(), 'Lifestyle Strategy'!$F$5, 'Lifestyle Strategy'!$G$5) ) * IF(MOD(B14,5)=0, 1 + 'Lifestyle Strategy'!$M$4, 1 + 0.025) -> 3034.2146 | AS14: =I14 * ( 'Lifestyle Strategy'!$B$6 + ('Lifestyle Strategy'!$C$6 - 'Lifestyle Strategy'!$B$6) * _xlfn.BETA.INV(RAND(), 'Lifestyle Strategy'!$F$6, 'Lifestyle Strategy'!$G$6) ) * IF(MOD(B14,5)=0, 1 + 'Lifestyle Strategy'!$M$4, 1 + 0.025) -> 2726.7948 | AT14: =I14 * ( 'Lifestyle Strategy'!$B$7 + ('Lifestyle Strategy'!$C$7 - 'Lifestyle Strategy'!$B$7) * _xlfn.BETA.INV(RAND(), 'Lifestyle Strategy'!$F$7, 'Lifestyle Strategy'!$G$7) ) * IF(MOD(B14,5)=0, 1 + 'Lifestyle Strategy'!$M$4, 1 + 0.025) -> 6270.7471 | AU14: =I14 * ( 'Lifestyle Strategy'!$B$8 + ('Lifestyle Strategy'!$C$8 - 'Lifestyle Strategy'!$B$8) * _xlfn.BETA.INV(RAND(), 'Lifestyle Strategy'!$F$8, 'Lifestyle Strategy'!$G$8) ) * IF(MOD(B14,5)=0, 1 + 'Lifestyle Strategy'!$M$4, 1 + 0.025) -> 3330.5888 | AV14: =IF('Lifestyle Strategy'!$B$14 = "Yes", IF(AND(B14>='Lifestyle Strategy'!$B$15, B14<'Lifestyle Strategy'!$B$16), 'Lifestyle Strategy'!$B$25, IF(B14>='Lifestyle Strategy'!$B$16, "", 0) ), 0 ) -> 17163.2 | AW14: =IF('Lifestyle Strategy'!$Q$4="No", 0, IF(AND(B14>='Lifestyle Strategy'!$Q$5, B14<'Lifestyle Strategy'!$Q$6), 'Lifestyle Strategy'!$Q$8 * (1.025^(B14-'Lifestyle Strategy'!$Q$5)) * (1.12^INT((B14-'Lifestyle Strategy'!$Q$5)/5)), 0 ) ) -> 0 | AX14: =IF(AO14 = "",0,AO14)+AP14+AQ14+AR14+AS14+AT14+AU14+AW14+IF(AV14 = "",0,AV14) -> 45513.392 | AY14: =IF(B14='Lifestyle Strategy'!$Q$10, MIN(AN14, 'Lifestyle Strategy'!$Q$11), 0) -> 0 | AZ14: =IF(B14='Lifestyle Strategy'!$Q$10, 'Lifestyle Strategy'!$Q$11, 0) -> 0 | BA14: =IF(B14='Lifestyle Strategy'!$Q$10, MAX(AZ14 - AY14, 0), 0) -> 0 | BB14: =U14+Y14+AC14+AJ14+AN14-AY14 -> 7574.811 | BC14: =TEXT(BB14/1000000, "[$$-en-US]0.00") & "M" -> $0.01M
B15: 2 | C15: 32 | D15: =IF(B15<>$B$5,D14*(1+_xlfn.NORM.INV(RAND(),$B$3,$B$4)),D14*(1+_xlfn.NORM.INV(RAND(),$B$3,$B$4))+D14*(1+_xlfn.NORM.INV(RAND(),$B$3,$B$4))) -> 73552.962 | E15: =D15-D14 -> 1495.7702 | F15: =E15/D14 -> 0.020758097 | G15: ='Tax rate cal'!C12 -> 14091.901 | H15: =$B$6*D15 -> 1228.3345 | I15: =D15-G15-H15 -> 58232.726 | J15: =MIN($E$2 + INT(B15/$E$3)*$E$4, $E$5) -> 0.04 | K15: 0.03 | L15: =IF(O15 = 0,0,'Lifestyle Strategy'!$Q$9) -> 0 | M15: =I15*J15 -> 2329.3091 | N15: =I15*K15 -> 1746.9818 | O15: =IF(AND('Lifestyle Strategy'!$Q$2="Yes", B15 >='Lifestyle Strategy'!$Q$3), I15 * 'Lifestyle Strategy'!$Q$9, 0 ) -> 0 | P15: =IF(B15<10,0,IF(MOD(B15, $E$6) = 0, $E$7, 0)) -> 0 | Q15: =M15+N15+O15+P15 -> 4076.2908 | R15: =IF(B15<=5, Q15*'Fund Allocation Strategy'!$B$2, IF(B15<=10, Q15*'Fund Allocation Strategy'!$B$3, IF(B15<=15, Q15*'Fund Allocation Strategy'!$B$4, IF(B15<=20, Q15*'Fund Allocation Strategy'!$B$5, IF(B15<=25, Q15*'Fund Allocation Strategy'!$B$6, IF(B15<=30, Q15*'Fund Allocation Strategy'!$B$7, Q15*'Fund Allocation Strategy'!$B$8)))))) -> 203.81454 | S15: =_xlfn.NORM.INV(RAND(),'Fund Allocation Strategy'!$B$11,'Fund Allocation Strategy'!$C$11) -> 0.036604432 | T15: =U14*S15+(R15*S15*0.5) -> 16.578902 | U15: =U14+R15+T15 -> 571.40679 | V15: =IF(B15<=5, Q15*'Fund Allocation Strategy'!$C$2, IF(B15<=10, Q15*'Fund Allocation Strategy'!$C$3, IF(B15<=15, Q15*'Fund Allocation Strategy'!$C$4, IF(B15<=20, Q15*'Fund Allocation Strategy'!$C$5, IF(B15<=25, Q15*'Fund Allocation Strategy'!$C$6, IF(B15<=30, Q15*'Fund Allocation Strategy'!$C$7, Q15*'Fund Allocation Strategy'!$C$8)))))) -> 203.81454 | W15: =_xlfn.NORM.INV(RAND(),'Fund Allocation Strategy'!$B$12,'Fund Allocation Strategy'!$C$12) -> 0.068860126 | X15: =Y14*W15 + (V15*W15*0.5) -> 31.978675 | Y15: =Y14+V15+X15 -> 598.28642 | Z15: =IF(B15<=5, Q15*'Fund Allocation Strategy'!$D$2, IF(B15<=10, Q15*'Fund Allocation Strategy'!$D$3, IF(B15<=15, Q15*'Fund Allocation Strategy'!$D$4, IF(B15<=20, Q15*'Fund Allocation Strategy'!$D$5, IF(B15<=25, Q15*'Fund Allocation Strategy'!$D$6, IF(B15<=30, Q15*'Fund Allocation Strategy'!$D$7, Q15*'Fund Allocation Strategy'!$D$8)))))) -> 1834.3309 | AA15: =_xlfn.NORM.INV(RAND(),'Fund Allocation Strategy'!$B$13,'Fund Allocation Strategy'!$C$13) -> 0.10158051 | AB15: =AC14*AA15+(Z15*AA15*0.5) -> 435.29502 | AC15: =AC14+Z15+AB15 -> 5637.6821 | AD15: =IF(B15<=5, Q15*'Fund Allocation Strategy'!$E$2, IF(B15<=10, Q15*'Fund Allocation Strategy'!$E$3, IF(B15<=15, Q15*'Fund Allocation Strategy'!$E$4, IF(B15<=20, Q15*'Fund Allocation Strategy'!$E$5, IF(B15<=25, Q15*'Fund Allocation Strategy'!$E$6, IF(B15<=30, Q15*'Fund Allocation Strategy'!$E$7, Q15*'Fund Allocation Strategy'!$E$8)))))) -> 1222.8873 | AE15: =_xlfn.NORM.INV(RAND(), 'Fund Allocation Strategy'!$B$14, 'Fund Allocation Strategy'!$C$14) + _xlfn.NORM.INV(RAND(), 'Fund Allocation Strategy'!$D$14,'Fund Allocation Strategy'!$E$14) -> 0.019662552 | AF15: =AM14*AE15+(AD15*AE15*0.5) -> 58.554633 | AG15: =IF(B15<=5, Q15*'Fund Allocation Strategy'!$F$2, IF(B15<=10, Q15*'Fund Allocation Strategy'!$F$3, IF(B15<=15, Q15*'Fund Allocation Strategy'!$F$4, IF(B15<=20, Q15*'Fund Allocation Strategy'!$F$5, IF(B15<=25, Q15*'Fund Allocation Strategy'!$F$6, IF(B15<=30, Q15*'Fund Allocation Strategy'!$F$7, Q15*'Fund Allocation Strategy'!$F$8)))))) -> 611.44363 | AH15: =_xlfn.NORM.INV(RAND(),'Fund Allocation Strategy'!$B$15,'Fund Allocation Strategy'!$C$15) -> 0.21323489 | AI15: =AI14*AH15+(AG15*AH15*0.5) -> 78.198329 | AJ15: =AJ14+AG15+AI15 -> 1816.3566 | AK15: =IF(AM15<50000,0, AM15*0.015) -> 0 | AL15: =IF(AM15<50000,0,0.015) -> 0 | AM15: =AM14+AD15+AF15 -> 3647.9756 | AN15: =AM15-AK15 -> 3647.9756 | AO15: =IF(AV15 = 0, I15 * ( 'Lifestyle Strategy'!$B$2 + ('Lifestyle Strategy'!$C$2 - 'Lifestyle Strategy'!$B$2) * _xlfn.BETA.INV(RAND(), 'Lifestyle Strategy'!$F$2, 'Lifestyle Strategy'!$G$2) ),IF(AV15 = "", "",0)) -> 0 | AP15: =I15 * ( 'Lifestyle Strategy'!$B$3 + ('Lifestyle Strategy'!$C$3 - 'Lifestyle Strategy'!$B$3) * _xlfn.BETA.INV(RAND(), 'Lifestyle Strategy'!$F$3, 'Lifestyle Strategy'!$G$3) ) * IF(MOD(B15,5)=0, 1 + 'Lifestyle Strategy'!$M$4, 1 + 0.025) -> 7966.7114 | AQ15: =I15 * ( 'Lifestyle Strategy'!$B$4 + ('Lifestyle Strategy'!$C$4 - 'Lifestyle Strategy'!$B$4) * _xlfn.BETA.INV(RAND(), 'Lifestyle Strategy'!$F$4, 'Lifestyle Strategy'!$G$4) ) * IF(MOD(B15,5)=0, 1 + 'Lifestyle Strategy'!$M$4, 1 + 0.025) -> 5865.7163 | AR15: =I15 * ( 'Lifestyle Strategy'!$B$5 + ('Lifestyle Strategy'!$C$5 - 'Lifestyle Strategy'!$B$5) * _xlfn.BETA.INV(RAND(), 'Lifestyle Strategy'!$F$5, 'Lifestyle Strategy'!$G$5) ) * IF(MOD(B15,5)=0, 1 + 'Lifestyle Strategy'!$M$4, 1 + 0.025) -> 3109.2717 | AS15: =I15 * ( 'Lifestyle Strategy'!$B$6 + ('Lifestyle Strategy'!$C$6 - 'Lifestyle Strategy'!$B$6) * _xlfn.BETA.INV(RAND(), 'Lifestyle Strategy'!$F$6, 'Lifestyle Strategy'!$G$6) ) * IF(MOD(B15,5)=0, 1 + 'Lifestyle Strategy'!$M$4, 1 + 0.025) -> 2980.6443 | AT15: =I15 * ( 'Lifestyle Strategy'!$B$7 + ('Lifestyle Strategy'!$C$7 - 'Lifestyle Strategy'!$B$7) * _xlfn.BETA.INV(RAND(), 'Lifestyle Strategy'!$F$7, 'Lifestyle Strategy'!$G$7) ) * IF(MOD(B15,5)=0, 1 + 'Lifestyle Strategy'!$M$4, 1 + 0.025) -> 5773.6762 | AU15: =I15 * ( 'Lifestyle Strategy'!$B$8 + ('Lifestyle Strategy'!$C$8 - 'Lifestyle Strategy'!$B$8) * _xlfn.BETA.INV(RAND(), 'Lifestyle Strategy'!$F$8, 'Lifestyle Strategy'!$G$8) ) * IF(MOD(B15,5)=0, 1 + 'Lifestyle Strategy'!$M$4, 1 + 0.025) -> 2248.2523 | AV15: =IF('Lifestyle Strategy'!$B$14 = "Yes", IF(AND(B15>='Lifestyle Strategy'!$B$15, B15<'Lifestyle Strategy'!$B$16), 'Lifestyle Strategy'!$B$25, IF(B15>='Lifestyle Strategy'!$B$16, "", 0) ), 0 ) -> 17163.2 | AW15: =IF('Lifestyle Strategy'!$Q$4="No", 0, IF(AND(B15>='Lifestyle Strategy'!$Q$5, B15<'Lifestyle Strategy'!$Q$6), 'Lifestyle Strategy'!$Q$8 * (1.025^(B15-'Lifestyle Strategy'!$Q$5)) * (1.12^INT((B15-'Lifestyle Strategy'!$Q$5)/5)), 0 ) ) -> 0 | AX15: =IF(AO15 = "",0,AO15)+AP15+AQ15+AR15+AS15+AT15+AU15+AW15+IF(AV15 = "",0,AV15) -> 45107.472 | AY15: =IF(B15='Lifestyle Strategy'!$Q$10, MIN(AN15, 'Lifestyle Strategy'!$Q$11), 0) -> 0 | AZ15: =IF(B15='Lifestyle Strategy'!$Q$10, 'Lifestyle Strategy'!$Q$11, 0) -> 0 | BA15: =IF(B15='Lifestyle Strategy'!$Q$10, MAX(AZ15 - AY15, 0), 0) -> 0 | BB15: =U15+Y15+AC15+AJ15+AN15-AY15 -> 12271.707 | BC15: =TEXT(BB15/1000000, "[$$-en-US]0.00") & "M" -> $0.01M | BQ15: Index | BR15: Post-Retirement Year | BS15: Age | BT15: Target Lifestyle Spending | BU15: Target Spending % of Corpus | BV15: Govt Support (NZ Super) | BW15: Withdrawal from Fund | BX15: Withdrawal % of Corpus | BY15: Annual Return Rate (%) | BZ15: Growth (NZD) | CA15: Remaining Corpus | CB15: Expected Corpus
B16: 3 | C16: 33 | D16: =IF(B16<>$B$5,D15*(1+_xlfn.NORM.INV(RAND(),$B$3,$B$4)),D15*(1+_xlfn.NORM.INV(RAND(),$B$3,$B$4))+D15*(1+_xlfn.NORM.INV(RAND(),$B$3,$B$4))) -> 76356.463 | E16: =D16-D15 -> 2803.5011 | F16: =E16/D15 -> 0.038115408 | G16: ='Tax rate cal'!C13 -> 14932.951 | H16: =$B$6*D16 -> 1275.1529 | I16: =D16-G16-H16 -> 60148.359 | J16: =MIN($E$2 + INT(B16/$E$3)*$E$4, $E$5) -> 0.04 | K16: 0.03 | L16: =IF(O16 = 0,0,'Lifestyle Strategy'!$Q$9) -> 0 | M16: =I16*J16 -> 2405.9343 | N16: =I16*K16 -> 1804.4508 | O16: =IF(AND('Lifestyle Strategy'!$Q$2="Yes", B16 >='Lifestyle Strategy'!$Q$3), I16 * 'Lifestyle Strategy'!$Q$9, 0 ) -> 0 | P16: =IF(B16<10,0,IF(MOD(B16, $E$6) = 0, $E$7, 0)) -> 0 | Q16: =M16+N16+O16+P16 -> 4210.3851 | R16: =IF(B16<=5, Q16*'Fund Allocation Strategy'!$B$2, IF(B16<=10, Q16*'Fund Allocation Strategy'!$B$3, IF(B16<=15, Q16*'Fund Allocation Strategy'!$B$4, IF(B16<=20, Q16*'Fund Allocation Strategy'!$B$5, IF(B16<=25, Q16*'Fund Allocation Strategy'!$B$6, IF(B16<=30, Q16*'Fund Allocation Strategy'!$B$7, Q16*'Fund Allocation Strategy'!$B$8)))))) -> 210.51926 | S16: =_xlfn.NORM.INV(RAND(),'Fund Allocation Strategy'!$B$11,'Fund Allocation Strategy'!$C$11) -> 0.037194842 | T16: =U15*S16+(R16*S16*0.5) -> 25.1685 | U16: =U15+R16+T16 -> 807.09454 | V16: =IF(B16<=5, Q16*'Fund Allocation Strategy'!$C$2, IF(B16<=10, Q16*'Fund Allocation Strategy'!$C$3, IF(B16<=15, Q16*'Fund Allocation Strategy'!$C$4, IF(B16<=20, Q16*'Fund Allocation Strategy'!$C$5, IF(B16<=25, Q16*'Fund Allocation Strategy'!$C$6, IF(B16<=30, Q16*'Fund Allocation Strategy'!$C$7, Q16*'Fund Allocation Strategy'!$C$8)))))) -> 210.51926 | W16: =_xlfn.NORM.INV(RAND(),'Fund Allocation Strategy'!$B$12,'Fund Allocation Strategy'!$C$12) -> 0.071244218 | X16: =Y15*W16 + (V16*W16*0.5) -> 50.123588 | Y16: =Y15+V16+X16 -> 858.92926 | Z16: =IF(B16<=5, Q16*'Fund Allocation Strategy'!$D$2, IF(B16<=10, Q16*'Fund Allocation Strategy'!$D$3, IF(B16<=15, Q16*'Fund Allocation Strategy'!$D$4, IF(B16<=20, Q16*'Fund Allocation Strategy'!$D$5, IF(B16<=25, Q16*'Fund Allocation Strategy'!$D$6, IF(B16<=30, Q16*'Fund Allocation Strategy'!$D$7, Q16*'Fund Allocation Strategy'!$D$8)))))) -> 1894.6733 | AA16: =_xlfn.NORM.INV(RAND(),'Fund Allocation Strategy'!$B$13,'Fund Allocation Strategy'!$C$13) -> 0.1043149 | AB16: =AC15*AA16+(Z16*AA16*0.5) -> 686.91554 | AC16: =AC15+Z16+AB16 -> 8219.2709 | AD16: =IF(B16<=5, Q16*'Fund Allocation Strategy'!$E$2, IF(B16<=10, Q16*'Fund Allocation Strategy'!$E$3, IF(B16<=15, Q16*'Fund Allocation Strategy'!$E$4, IF(B16<=20, Q16*'Fund Allocation Strategy'!$E$5, IF(B16<=25, Q16*'Fund Allocation Strategy'!$E$6, IF(B16<=30, Q16*'Fund Allocation Strategy'!$E$7, Q16*'Fund Allocation Strategy'!$E$8)))))) -> 1263.1155 | AE16: =_xlfn.NORM.INV(RAND(), 'Fund Allocation Strategy'!$B$14, 'Fund Allocation Strategy'!$C$14) + _xlfn.NORM.INV(RAND(), 'Fund Allocation Strategy'!$D$14,'Fund Allocation Strategy'!$E$14) -> 0.2836789 | AF16: =AM15*AE16+(AD16*AE16*0.5) -> 1214.0133 | AG16: =IF(B16<=5, Q16*'Fund Allocation Strategy'!$F$2, IF(B16<=10, Q16*'Fund Allocation Strategy'!$F$3, IF(B16<=15, Q16*'Fund Allocation Strategy'!$F$4, IF(B16<=20, Q16*'Fund Allocation Strategy'!$F$5, IF(B16<=25, Q16*'Fund Allocation Strategy'!$F$6, IF(B16<=30, Q16*'Fund Allocation Strategy'!$F$7, Q16*'Fund Allocation Strategy'!$F$8)))))) -> 631.55777 | AH16: =_xlfn.NORM.INV(RAND(),'Fund Allocation Strategy'!$B$15,'Fund Allocation Strategy'!$C$15) -> 0.20019019 | AI16: =AI15*AH16+(AG16*AH16*0.5) -> 78.870375 | AJ16: =AJ15+AG16+AI16 -> 2526.7847 | AK16: =IF(AM16<50000,0, AM16*0.015) -> 0 | AL16: =IF(AM16<50000,0,0.015) -> 0 | AM16: =AM15+AD16+AF16 -> 6125.1044 | AN16: =AM16-AK16 -> 6125.1044 | AO16: =IF(AV16 = 0, I16 * ( 'Lifestyle Strategy'!$B$2 + ('Lifestyle Strategy'!$C$2 - 'Lifestyle Strategy'!$B$2) * _xlfn.BETA.INV(RAND(), 'Lifestyle Strategy'!$F$2, 'Lifestyle Strategy'!$G$2) ),IF(AV16 = "", "",0)) -> 0 | AP16: =I16 * ( 'Lifestyle Strategy'!$B$3 + ('Lifestyle Strategy'!$C$3 - 'Lifestyle Strategy'!$B$3) * _xlfn.BETA.INV(RAND(), 'Lifestyle Strategy'!$F$3, 'Lifestyle Strategy'!$G$3) ) * IF(MOD(B16,5)=0, 1 + 'Lifestyle Strategy'!$M$4, 1 + 0.025) -> 8051.6206 | AQ16: =I16 * ( 'Lifestyle Strategy'!$B$4 + ('Lifestyle Strategy'!$C$4 - 'Lifestyle Strategy'!$B$4) * _xlfn.BETA.INV(RAND(), 'Lifestyle Strategy'!$F$4, 'Lifestyle Strategy'!$G$4) ) * IF(MOD(B16,5)=0, 1 + 'Lifestyle Strategy'!$M$4, 1 + 0.025) -> 3877.3029 | AR16: =I16 * ( 'Lifestyle Strategy'!$B$5 + ('Lifestyle Strategy'!$C$5 - 'Lifestyle Strategy'!$B$5) * _xlfn.BETA.INV(RAND(), 'Lifestyle Strategy'!$F$5, 'Lifestyle Strategy'!$G$5) ) * IF(MOD(B16,5)=0, 1 + 'Lifestyle Strategy'!$M$4, 1 + 0.025) -> 3318.1232 | AS16: =I16 * ( 'Lifestyle Strategy'!$B$6 + ('Lifestyle Strategy'!$C$6 - 'Lifestyle Strategy'!$B$6) * _xlfn.BETA.INV(RAND(), 'Lifestyle Strategy'!$F$6, 'Lifestyle Strategy'!$G$6) ) * IF(MOD(B16,5)=0, 1 + 'Lifestyle Strategy'!$M$4, 1 + 0.025) -> 3217.9259 | AT16: =I16 * ( 'Lifestyle Strategy'!$B$7 + ('Lifestyle Strategy'!$C$7 - 'Lifestyle Strategy'!$B$7) * _xlfn.BETA.INV(RAND(), 'Lifestyle Strategy'!$F$7, 'Lifestyle Strategy'!$G$7) ) * IF(MOD(B16,5)=0, 1 + 'Lifestyle Strategy'!$M$4, 1 + 0.025) -> 6811.4114 | AU16: =I16 * ( 'Lifestyle Strategy'!$B$8 + ('Lifestyle Strategy'!$C$8 - 'Lifestyle Strategy'!$B$8) * _xlfn.BETA.INV(RAND(), 'Lifestyle Strategy'!$F$8, 'Lifestyle Strategy'!$G$8) ) * IF(MOD(B16,5)=0, 1 + 'Lifestyle Strategy'!$M$4, 1 + 0.025) -> 3051.9537 | AV16: =IF('Lifestyle Strategy'!$B$14 = "Yes", IF(AND(B16>='Lifestyle Strategy'!$B$15, B16<'Lifestyle Strategy'!$B$16), 'Lifestyle Strategy'!$B$25, IF(B16>='Lifestyle Strategy'!$B$16, "", 0) ), 0 ) -> 17163.2 | AW16: =IF('Lifestyle Strategy'!$Q$4="No", 0, IF(AND(B16>='Lifestyle Strategy'!$Q$5, B16<'Lifestyle Strategy'!$Q$6), 'Lifestyle Strategy'!$Q$8 * (1.025^(B16-'Lifestyle Strategy'!$Q$5)) * (1.12^INT((B16-'Lifestyle Strategy'!$Q$5)/5)), 0 ) ) -> 0 | AX16: =IF(AO16 = "",0,AO16)+AP16+AQ16+AR16+AS16+AT16+AU16+AW16+IF(AV16 = "",0,AV16) -> 45491.538 | AY16: =IF(B16='Lifestyle Strategy'!$Q$10, MIN(AN16, 'Lifestyle Strategy'!$Q$11), 0) -> 0 | AZ16: =IF(B16='Lifestyle Strategy'!$Q$10, 'Lifestyle Strategy'!$Q$11, 0) -> 0 | BA16: =IF(B16='Lifestyle Strategy'!$Q$10, MAX(AZ16 - AY16, 0), 0) -> 0 | BB16: =U16+Y16+AC16+AJ16+AN16-AY16 -> 18537.184 | BC16: =TEXT(BB16/1000000, "[$$-en-US]0.00") & "M" -> $0.02M | BR16: 1 | BS16: 66 | BT16: =AX48 -> 143809.59 | BU16: =BT16/CA16 -> 0.029713728 | BV16: ='Lifestyle Strategy'!$M$22*(1+'Lifestyle Strategy'!$M$16)^('Lifestyle Strategy'!$M$23 + BR16-1) -> 54583.719 | BW16: =BT16-BV16 -> 89225.872 | BX16: =BW16/CA16 -> 0.018435719 | BY16: =IFERROR(_xlfn.NORM.INV(RAND(),'Lifestyle Strategy'!$M$27,'Lifestyle Strategy'!$M$28),0) -> 0.02602631 | BZ16: ='Lifestyle Strategy'!$M$26*BY16 -> 125031.21 | CA16: =('Pre-Retirement_cal'!$BB$48 + BZ16)-BW16 -> 4839836.7 | CB16: =IF('Post-Retirement_Cal'!$K16<0, ABS('Post-Retirement_Cal'!$K16),0) -> 0
B17: 4 | C17: 34 | D17: =IF(B17<>$B$5,D16*(1+_xlfn.NORM.INV(RAND(),$B$3,$B$4)),D16*(1+_xlfn.NORM.INV(RAND(),$B$3,$B$4))+D16*(1+_xlfn.NORM.INV(RAND(),$B$3,$B$4))) -> 79363.04 | E17: =D17-D16 -> 3006.5765 | F17: =E17/D16 -> 0.039375534 | G17: ='Tax rate cal'!C14 -> 15834.924 | H17: =$B$6*D17 -> 1325.3628 | I17: =D17-G17-H17 -> 62202.752 | J17: =MIN($E$2 + INT(B17/$E$3)*$E$4, $E$5) -> 0.05 | K17: 0.03 | L17: =IF(O17 = 0,0,'Lifestyle Strategy'!$Q$9) -> 0 | M17: =I17*J17 -> 3110.1376 | N17: =I17*K17 -> 1866.0826 | O17: =IF(AND('Lifestyle Strategy'!$Q$2="Yes", B17 >='Lifestyle Strategy'!$Q$3), I17 * 'Lifestyle Strategy'!$Q$9, 0 ) -> 0 | P17: =IF(B17<10,0,IF(MOD(B17, $E$6) = 0, $E$7, 0)) -> 0 | Q17: =M17+N17+O17+P17 -> 4976.2202 | R17: =IF(B17<=5, Q17*'Fund Allocation Strategy'!$B$2, IF(B17<=10, Q17*'Fund Allocation Strategy'!$B$3, IF(B17<=15, Q17*'Fund Allocation Strategy'!$B$4, IF(B17<=20, Q17*'Fund Allocation Strategy'!$B$5, IF(B17<=25, Q17*'Fund Allocation Strategy'!$B$6, IF(B17<=30, Q17*'Fund Allocation Strategy'!$B$7, Q17*'Fund Allocation Strategy'!$B$8)))))) -> 248.81101 | S17: =_xlfn.NORM.INV(RAND(),'Fund Allocation Strategy'!$B$11,'Fund Allocation Strategy'!$C$11) -> 0.037570372 | T17: =U16*S17+(R17*S17*0.5) -> 34.996803 | U17: =U16+R17+T17 -> 1090.9024 | V17: =IF(B17<=5, Q17*'Fund Allocation Strategy'!$C$2, IF(B17<=10, Q17*'Fund Allocation Strategy'!$C$3, IF(B17<=15, Q17*'Fund Allocation Strategy'!$C$4, IF(B17<=20, Q17*'Fund Allocation Strategy'!$C$5, IF(B17<=25, Q17*'Fund Allocation Strategy'!$C$6, IF(B17<=30, Q17*'Fund Allocation Strategy'!$C$7, Q17*'Fund Allocation Strategy'!$C$8)))))) -> 248.81101 | W17: =_xlfn.NORM.INV(RAND(),'Fund Allocation Strategy'!$B$12,'Fund Allocation Strategy'!$C$12) -> 0.070351282 | X17: =Y16*W17 + (V17*W17*0.5) -> 69.178861 | Y17: =Y16+V17+X17 -> 1176.9191 | Z17: =IF(B17<=5, Q17*'Fund Allocation Strategy'!$D$2, IF(B17<=10, Q17*'Fund Allocation Strategy'!$D$3, IF(B17<=15, Q17*'Fund Allocation Strategy'!$D$4, IF(B17<=20, Q17*'Fund Allocation Strategy'!$D$5, IF(B17<=25, Q17*'Fund Allocation Strategy'!$D$6, IF(B17<=30, Q17*'Fund Allocation Strategy'!$D$7, Q17*'Fund Allocation Strategy'!$D$8)))))) -> 2239.2991 | AA17: =_xlfn.NORM.INV(RAND(),'Fund Allocation Strategy'!$B$13,'Fund Allocation Strategy'!$C$13) -> 0.10462586 | AB17: =AC16*AA17+(Z17*AA17*0.5) -> 977.09262 | AC17: =AC16+Z17+AB17 -> 11435.663 | AD17: =IF(B17<=5, Q17*'Fund Allocation Strategy'!$E$2, IF(B17<=10, Q17*'Fund Allocation Strategy'!$E$3, IF(B17<=15, Q17*'Fund Allocation Strategy'!$E$4, IF(B17<=20, Q17*'Fund Allocation Strategy'!$E$5, IF(B17<=25, Q17*'Fund Allocation Strategy'!$E$6, IF(B17<=30, Q17*'Fund Allocation Strategy'!$E$7, Q17*'Fund Allocation Strategy'!$E$8)))))) -> 1492.8661 | AE17: =_xlfn.NORM.INV(RAND(), 'Fund Allocation Strategy'!$B$14, 'Fund Allocation Strategy'!$C$14) + _xlfn.NORM.INV(RAND(), 'Fund Allocation Strategy'!$D$14,'Fund Allocation Strategy'!$E$14) -> 0.5750956 | AF17: =AM16*AE17+(AD17*AE17*0.5) -> 3951.7909 | AG17: =IF(B17<=5, Q17*'Fund Allocation Strategy'!$F$2, IF(B17<=10, Q17*'Fund Allocation Strategy'!$F$3, IF(B17<=15, Q17*'Fund Allocation Strategy'!$F$4, IF(B17<=20, Q17*'Fund Allocation Strategy'!$F$5, IF(B17<=25, Q17*'Fund Allocation Strategy'!$F$6, IF(B17<=30, Q17*'Fund Allocation Strategy'!$F$7, Q17*'Fund Allocation Strategy'!$F$8)))))) -> 746.43303 | AH17: =_xlfn.NORM.INV(RAND(),'Fund Allocation Strategy'!$B$15,'Fund Allocation Strategy'!$C$15) -> 0.21176197 | AI17: =AI16*AH17+(AG17*AH17*0.5) -> 95.734809 | AJ17: =AJ16+AG17+AI17 -> 3368.9526 | AK17: =IF(AM17<50000,0, AM17*0.015) -> 0 | AL17: =IF(AM17<50000,0,0.015) -> 0 | AM17: =AM16+AD17+AF17 -> 11569.761 | AN17: =AM17-AK17 -> 11569.761 | AO17: =IF(AV17 = 0, I17 * ( 'Lifestyle Strategy'!$B$2 + ('Lifestyle Strategy'!$C$2 - 'Lifestyle Strategy'!$B$2) * _xlfn.BETA.INV(RAND(), 'Lifestyle Strategy'!$F$2, 'Lifestyle Strategy'!$G$2) ),IF(AV17 = "", "",0)) -> 0 | AP17: =I17 * ( 'Lifestyle Strategy'!$B$3 + ('Lifestyle Strategy'!$C$3 - 'Lifestyle Strategy'!$B$3) * _xlfn.BETA.INV(RAND(), 'Lifestyle Strategy'!$F$3, 'Lifestyle Strategy'!$G$3) ) * IF(MOD(B17,5)=0, 1 + 'Lifestyle Strategy'!$M$4, 1 + 0.025) -> 7483.0972 | AQ17: =I17 * ( 'Lifestyle Strategy'!$B$4 + ('Lifestyle Strategy'!$C$4 - 'Lifestyle Strategy'!$B$4) * _xlfn.BETA.INV(RAND(), 'Lifestyle Strategy'!$F$4, 'Lifestyle Strategy'!$G$4) ) * IF(MOD(B17,5)=0, 1 + 'Lifestyle Strategy'!$M$4, 1 + 0.025) -> 5212.5531 | AR17: =I17 * ( 'Lifestyle Strategy'!$B$5 + ('Lifestyle Strategy'!$C$5 - 'Lifestyle Strategy'!$B$5) * _xlfn.BETA.INV(RAND(), 'Lifestyle Strategy'!$F$5, 'Lifestyle Strategy'!$G$5) ) * IF(MOD(B17,5)=0, 1 + 'Lifestyle Strategy'!$M$4, 1 + 0.025) -> 3216.3509 | AS17: =I17 * ( 'Lifestyle Strategy'!$B$6 + ('Lifestyle Strategy'!$C$6 - 'Lifestyle Strategy'!$B$6) * _xlfn.BETA.INV(RAND(), 'Lifestyle Strategy'!$F$6, 'Lifestyle Strategy'!$G$6) ) * IF(MOD(B17,5)=0, 1 + 'Lifestyle Strategy'!$M$4, 1 + 0.025) -> 3290.1145 | AT17: =I17 * ( 'Lifestyle Strategy'!$B$7 + ('Lifestyle Strategy'!$C$7 - 'Lifestyle Strategy'!$B$7) * _xlfn.BETA.INV(RAND(), 'Lifestyle Strategy'!$F$7, 'Lifestyle Strategy'!$G$7) ) * IF(MOD(B17,5)=0, 1 + 'Lifestyle Strategy'!$M$4, 1 + 0.025) -> 6613.1781 | AU17: =I17 * ( 'Lifestyle Strategy'!$B$8 + ('Lifestyle Strategy'!$C$8 - 'Lifestyle Strategy'!$B$8) * _xlfn.BETA.INV(RAND(), 'Lifestyle Strategy'!$F$8, 'Lifestyle Strategy'!$G$8) ) * IF(MOD(B17,5)=0, 1 + 'Lifestyle Strategy'!$M$4, 1 + 0.025) -> 2995.5482 | AV17: =IF('Lifestyle Strategy'!$B$14 = "Yes", IF(AND(B17>='Lifestyle Strategy'!$B$15, B17<'Lifestyle Strategy'!$B$16), 'Lifestyle Strategy'!$B$25, IF(B17>='Lifestyle Strategy'!$B$16, "", 0) ), 0 ) -> 17163.2 | AW17: =IF('Lifestyle Strategy'!$Q$4="No", 0, IF(AND(B17>='Lifestyle Strategy'!$Q$5, B17<'Lifestyle Strategy'!$Q$6), 'Lifestyle Strategy'!$Q$8 * (1.025^(B17-'Lifestyle Strategy'!$Q$5)) * (1.12^INT((B17-'Lifestyle Strategy'!$Q$5)/5)), 0 ) ) -> 0 | AX17: =IF(AO17 = "",0,AO17)+AP17+AQ17+AR17+AS17+AT17+AU17+AW17+IF(AV17 = "",0,AV17) -> 45974.042 | AY17: =IF(B17='Lifestyle Strategy'!$Q$10, MIN(AN17, 'Lifestyle Strategy'!$Q$11), 0) -> 0 | AZ17: =IF(B17='Lifestyle Strategy'!$Q$10, 'Lifestyle Strategy'!$Q$11, 0) -> 0 | BA17: =IF(B17='Lifestyle Strategy'!$Q$10, MAX(AZ17 - AY17, 0), 0) -> 0 | BB17: =U17+Y17+AC17+AJ17+AN17-AY17 -> 28642.198 | BC17: =TEXT(BB17/1000000, "[$$-en-US]0.00") & "M" -> $0.03M | BR17: 2 | BS17: 67 | BT17: =IF(BS17<'Lifestyle Strategy'!$M$14, 0, 'Lifestyle Strategy'!$M$15 * (1 + 'Lifestyle Strategy'!$M$16)^(BS17-'Lifestyle Strategy'!$M$14) * (1 + IF(RAND() < (0.08 - 0.06) / (0.1 - 0.06), 0.06 + SQRT(RAND() * (0.08 - 0.06) * (0.1 - 0.06)), 0.1 - SQRT((1 - RAND()) * (0.1 - 0.08) * (0.1 - 0.06)) ))^INT((BS17-'Lifestyle Strategy'!$M$14)/5) ) -> 147404.83 | BU17: =BT17/CA17 -> 0.029954804 | BV17: ='Lifestyle Strategy'!$M$22*(1+'Lifestyle Strategy'!$M$16)^('Lifestyle Strategy'!$M$23 + BR17-1) -> 55948.312 | BW17: =BT17-BV17 -> 91456.519 | BX17: =BW17/CA17 -> 0.018585294 | BY17: =IFERROR(_xlfn.NORM.INV(RAND(),'Lifestyle Strategy'!$M$27,'Lifestyle Strategy'!$M$28),0) -> 0.035647396 | BZ17: =CA16*BY17 -> 172527.58 | CA17: =(CA16+BZ17)-BW17 -> 4920907.8 | CB17: =IF('Post-Retirement_Cal'!$K17<0, ABS('Post-Retirement_Cal'!$K17),0) -> 0
B18: 5 | C18: 35 | D18: =IF(B18<>$B$5,D17*(1+_xlfn.NORM.INV(RAND(),$B$3,$B$4)),D17*(1+_xlfn.NORM.INV(RAND(),$B$3,$B$4))+D17*(1+_xlfn.NORM.INV(RAND(),$B$3,$B$4))) -> 82334.238 | E18: =D18-D17 -> 2971.1982 | F18: =E18/D17 -> 0.03743806 | G18: ='Tax rate cal'!C15 -> 16794.736 | H18: =$B$6*D18 -> 1374.9818 | I18: =D18-G18-H18 -> 64164.52 | J18: =MIN($E$2 + INT(B18/$E$3)*$E$4, $E$5) -> 0.05 | K18: 0.03 | L18: =IF(O18 = 0,0,'Lifestyle Strategy'!$Q$9) -> 0 | M18: =I18*J18 -> 3208.226 | N18: =I18*K18 -> 1924.9356 | O18: =IF(AND('Lifestyle Strategy'!$Q$2="Yes", B18 >='Lifestyle Strategy'!$Q$3), I18 * 'Lifestyle Strategy'!$Q$9, 0 ) -> 0 | P18: =IF(B18<10,0,IF(MOD(B18, $E$6) = 0, $E$7, 0)) -> 0 | Q18: =M18+N18+O18+P18 -> 5133.1616 | R18: =IF(B18<=5, Q18*'Fund Allocation Strategy'!$B$2, IF(B18<=10, Q18*'Fund Allocation Strategy'!$B$3, IF(B18<=15, Q18*'Fund Allocation Strategy'!$B$4, IF(B18<=20, Q18*'Fund Allocation Strategy'!$B$5, IF(B18<=25, Q18*'Fund Allocation Strategy'!$B$6, IF(B18<=30, Q18*'Fund Allocation Strategy'!$B$7, Q18*'Fund Allocation Strategy'!$B$8)))))) -> 256.65808 | S18: =_xlfn.NORM.INV(RAND(),'Fund Allocation Strategy'!$B$11,'Fund Allocation Strategy'!$C$11) -> 0.037355341 | T18: =U17*S18+(R18*S18*0.5) -> 45.544805 | U18: =U17+R18+T18 -> 1393.1052 | V18: =IF(B18<=5, Q18*'Fund Allocation Strategy'!$C$2, IF(B18<=10, Q18*'Fund Allocation Strategy'!$C$3, IF(B18<=15, Q18*'Fund Allocation Strategy'!$C$4, IF(B18<=20, Q18*'Fund Allocation Strategy'!$C$5, IF(B18<=25, Q18*'Fund Allocation Strategy'!$C$6, IF(B18<=30, Q18*'Fund Allocation Strategy'!$C$7, Q18*'Fund Allocation Strategy'!$C$8)))))) -> 256.65808 | W18: =_xlfn.NORM.INV(RAND(),'Fund Allocation Strategy'!$B$12,'Fund Allocation Strategy'!$C$12) -> 0.070688407 | X18: =Y17*W18 + (V18*W18*0.5) -> 92.265914 | Y18: =Y17+V18+X18 -> 1525.8431 | Z18: =IF(B18<=5, Q18*'Fund Allocation Strategy'!$D$2, IF(B18<=10, Q18*'Fund Allocation Strategy'!$D$3, IF(B18<=15, Q18*'Fund Allocation Strategy'!$D$4, IF(B18<=20, Q18*'Fund Allocation Strategy'!$D$5, IF(B18<=25, Q18*'Fund Allocation Strategy'!$D$6, IF(B18<=30, Q18*'Fund Allocation Strategy'!$D$7, Q18*'Fund Allocation Strategy'!$D$8)))))) -> 2309.9227 | AA18: =_xlfn.NORM.INV(RAND(),'Fund Allocation Strategy'!$B$13,'Fund Allocation Strategy'!$C$13) -> 0.10638208 | AB18: =AC17*AA18+(Z18*AA18*0.5) -> 1339.4167 | AC18: =AC17+Z18+AB18 -> 15085.002 | AD18: =IF(B18<=5, Q18*'Fund Allocation Strategy'!$E$2, IF(B18<=10, Q18*'Fund Allocation Strategy'!$E$3, IF(B18<=15, Q18*'Fund Allocation Strategy'!$E$4, IF(B18<=20, Q18*'Fund Allocation Strategy'!$E$5, IF(B18<=25, Q18*'Fund Allocation Strategy'!$E$6, IF(B18<=30, Q18*'Fund Allocation Strategy'!$E$7, Q18*'Fund Allocation Strategy'!$E$8)))))) -> 1539.9485 | AE18: =_xlfn.NORM.INV(RAND(), 'Fund Allocation Strategy'!$B$14, 'Fund Allocation Strategy'!$C$14) + _xlfn.NORM.INV(RAND(), 'Fund Allocation Strategy'!$D$14,'Fund Allocation Strategy'!$E$14) -> 0.11889284 | AF18: =AM17*AE18+(AD18*AE18*0.5) -> 1467.1062 | AG18: =IF(B18<=5, Q18*'Fund Allocation Strategy'!$F$2, IF(B18<=10, Q18*'Fund Allocation Strategy'!$F$3, IF(B18<=15, Q18*'Fund Allocation Strategy'!$F$4, IF(B18<=20, Q18*'Fund Allocation Strategy'!$F$5, IF(B18<=25, Q18*'Fund Allocation Strategy'!$F$6, IF(B18<=30, Q18*'Fund Allocation Strategy'!$F$7, Q18*'Fund Allocation Strategy'!$F$8)))))) -> 769.97424 | AH18: =_xlfn.NORM.INV(RAND(),'Fund Allocation Strategy'!$B$15,'Fund Allocation Strategy'!$C$15) -> 0.21020493 | AI18: =AI17*AH18+(AG18*AH18*0.5) -> 101.05012 | AJ18: =AJ17+AG18+AI18 -> 4239.9769 | AK18: =IF(AM18<50000,0, AM18*0.015) -> 0 | AL18: =IF(AM18<50000,0,0.015) -> 0 | AM18: =AM17+AD18+AF18 -> 14576.816 | AN18: =AM18-AK18 -> 14576.816 | AO18: =IF(AV18 = 0, I18 * ( 'Lifestyle Strategy'!$B$2 + ('Lifestyle Strategy'!$C$2 - 'Lifestyle Strategy'!$B$2) * _xlfn.BETA.INV(RAND(), 'Lifestyle Strategy'!$F$2, 'Lifestyle Strategy'!$G$2) ),IF(AV18 = "", "",0)) -> 0 | AP18: =I18 * ( 'Lifestyle Strategy'!$B$3 + ('Lifestyle Strategy'!$C$3 - 'Lifestyle Strategy'!$B$3) * _xlfn.BETA.INV(RAND(), 'Lifestyle Strategy'!$F$3, 'Lifestyle Strategy'!$G$3) ) * IF(MOD(B18,5)=0, 1 + 'Lifestyle Strategy'!$M$4, 1 + 0.025) -> 9644.806 | AQ18: =I18 * ( 'Lifestyle Strategy'!$B$4 + ('Lifestyle Strategy'!$C$4 - 'Lifestyle Strategy'!$B$4) * _xlfn.BETA.INV(RAND(), 'Lifestyle Strategy'!$F$4, 'Lifestyle Strategy'!$G$4) ) * IF(MOD(B18,5)=0, 1 + 'Lifestyle Strategy'!$M$4, 1 + 0.025) -> 6398.9283 | AR18: =I18 * ( 'Lifestyle Strategy'!$B$5 + ('Lifestyle Strategy'!$C$5 - 'Lifestyle Strategy'!$B$5) * _xlfn.BETA.INV(RAND(), 'Lifestyle Strategy'!$F$5, 'Lifestyle Strategy'!$G$5) ) * IF(MOD(B18,5)=0, 1 + 'Lifestyle Strategy'!$M$4, 1 + 0.025) -> 3473.3699 | AS18: =I18 * ( 'Lifestyle Strategy'!$B$6 + ('Lifestyle Strategy'!$C$6 - 'Lifestyle Strategy'!$B$6) * _xlfn.BETA.INV(RAND(), 'Lifestyle Strategy'!$F$6, 'Lifestyle Strategy'!$G$6) ) * IF(MOD(B18,5)=0, 1 + 'Lifestyle Strategy'!$M$4, 1 + 0.025) -> 3688.1278 | AT18: =I18 * ( 'Lifestyle Strategy'!$B$7 + ('Lifestyle Strategy'!$C$7 - 'Lifestyle Strategy'!$B$7) * _xlfn.BETA.INV(RAND(), 'Lifestyle Strategy'!$F$7, 'Lifestyle Strategy'!$G$7) ) * IF(MOD(B18,5)=0, 1 + 'Lifestyle Strategy'!$M$4, 1 + 0.025) -> 7893.4044 | AU18: =I18 * ( 'Lifestyle Strategy'!$B$8 + ('Lifestyle Strategy'!$C$8 - 'Lifestyle Strategy'!$B$8) * _xlfn.BETA.INV(RAND(), 'Lifestyle Strategy'!$F$8, 'Lifestyle Strategy'!$G$8) ) * IF(MOD(B18,5)=0, 1 + 'Lifestyle Strategy'!$M$4, 1 + 0.025) -> 2385.8151 | AV18: =IF('Lifestyle Strategy'!$B$14 = "Yes", IF(AND(B18>='Lifestyle Strategy'!$B$15, B18<'Lifestyle Strategy'!$B$16), 'Lifestyle Strategy'!$B$25, IF(B18>='Lifestyle Strategy'!$B$16, "", 0) ), 0 ) -> 17163.2 | AW18: =IF('Lifestyle Strategy'!$Q$4="No", 0, IF(AND(B18>='Lifestyle Strategy'!$Q$5, B18<'Lifestyle Strategy'!$Q$6), 'Lifestyle Strategy'!$Q$8 * (1.025^(B18-'Lifestyle Strategy'!$Q$5)) * (1.12^INT((B18-'Lifestyle Strategy'!$Q$5)/5)), 0 ) ) -> 0 | AX18: =IF(AO18 = "",0,AO18)+AP18+AQ18+AR18+AS18+AT18+AU18+AW18+IF(AV18 = "",0,AV18) -> 50647.651 | AY18: =IF(B18='Lifestyle Strategy'!$Q$10, MIN(AN18, 'Lifestyle Strategy'!$Q$11), 0) -> 0 | AZ18: =IF(B18='Lifestyle Strategy'!$Q$10, 'Lifestyle Strategy'!$Q$11, 0) -> 0 | BA18: =IF(B18='Lifestyle Strategy'!$Q$10, MAX(AZ18 - AY18, 0), 0) -> 0 | BB18: =U18+Y18+AC18+AJ18+AN18-AY18 -> 36820.743 | BC18: =TEXT(BB18/1000000, "[$$-en-US]0.00") & "M" -> $0.04M | BR18: 3 | BS18: 68 | BT18: =IF(BS18<'Lifestyle Strategy'!$M$14, 0, 'Lifestyle Strategy'!$M$15 * (1 + 'Lifestyle Strategy'!$M$16)^(BS18-'Lifestyle Strategy'!$M$14) * (1 + IF(RAND() < (0.08 - 0.06) / (0.1 - 0.06), 0.06 + SQRT(RAND() * (0.08 - 0.06) * (0.1 - 0.06)), 0.1 - SQRT((1 - RAND()) * (0.1 - 0.08) * (0.1 - 0.06)) ))^INT((BS18-'Lifestyle Strategy'!$M$14)/5) ) -> 151089.95 | BU18: =BT18/CA18 -> 0.029952948 | BV18: ='Lifestyle Strategy'!$M$22*(1+'Lifestyle Strategy'!$M$16)^('Lifestyle Strategy'!$M$23 + BR18-1) -> 57347.02 | BW18: =BT18-BV18 -> 93742.932 | BX18: =BW18/CA18 -> 0.018584142 | BY18: =IFERROR(_xlfn.NORM.INV(RAND(),'Lifestyle Strategy'!$M$27,'Lifestyle Strategy'!$M$28),0) -> 0.044113463 | BZ18: =CA17*BY18 -> 217078.28 | CA18: =(CA17+BZ18)-BW18 -> 5044243.2 | CB18: =IF('Post-Retirement_Cal'!$K18<0, ABS('Post-Retirement_Cal'!$K18),0) -> 0
B19: 6 | C19: 36 | D19: =IF(B19<>$B$5,D18*(1+_xlfn.NORM.INV(RAND(),$B$3,$B$4)),D18*(1+_xlfn.NORM.INV(RAND(),$B$3,$B$4))+D18*(1+_xlfn.NORM.INV(RAND(),$B$3,$B$4))) -> 85475.278 | E19: =D19-D18 -> 3141.0404 | F19: =E19/D18 -> 0.038149869 | G19: ='Tax rate cal'!C16 -> 17831.279 | H19: =$B$6*D19 -> 1427.4371 | I19: =D19-G19-H19 -> 66216.562 | J19: =MIN($E$2 + INT(B19/$E$3)*$E$4, $E$5) -> 0.06 | K19: 0.03 | L19: =IF(O19 = 0,0,'Lifestyle Strategy'!$Q$9) -> 0 | M19: =I19*J19 -> 3972.9937 | N19: =I19*K19 -> 1986.4969 | O19: =IF(AND('Lifestyle Strategy'!$Q$2="Yes", B19 >='Lifestyle Strategy'!$Q$3), I19 * 'Lifestyle Strategy'!$Q$9, 0 ) -> 0 | P19: =IF(B19<10,0,IF(MOD(B19, $E$6) = 0, $E$7, 0)) -> 0 | Q19: =M19+N19+O19+P19 -> 5959.4906 | R19: =IF(B19<=5, Q19*'Fund Allocation Strategy'!$B$2, IF(B19<=10, Q19*'Fund Allocation Strategy'!$B$3, IF(B19<=15, Q19*'Fund Allocation Strategy'!$B$4, IF(B19<=20, Q19*'Fund Allocation Strategy'!$B$5, IF(B19<=25, Q19*'Fund Allocation Strategy'!$B$6, IF(B19<=30, Q19*'Fund Allocation Strategy'!$B$7, Q19*'Fund Allocation Strategy'!$B$8)))))) -> 595.94906 | S19: =_xlfn.NORM.INV(RAND(),'Fund Allocation Strategy'!$B$11,'Fund Allocation Strategy'!$C$11) -> 0.036709626 | T19: =U18*S19+(R19*S19*0.5) -> 62.078905 | U19: =U18+R19+T19 -> 2051.1332 | V19: =IF(B19<=5, Q19*'Fund Allocation Strategy'!$C$2, IF(B19<=10, Q19*'Fund Allocation Strategy'!$C$3, IF(B19<=15, Q19*'Fund Allocation Strategy'!$C$4, IF(B19<=20, Q19*'Fund Allocation Strategy'!$C$5, IF(B19<=25, Q19*'Fund Allocation Strategy'!$C$6, IF(B19<=30, Q19*'Fund Allocation Strategy'!$C$7, Q19*'Fund Allocation Strategy'!$C$8)))))) -> 744.93632 | W19: =_xlfn.NORM.INV(RAND(),'Fund Allocation Strategy'!$B$12,'Fund Allocation Strategy'!$C$12) -> 0.070584419 | X19: =Y18*W19 + (V19*W19*0.5) -> 133.9912 | Y19: =Y18+V19+X19 -> 2404.7706 | Z19: =IF(B19<=5, Q19*'Fund Allocation Strategy'!$D$2, IF(B19<=10, Q19*'Fund Allocation Strategy'!$D$3, IF(B19<=15, Q19*'Fund Allocation Strategy'!$D$4, IF(B19<=20, Q19*'Fund Allocation Strategy'!$D$5, IF(B19<=25, Q19*'Fund Allocation Strategy'!$D$6, IF(B19<=30, Q19*'Fund Allocation Strategy'!$D$7, Q19*'Fund Allocation Strategy'!$D$8)))))) -> 2383.7962 | AA19: =_xlfn.NORM.INV(RAND(),'Fund Allocation Strategy'!$B$13,'Fund Allocation Strategy'!$C$13) -> 0.1054413 | AB19: =AC18*AA19+(Z19*AA19*0.5) -> 1716.2575 | AC19: =AC18+Z19+AB19 -> 19185.056 | AD19: =IF(B19<=5, Q19*'Fund Allocation Strategy'!$E$2, IF(B19<=10, Q19*'Fund Allocation Strategy'!$E$3, IF(B19<=15, Q19*'Fund Allocation Strategy'!$E$4, IF(B19<=20, Q19*'Fund Allocation Strategy'!$E$5, IF(B19<=25, Q19*'Fund Allocation Strategy'!$E$6, IF(B19<=30, Q19*'Fund Allocation Strategy'!$E$7, Q19*'Fund Allocation Strategy'!$E$8)))))) -> 1489.8726 | AE19: =_xlfn.NORM.INV(RAND(), 'Fund Allocation Strategy'!$B$14, 'Fund Allocation Strategy'!$C$14) + _xlfn.NORM.INV(RAND(), 'Fund Allocation Strategy'!$D$14,'Fund Allocation Strategy'!$E$14) -> 0.18814095 | AF19: =AM18*AE19+(AD19*AE19*0.5) -> 2882.649 | AG19: =IF(B19<=5, Q19*'Fund Allocation Strategy'!$F$2, IF(B19<=10, Q19*'Fund Allocation Strategy'!$F$3, IF(B19<=15, Q19*'Fund Allocation Strategy'!$F$4, IF(B19<=20, Q19*'Fund Allocation Strategy'!$F$5, IF(B19<=25, Q19*'Fund Allocation Strategy'!$F$6, IF(B19<=30, Q19*'Fund Allocation Strategy'!$F$7, Q19*'Fund Allocation Strategy'!$F$8)))))) -> 744.93632 | AH19: =_xlfn.NORM.INV(RAND(),'Fund Allocation Strategy'!$B$15,'Fund Allocation Strategy'!$C$15) -> 0.2112588 | AI19: =AI18*AH19+(AG19*AH19*0.5) -> 100.0349 | AJ19: =AJ18+AG19+AI19 -> 5084.9481 | AK19: =IF(AM19<50000,0, AM19*0.015) -> 0 | AL19: =IF(AM19<50000,0,0.015) -> 0 | AM19: =AM18+AD19+AF19 -> 18949.338 | AN19: =AM19-AK19 -> 18949.338 | AO19: =IF(AV19 = 0, I19 * ( 'Lifestyle Strategy'!$B$2 + ('Lifestyle Strategy'!$C$2 - 'Lifestyle Strategy'!$B$2) * _xlfn.BETA.INV(RAND(), 'Lifestyle Strategy'!$F$2, 'Lifestyle Strategy'!$G$2) ),IF(AV19 = "", "",0)) -> 0 | AP19: =I19 * ( 'Lifestyle Strategy'!$B$3 + ('Lifestyle Strategy'!$C$3 - 'Lifestyle Strategy'!$B$3) * _xlfn.BETA.INV(RAND(), 'Lifestyle Strategy'!$F$3, 'Lifestyle Strategy'!$G$3) ) * IF(MOD(B19,5)=0, 1 + 'Lifestyle Strategy'!$M$4, 1 + 0.025) -> 7325.2228 | AQ19: =I19 * ( 'Lifestyle Strategy'!$B$4 + ('Lifestyle Strategy'!$C$4 - 'Lifestyle Strategy'!$B$4) * _xlfn.BETA.INV(RAND(), 'Lifestyle Strategy'!$F$4, 'Lifestyle Strategy'!$G$4) ) * IF(MOD(B19,5)=0, 1 + 'Lifestyle Strategy'!$M$4, 1 + 0.025) -> 4971.6273 | AR19: =I19 * ( 'Lifestyle Strategy'!$B$5 + ('Lifestyle Strategy'!$C$5 - 'Lifestyle Strategy'!$B$5) * _xlfn.BETA.INV(RAND(), 'Lifestyle Strategy'!$F$5, 'Lifestyle Strategy'!$G$5) ) * IF(MOD(B19,5)=0, 1 + 'Lifestyle Strategy'!$M$4, 1 + 0.025) -> 3492.0943 | AS19: =I19 * ( 'Lifestyle Strategy'!$B$6 + ('Lifestyle Strategy'!$C$6 - 'Lifestyle Strategy'!$B$6) * _xlfn.BETA.INV(RAND(), 'Lifestyle Strategy'!$F$6, 'Lifestyle Strategy'!$G$6) ) * IF(MOD(B19,5)=0, 1 + 'Lifestyle Strategy'!$M$4, 1 + 0.025) -> 3233.5167 | AT19: =I19 * ( 'Lifestyle Strategy'!$B$7 + ('Lifestyle Strategy'!$C$7 - 'Lifestyle Strategy'!$B$7) * _xlfn.BETA.INV(RAND(), 'Lifestyle Strategy'!$F$7, 'Lifestyle Strategy'!$G$7) ) * IF(MOD(B19,5)=0, 1 + 'Lifestyle Strategy'!$M$4, 1 + 0.025) -> 6096.6183 | AU19: =I19 * ( 'Lifestyle Strategy'!$B$8 + ('Lifestyle Strategy'!$C$8 - 'Lifestyle Strategy'!$B$8) * _xlfn.BETA.INV(RAND(), 'Lifestyle Strategy'!$F$8, 'Lifestyle Strategy'!$G$8) ) * IF(MOD(B19,5)=0, 1 + 'Lifestyle Strategy'!$M$4, 1 + 0.025) -> 4230.3433 | AV19: =IF('Lifestyle Strategy'!$B$14 = "Yes", IF(AND(B19>='Lifestyle Strategy'!$B$15, B19<'Lifestyle Strategy'!$B$16), 'Lifestyle Strategy'!$B$25, IF(B19>='Lifestyle Strategy'!$B$16, "", 0) ), 0 ) -> 17163.2 | AW19: =IF('Lifestyle Strategy'!$Q$4="No", 0, IF(AND(B19>='Lifestyle Strategy'!$Q$5, B19<'Lifestyle Strategy'!$Q$6), 'Lifestyle Strategy'!$Q$8 * (1.025^(B19-'Lifestyle Strategy'!$Q$5)) * (1.12^INT((B19-'Lifestyle Strategy'!$Q$5)/5)), 0 ) ) -> 0 | AX19: =IF(AO19 = "",0,AO19)+AP19+AQ19+AR19+AS19+AT19+AU19+AW19+IF(AV19 = "",0,AV19) -> 46512.623 | AY19: =IF(B19='Lifestyle Strategy'!$Q$10, MIN(AN19, 'Lifestyle Strategy'!$Q$11), 0) -> 0 | AZ19: =IF(B19='Lifestyle Strategy'!$Q$10, 'Lifestyle Strategy'!$Q$11, 0) -> 0 | BA19: =IF(B19='Lifestyle Strategy'!$Q$10, MAX(AZ19 - AY19, 0), 0) -> 0 | BB19: =U19+Y19+AC19+AJ19+AN19-AY19 -> 47675.246 | BC19: =TEXT(BB19/1000000, "[$$-en-US]0.00") & "M" -> $0.05M | BR19: 4 | BS19: 69 | BT19: =IF(BS19<'Lifestyle Strategy'!$M$14, 0, 'Lifestyle Strategy'!$M$15 * (1 + 'Lifestyle Strategy'!$M$16)^(BS19-'Lifestyle Strategy'!$M$14) * (1 + IF(RAND() < (0.08 - 0.06) / (0.1 - 0.06), 0.06 + SQRT(RAND() * (0.08 - 0.06) * (0.1 - 0.06)), 0.1 - SQRT((1 - RAND()) * (0.1 - 0.08) * (0.1 - 0.06)) ))^INT((BS19-'Lifestyle Strategy'!$M$14)/5) ) -> 154867.2 | BU19: =BT19/CA19 -> 0.029810999 | BV19: ='Lifestyle Strategy'!$M$22*(1+'Lifestyle Strategy'!$M$16)^('Lifestyle Strategy'!$M$23 + BR19-1) -> 58780.696 | BW19: =BT19-BV19 -> 96086.505 | BX19: =BW19/CA19 -> 0.01849607 | BY19: =IFERROR(_xlfn.NORM.INV(RAND(),'Lifestyle Strategy'!$M$27,'Lifestyle Strategy'!$M$28),0) -> 0.048929427 | BZ19: =CA18*BY19 -> 246811.92 | CA19: =(CA18+BZ19)-BW19 -> 5194968.6 | CB19: =IF('Post-Retirement_Cal'!$K19<0, ABS('Post-Retirement_Cal'!$K19),0) -> 0
B20: 7 | C20: 37 | D20: =IF(B20<>$B$5,D19*(1+_xlfn.NORM.INV(RAND(),$B$3,$B$4)),D19*(1+_xlfn.NORM.INV(RAND(),$B$3,$B$4))+D19*(1+_xlfn.NORM.INV(RAND(),$B$3,$B$4))) -> 89433.648 | E20: =D20-D19 -> 3958.3701 | F20: =E20/D19 -> 0.046310117 | G20: ='Tax rate cal'!C17 -> 19137.541 | H20: =$B$6*D20 -> 1493.5419 | I20: =D20-G20-H20 -> 68802.565 | J20: =MIN($E$2 + INT(B20/$E$3)*$E$4, $E$5) -> 0.06 | K20: 0.03 | L20: =IF(O20 = 0,0,'Lifestyle Strategy'!$Q$9) -> 0 | M20: =I20*J20 -> 4128.1539 | N20: =I20*K20 -> 2064.0769 | O20: =IF(AND('Lifestyle Strategy'!$Q$2="Yes", B20 >='Lifestyle Strategy'!$Q$3), I20 * 'Lifestyle Strategy'!$Q$9, 0 ) -> 0 | P20: =IF(B20<10,0,IF(MOD(B20, $E$6) = 0, $E$7, 0)) -> 0 | Q20: =M20+N20+O20+P20 -> 6192.2308 | R20: =IF(B20<=5, Q20*'Fund Allocation Strategy'!$B$2, IF(B20<=10, Q20*'Fund Allocation Strategy'!$B$3, IF(B20<=15, Q20*'Fund Allocation Strategy'!$B$4, IF(B20<=20, Q20*'Fund Allocation Strategy'!$B$5, IF(B20<=25, Q20*'Fund Allocation Strategy'!$B$6, IF(B20<=30, Q20*'Fund Allocation Strategy'!$B$7, Q20*'Fund Allocation Strategy'!$B$8)))))) -> 619.22308 | S20: =_xlfn.NORM.INV(RAND(),'Fund Allocation Strategy'!$B$11,'Fund Allocation Strategy'!$C$11) -> 0.037891515 | T20: =U19*S20+(R20*S20*0.5) -> 89.452196 | U20: =U19+R20+T20 -> 2759.8085 | V20: =IF(B20<=5, Q20*'Fund Allocation Strategy'!$C$2, IF(B20<=10, Q20*'Fund Allocation Strategy'!$C$3, IF(B20<=15, Q20*'Fund Allocation Strategy'!$C$4, IF(B20<=20, Q20*'Fund Allocation Strategy'!$C$5, IF(B20<=25, Q20*'Fund Allocation Strategy'!$C$6, IF(B20<=30, Q20*'Fund Allocation Strategy'!$C$7, Q20*'Fund Allocation Strategy'!$C$8)))))) -> 774.02886 | W20: =_xlfn.NORM.INV(RAND(),'Fund Allocation Strategy'!$B$12,'Fund Allocation Strategy'!$C$12) -> 0.068615264 | X20: =Y19*W20 + (V20*W20*0.5) -> 191.55907 | Y20: =Y19+V20+X20 -> 3370.3586 | Z20: =IF(B20<=5, Q20*'Fund Allocation Strategy'!$D$2, IF(B20<=10, Q20*'Fund Allocation Strategy'!$D$3, IF(B20<=15, Q20*'Fund Allocation Strategy'!$D$4, IF(B20<=20, Q20*'Fund Allocation Strategy'!$D$5, IF(B20<=25, Q20*'Fund Allocation Strategy'!$D$6, IF(B20<=30, Q20*'Fund Allocation Strategy'!$D$7, Q20*'Fund Allocation Strategy'!$D$8)))))) -> 2476.8923 | AA20: =_xlfn.NORM.INV(RAND(),'Fund Allocation Strategy'!$B$13,'Fund Allocation Strategy'!$C$13) -> 0.10079415 | AB20: =AC19*AA20+(Z20*AA20*0.5) -> 2058.5695 | AC20: =AC19+Z20+AB20 -> 23720.518 | AD20: =IF(B20<=5, Q20*'Fund Allocation Strategy'!$E$2, IF(B20<=10, Q20*'Fund Allocation Strategy'!$E$3, IF(B20<=15, Q20*'Fund Allocation Strategy'!$E$4, IF(B20<=20, Q20*'Fund Allocation Strategy'!$E$5, IF(B20<=25, Q20*'Fund Allocation Strategy'!$E$6, IF(B20<=30, Q20*'Fund Allocation Strategy'!$E$7, Q20*'Fund Allocation Strategy'!$E$8)))))) -> 1548.0577 | AE20: =_xlfn.NORM.INV(RAND(), 'Fund Allocation Strategy'!$B$14, 'Fund Allocation Strategy'!$C$14) + _xlfn.NORM.INV(RAND(), 'Fund Allocation Strategy'!$D$14,'Fund Allocation Strategy'!$E$14) -> 0.031419889 | AF20: =AM19*AE20+(AD20*AE20*0.5) -> 619.70599 | AG20: =IF(B20<=5, Q20*'Fund Allocation Strategy'!$F$2, IF(B20<=10, Q20*'Fund Allocation Strategy'!$F$3, IF(B20<=15, Q20*'Fund Allocation Strategy'!$F$4, IF(B20<=20, Q20*'Fund Allocation Strategy'!$F$5, IF(B20<=25, Q20*'Fund Allocation Strategy'!$F$6, IF(B20<=30, Q20*'Fund Allocation Strategy'!$F$7, Q20*'Fund Allocation Strategy'!$F$8)))))) -> 774.02886 | AH20: =_xlfn.NORM.INV(RAND(),'Fund Allocation Strategy'!$B$15,'Fund Allocation Strategy'!$C$15) -> 0.20247357 | AI20: =AI19*AH20+(AG20*AH20*0.5) -> 98.614616 | AJ20: =AJ19+AG20+AI20 -> 5957.5916 | AK20: =IF(AM20<50000,0, AM20*0.015) -> 0 | AL20: =IF(AM20<50000,0,0.015) -> 0 | AM20: =AM19+AD20+AF20 -> 21117.101 | AN20: =AM20-AK20 -> 21117.101 | AO20: =IF(AV20 = 0, I20 * ( 'Lifestyle Strategy'!$B$2 + ('Lifestyle Strategy'!$C$2 - 'Lifestyle Strategy'!$B$2) * _xlfn.BETA.INV(RAND(), 'Lifestyle Strategy'!$F$2, 'Lifestyle Strategy'!$G$2) ),IF(AV20 = "", "",0)) -> 0 | AP20: =I20 * ( 'Lifestyle Strategy'!$B$3 + ('Lifestyle Strategy'!$C$3 - 'Lifestyle Strategy'!$B$3) * _xlfn.BETA.INV(RAND(), 'Lifestyle Strategy'!$F$3, 'Lifestyle Strategy'!$G$3) ) * IF(MOD(B20,5)=0, 1 + 'Lifestyle Strategy'!$M$4, 1 + 0.025) -> 8863.4337 | AQ20: =I20 * ( 'Lifestyle Strategy'!$B$4 + ('Lifestyle Strategy'!$C$4 - 'Lifestyle Strategy'!$B$4) * _xlfn.BETA.INV(RAND(), 'Lifestyle Strategy'!$F$4, 'Lifestyle Strategy'!$G$4) ) * IF(MOD(B20,5)=0, 1 + 'Lifestyle Strategy'!$M$4, 1 + 0.025) -> 4854.9966 | AR20: =I20 * ( 'Lifestyle Strategy'!$B$5 + ('Lifestyle Strategy'!$C$5 - 'Lifestyle Strategy'!$B$5) * _xlfn.BETA.INV(RAND(), 'Lifestyle Strategy'!$F$5, 'Lifestyle Strategy'!$G$5) ) * IF(MOD(B20,5)=0, 1 + 'Lifestyle Strategy'!$M$4, 1 + 0.025) -> 3472.2914 | AS20: =I20 * ( 'Lifestyle Strategy'!$B$6 + ('Lifestyle Strategy'!$C$6 - 'Lifestyle Strategy'!$B$6) * _xlfn.BETA.INV(RAND(), 'Lifestyle Strategy'!$F$6, 'Lifestyle Strategy'!$G$6) ) * IF(MOD(B20,5)=0, 1 + 'Lifestyle Strategy'!$M$4, 1 + 0.025) -> 3908.8022 | AT20: =I20 * ( 'Lifestyle Strategy'!$B$7 + ('Lifestyle Strategy'!$C$7 - 'Lifestyle Strategy'!$B$7) * _xlfn.BETA.INV(RAND(), 'Lifestyle Strategy'!$F$7, 'Lifestyle Strategy'!$G$7) ) * IF(MOD(B20,5)=0, 1 + 'Lifestyle Strategy'!$M$4, 1 + 0.025) -> 7707.797 | AU20: =I20 * ( 'Lifestyle Strategy'!$B$8 + ('Lifestyle Strategy'!$C$8 - 'Lifestyle Strategy'!$B$8) * _xlfn.BETA.INV(RAND(), 'Lifestyle Strategy'!$F$8, 'Lifestyle Strategy'!$G$8) ) * IF(MOD(B20,5)=0, 1 + 'Lifestyle Strategy'!$M$4, 1 + 0.025) -> 3200.2233 | AV20: =IF('Lifestyle Strategy'!$B$14 = "Yes", IF(AND(B20>='Lifestyle Strategy'!$B$15, B20<'Lifestyle Strategy'!$B$16), 'Lifestyle Strategy'!$B$25, IF(B20>='Lifestyle Strategy'!$B$16, "", 0) ), 0 ) -> 17163.2 | AW20: =IF('Lifestyle Strategy'!$Q$4="No", 0, IF(AND(B20>='Lifestyle Strategy'!$Q$5, B20<'Lifestyle Strategy'!$Q$6), 'Lifestyle Strategy'!$Q$8 * (1.025^(B20-'Lifestyle Strategy'!$Q$5)) * (1.12^INT((B20-'Lifestyle Strategy'!$Q$5)/5)), 0 ) ) -> 0 | AX20: =IF(AO20 = "",0,AO20)+AP20+AQ20+AR20+AS20+AT20+AU20+AW20+IF(AV20 = "",0,AV20) -> 49170.744 | AY20: =IF(B20='Lifestyle Strategy'!$Q$10, MIN(AN20, 'Lifestyle Strategy'!$Q$11), 0) -> 0 | AZ20: =IF(B20='Lifestyle Strategy'!$Q$10, 'Lifestyle Strategy'!$Q$11, 0) -> 0 | BA20: =IF(B20='Lifestyle Strategy'!$Q$10, MAX(AZ20 - AY20, 0), 0) -> 0 | BB20: =U20+Y20+AC20+AJ20+AN20-AY20 -> 56925.378 | BC20: =TEXT(BB20/1000000, "[$$-en-US]0.00") & "M" -> $0.06M | BR20: 5 | BS20: 70 | BT20: =IF(BS20<'Lifestyle Strategy'!$M$14, 0, 'Lifestyle Strategy'!$M$15 * (1 + 'Lifestyle Strategy'!$M$16)^(BS20-'Lifestyle Strategy'!$M$14) * (1 + IF(RAND() < (0.08 - 0.06) / (0.1 - 0.06), 0.06 + SQRT(RAND() * (0.08 - 0.06) * (0.1 - 0.06)), 0.1 - SQRT((1 - RAND()) * (0.1 - 0.08) * (0.1 - 0.06)) ))^INT((BS20-'Lifestyle Strategy'!$M$14)/5) ) -> 158738.88 | BU20: =BT20/CA20 -> 0.030827979 | BV20: ='Lifestyle Strategy'!$M$22*(1+'Lifestyle Strategy'!$M$16)^('Lifestyle Strategy'!$M$23 + BR20-1) -> 60250.213 | BW20: =BT20-BV20 -> 98488.668 | BX20: =BW20/CA20 -> 0.019127051 | BY20: =IFERROR(_xlfn.NORM.INV(RAND(),'Lifestyle Strategy'!$M$27,'Lifestyle Strategy'!$M$28),0) -> 0.010144856 | BZ20: =CA19*BY20 -> 52702.211 | CA20: =(CA19+BZ20)-BW20 -> 5149182.1 | CB20: =IF('Post-Retirement_Cal'!$K20<0, ABS('Post-Retirement_Cal'!$K20),0) -> 0
B21: 8 | C21: 38 | D21: =IF(B21<>$B$5,D20*(1+_xlfn.NORM.INV(RAND(),$B$3,$B$4)),D20*(1+_xlfn.NORM.INV(RAND(),$B$3,$B$4))+D20*(1+_xlfn.NORM.INV(RAND(),$B$3,$B$4))) -> 93173.734 | E21: =D21-D20 -> 3740.0856 | F21: =E21/D20 -> 0.041819669 | G21: ='Tax rate cal'!C18 -> 20371.77 | H21: =$B$6*D21 -> 1556.0014 | I21: =D21-G21-H21 -> 71245.963 | J21: =MIN($E$2 + INT(B21/$E$3)*$E$4, $E$5) -> 0.07 | K21: 0.03 | L21: =IF(O21 = 0,0,'Lifestyle Strategy'!$Q$9) -> 0 | M21: =I21*J21 -> 4987.2174 | N21: =I21*K21 -> 2137.3789 | O21: =IF(AND('Lifestyle Strategy'!$Q$2="Yes", B21 >='Lifestyle Strategy'!$Q$3), I21 * 'Lifestyle Strategy'!$Q$9, 0 ) -> 0 | P21: =IF(B21<10,0,IF(MOD(B21, $E$6) = 0, $E$7, 0)) -> 0 | Q21: =M21+N21+O21+P21 -> 7124.5963 | R21: =IF(B21<=5, Q21*'Fund Allocation Strategy'!$B$2, IF(B21<=10, Q21*'Fund Allocation Strategy'!$B$3, IF(B21<=15, Q21*'Fund Allocation Strategy'!$B$4, IF(B21<=20, Q21*'Fund Allocation Strategy'!$B$5, IF(B21<=25, Q21*'Fund Allocation Strategy'!$B$6, IF(B21<=30, Q21*'Fund Allocation Strategy'!$B$7, Q21*'Fund Allocation Strategy'!$B$8)))))) -> 712.45963 | S21: =_xlfn.NORM.INV(RAND(),'Fund Allocation Strategy'!$B$11,'Fund Allocation Strategy'!$C$11) -> 0.037513694 | T21: =U20*S21+(R21*S21*0.5) -> 116.89411 | U21: =U20+R21+T21 -> 3589.1622 | V21: =IF(B21<=5, Q21*'Fund Allocation Strategy'!$C$2, IF(B21<=10, Q21*'Fund Allocation Strategy'!$C$3, IF(B21<=15, Q21*'Fund Allocation Strategy'!$C$4, IF(B21<=20, Q21*'Fund Allocation Strategy'!$C$5, IF(B21<=25, Q21*'Fund Allocation Strategy'!$C$6, IF(B21<=30, Q21*'Fund Allocation Strategy'!$C$7, Q21*'Fund Allocation Strategy'!$C$8)))))) -> 890.57454 | W21: =_xlfn.NORM.INV(RAND(),'Fund Allocation Strategy'!$B$12,'Fund Allocation Strategy'!$C$12) -> 0.071159411 | X21: =Y20*W21 + (V21*W21*0.5) -> 271.51911 | Y21: =Y20+V21+X21 -> 4532.4522 | Z21: =IF(B21<=5, Q21*'Fund Allocation Strategy'!$D$2, IF(B21<=10, Q21*'Fund Allocation Strategy'!$D$3, IF(B21<=15, Q21*'Fund Allocation Strategy'!$D$4, IF(B21<=20, Q21*'Fund Allocation Strategy'!$D$5, IF(B21<=25, Q21*'Fund Allocation Strategy'!$D$6, IF(B21<=30, Q21*'Fund Allocation Strategy'!$D$7, Q21*'Fund Allocation Strategy'!$D$8)))))) -> 2849.8385 | AA21: =_xlfn.NORM.INV(RAND(),'Fund Allocation Strategy'!$B$13,'Fund Allocation Strategy'!$C$13) -> 0.10255553 | AB21: =AC20*AA21+(Z21*AA21*0.5) -> 2578.8035 | AC21: =AC20+Z21+AB21 -> 29149.16 | AD21: =IF(B21<=5, Q21*'Fund Allocation Strategy'!$E$2, IF(B21<=10, Q21*'Fund Allocation Strategy'!$E$3, IF(B21<=15, Q21*'Fund Allocation Strategy'!$E$4, IF(B21<=20, Q21*'Fund Allocation Strategy'!$E$5, IF(B21<=25, Q21*'Fund Allocation Strategy'!$E$6, IF(B21<=30, Q21*'Fund Allocation Strategy'!$E$7, Q21*'Fund Allocation Strategy'!$E$8)))))) -> 1781.1491 | AE21: =_xlfn.NORM.INV(RAND(), 'Fund Allocation Strategy'!$B$14, 'Fund Allocation Strategy'!$C$14) + _xlfn.NORM.INV(RAND(), 'Fund Allocation Strategy'!$D$14,'Fund Allocation Strategy'!$E$14) -> 0.029861961 | AF21: =AM20*AE21+(AD21*AE21*0.5) -> 657.19235 | AG21: =IF(B21<=5, Q21*'Fund Allocation Strategy'!$F$2, IF(B21<=10, Q21*'Fund Allocation Strategy'!$F$3, IF(B21<=15, Q21*'Fund Allocation Strategy'!$F$4, IF(B21<=20, Q21*'Fund Allocation Strategy'!$F$5, IF(B21<=25, Q21*'Fund Allocation Strategy'!$F$6, IF(B21<=30, Q21*'Fund Allocation Strategy'!$F$7, Q21*'Fund Allocation Strategy'!$F$8)))))) -> 890.57454 | AH21: =_xlfn.NORM.INV(RAND(),'Fund Allocation Strategy'!$B$15,'Fund Allocation Strategy'!$C$15) -> 0.20840603 | AI21: =AI20*AH21+(AG21*AH21*0.5) -> 113.35243 | AJ21: =AJ20+AG21+AI21 -> 6961.5186 | AK21: =IF(AM21<50000,0, AM21*0.015) -> 0 | AL21: =IF(AM21<50000,0,0.015) -> 0 | AM21: =AM20+AD21+AF21 -> 23555.443 | AN21: =AM21-AK21 -> 23555.443 | AO21: =IF(AV21 = 0, I21 * ( 'Lifestyle Strategy'!$B$2 + ('Lifestyle Strategy'!$C$2 - 'Lifestyle Strategy'!$B$2) * _xlfn.BETA.INV(RAND(), 'Lifestyle Strategy'!$F$2, 'Lifestyle Strategy'!$G$2) ),IF(AV21 = "", "",0)) -> 0 | AP21: =I21 * ( 'Lifestyle Strategy'!$B$3 + ('Lifestyle Strategy'!$C$3 - 'Lifestyle Strategy'!$B$3) * _xlfn.BETA.INV(RAND(), 'Lifestyle Strategy'!$F$3, 'Lifestyle Strategy'!$G$3) ) * IF(MOD(B21,5)=0, 1 + 'Lifestyle Strategy'!$M$4, 1 + 0.025) -> 8506.6499 | AQ21: =I21 * ( 'Lifestyle Strategy'!$B$4 + ('Lifestyle Strategy'!$C$4 - 'Lifestyle Strategy'!$B$4) * _xlfn.BETA.INV(RAND(), 'Lifestyle Strategy'!$F$4, 'Lifestyle Strategy'!$G$4) ) * IF(MOD(B21,5)=0, 1 + 'Lifestyle Strategy'!$M$4, 1 + 0.025) -> 6364.7395 | AR21: =I21 * ( 'Lifestyle Strategy'!$B$5 + ('Lifestyle Strategy'!$C$5 - 'Lifestyle Strategy'!$B$5) * _xlfn.BETA.INV(RAND(), 'Lifestyle Strategy'!$F$5, 'Lifestyle Strategy'!$G$5) ) * IF(MOD(B21,5)=0, 1 + 'Lifestyle Strategy'!$M$4, 1 + 0.025) -> 3675.0257 | AS21: =I21 * ( 'Lifestyle Strategy'!$B$6 + ('Lifestyle Strategy'!$C$6 - 'Lifestyle Strategy'!$B$6) * _xlfn.BETA.INV(RAND(), 'Lifestyle Strategy'!$F$6, 'Lifestyle Strategy'!$G$6) ) * IF(MOD(B21,5)=0, 1 + 'Lifestyle Strategy'!$M$4, 1 + 0.025) -> 3916.2117 | AT21: =I21 * ( 'Lifestyle Strategy'!$B$7 + ('Lifestyle Strategy'!$C$7 - 'Lifestyle Strategy'!$B$7) * _xlfn.BETA.INV(RAND(), 'Lifestyle Strategy'!$F$7, 'Lifestyle Strategy'!$G$7) ) * IF(MOD(B21,5)=0, 1 + 'Lifestyle Strategy'!$M$4, 1 + 0.025) -> 7485.3796 | AU21: =I21 * ( 'Lifestyle Strategy'!$B$8 + ('Lifestyle Strategy'!$C$8 - 'Lifestyle Strategy'!$B$8) * _xlfn.BETA.INV(RAND(), 'Lifestyle Strategy'!$F$8, 'Lifestyle Strategy'!$G$8) ) * IF(MOD(B21,5)=0, 1 + 'Lifestyle Strategy'!$M$4, 1 + 0.025) -> 2254.6244 | AV21: =IF('Lifestyle Strategy'!$B$14 = "Yes", IF(AND(B21>='Lifestyle Strategy'!$B$15, B21<'Lifestyle Strategy'!$B$16), 'Lifestyle Strategy'!$B$25, IF(B21>='Lifestyle Strategy'!$B$16, "", 0) ), 0 ) -> 17163.2 | AW21: =IF('Lifestyle Strategy'!$Q$4="No", 0, IF(AND(B21>='Lifestyle Strategy'!$Q$5, B21<'Lifestyle Strategy'!$Q$6), 'Lifestyle Strategy'!$Q$8 * (1.025^(B21-'Lifestyle Strategy'!$Q$5)) * (1.12^INT((B21-'Lifestyle Strategy'!$Q$5)/5)), 0 ) ) -> 0 | AX21: =IF(AO21 = "",0,AO21)+AP21+AQ21+AR21+AS21+AT21+AU21+AW21+IF(AV21 = "",0,AV21) -> 49365.831 | AY21: =IF(B21='Lifestyle Strategy'!$Q$10, MIN(AN21, 'Lifestyle Strategy'!$Q$11), 0) -> 0 | AZ21: =IF(B21='Lifestyle Strategy'!$Q$10, 'Lifestyle Strategy'!$Q$11, 0) -> 0 | BA21: =IF(B21='Lifestyle Strategy'!$Q$10, MAX(AZ21 - AY21, 0), 0) -> 0 | BB21: =U21+Y21+AC21+AJ21+AN21-AY21 -> 67787.736 | BC21: =TEXT(BB21/1000000, "[$$-en-US]0.00") & "M" -> $0.07M | BR21: 6 | BS21: 71 | BT21: =IF(BS21<'Lifestyle Strategy'!$M$14, 0, 'Lifestyle Strategy'!$M$15 * (1 + 'Lifestyle Strategy'!$M$16)^(BS21-'Lifestyle Strategy'!$M$14) * (1 + IF(RAND() < (0.08 - 0.06) / (0.1 - 0.06), 0.06 + SQRT(RAND() * (0.08 - 0.06) * (0.1 - 0.06)), 0.1 - SQRT((1 - RAND()) * (0.1 - 0.08) * (0.1 - 0.06)) ))^INT((BS21-'Lifestyle Strategy'!$M$14)/5) ) -> 173354.14 | BU21: =BT21/CA21 -> 0.032765398 | BV21: ='Lifestyle Strategy'!$M$22*(1+'Lifestyle Strategy'!$M$16)^('Lifestyle Strategy'!$M$23 + BR21-1) -> 61756.468 | BW21: =BT21-BV21 -> 111597.67 | BX21: =BW21/CA21 -> 0.021092903 | BY21: =IFERROR(_xlfn.NORM.INV(RAND(),'Lifestyle Strategy'!$M$27,'Lifestyle Strategy'!$M$28),0) -> 0.049169769 | BZ21: =CA20*BY21 -> 253184.1 | CA21: =(CA20+BZ21)-BW21 -> 5290768.5 | CB21: =IF('Post-Retirement_Cal'!$K21<0, ABS('Post-Retirement_Cal'!$K21),0) -> 0
B22: 9 | C22: 39 | D22: =IF(B22<>$B$5,D21*(1+_xlfn.NORM.INV(RAND(),$B$3,$B$4)),D21*(1+_xlfn.NORM.INV(RAND(),$B$3,$B$4))+D21*(1+_xlfn.NORM.INV(RAND(),$B$3,$B$4))) -> 96201.393 | E22: =D22-D21 -> 3027.6592 | F22: =E22/D21 -> 0.032494772 | G22: ='Tax rate cal'!C19 -> 21370.897 | H22: =$B$6*D22 -> 1606.5633 | I22: =D22-G22-H22 -> 73223.933 | J22: =MIN($E$2 + INT(B22/$E$3)*$E$4, $E$5) -> 0.07 | K22: 0.03 | L22: =IF(O22 = 0,0,'Lifestyle Strategy'!$Q$9) -> 0 | M22: =I22*J22 -> 5125.6753 | N22: =I22*K22 -> 2196.718 | O22: =IF(AND('Lifestyle Strategy'!$Q$2="Yes", B22 >='Lifestyle Strategy'!$Q$3), I22 * 'Lifestyle Strategy'!$Q$9, 0 ) -> 0 | P22: =IF(B22<10,0,IF(MOD(B22, $E$6) = 0, $E$7, 0)) -> 0 | Q22: =M22+N22+O22+P22 -> 7322.3933 | R22: =IF(B22<=5, Q22*'Fund Allocation Strategy'!$B$2, IF(B22<=10, Q22*'Fund Allocation Strategy'!$B$3, IF(B22<=15, Q22*'Fund Allocation Strategy'!$B$4, IF(B22<=20, Q22*'Fund Allocation Strategy'!$B$5, IF(B22<=25, Q22*'Fund Allocation Strategy'!$B$6, IF(B22<=30, Q22*'Fund Allocation Strategy'!$B$7, Q22*'Fund Allocation Strategy'!$B$8)))))) -> 732.23933 | S22: =_xlfn.NORM.INV(RAND(),'Fund Allocation Strategy'!$B$11,'Fund Allocation Strategy'!$C$11) -> 0.038082448 | T22: =U21*S22+(R22*S22*0.5) -> 150.62681 | U22: =U21+R22+T22 -> 4472.0284 | V22: =IF(B22<=5, Q22*'Fund Allocation Strategy'!$C$2, IF(B22<=10, Q22*'Fund Allocation Strategy'!$C$3, IF(B22<=15, Q22*'Fund Allocation Strategy'!$C$4, IF(B22<=20, Q22*'Fund Allocation Strategy'!$C$5, IF(B22<=25, Q22*'Fund Allocation Strategy'!$C$6, IF(B22<=30, Q22*'Fund Allocation Strategy'!$C$7, Q22*'Fund Allocation Strategy'!$C$8)))))) -> 915.29916 | W22: =_xlfn.NORM.INV(RAND(),'Fund Allocation Strategy'!$B$12,'Fund Allocation Strategy'!$C$12) -> 0.070404553 | X22: =Y21*W22 + (V22*W22*0.5) -> 351.32588 | Y22: =Y21+V22+X22 -> 5799.0773 | Z22: =IF(B22<=5, Q22*'Fund Allocation Strategy'!$D$2, IF(B22<=10, Q22*'Fund Allocation Strategy'!$D$3, IF(B22<=15, Q22*'Fund Allocation Strategy'!$D$4, IF(B22<=20, Q22*'Fund Allocation Strategy'!$D$5, IF(B22<=25, Q22*'Fund Allocation Strategy'!$D$6, IF(B22<=30, Q22*'Fund Allocation Strategy'!$D$7, Q22*'Fund Allocation Strategy'!$D$8)))))) -> 2928.9573 | AA22: =_xlfn.NORM.INV(RAND(),'Fund Allocation Strategy'!$B$13,'Fund Allocation Strategy'!$C$13) -> 0.1048418 | AB22: =AC21*AA22+(Z22*AA22*0.5) -> 3209.589 | AC22: =AC21+Z22+AB22 -> 35287.706 | AD22: =IF(B22<=5, Q22*'Fund Allocation Strategy'!$E$2, IF(B22<=10, Q22*'Fund Allocation Strategy'!$E$3, IF(B22<=15, Q22*'Fund Allocation Strategy'!$E$4, IF(B22<=20, Q22*'Fund Allocation Strategy'!$E$5, IF(B22<=25, Q22*'Fund Allocation Strategy'!$E$6, IF(B22<=30, Q22*'Fund Allocation Strategy'!$E$7, Q22*'Fund Allocation Strategy'!$E$8)))))) -> 1830.5983 | AE22: =_xlfn.NORM.INV(RAND(), 'Fund Allocation Strategy'!$B$14, 'Fund Allocation Strategy'!$C$14) + _xlfn.NORM.INV(RAND(), 'Fund Allocation Strategy'!$D$14,'Fund Allocation Strategy'!$E$14) -> 0.050720878 | AF22: =AM21*AE22+(AD22*AE22*0.5) -> 1241.1775 | AG22: =IF(B22<=5, Q22*'Fund Allocation Strategy'!$F$2, IF(B22<=10, Q22*'Fund Allocation Strategy'!$F$3, IF(B22<=15, Q22*'Fund Allocation Strategy'!$F$4, IF(B22<=20, Q22*'Fund Allocation Strategy'!$F$5, IF(B22<=25, Q22*'Fund Allocation Strategy'!$F$6, IF(B22<=30, Q22*'Fund Allocation Strategy'!$F$7, Q22*'Fund Allocation Strategy'!$F$8)))))) -> 915.29916 | AH22: =_xlfn.NORM.INV(RAND(),'Fund Allocation Strategy'!$B$15,'Fund Allocation Strategy'!$C$15) -> 0.20980075 | AI22: =AI21*AH22+(AG22*AH22*0.5) -> 119.79665 | AJ22: =AJ21+AG22+AI22 -> 7996.6144 | AK22: =IF(AM22<50000,0, AM22*0.015) -> 0 | AL22: =IF(AM22<50000,0,0.015) -> 0 | AM22: =AM21+AD22+AF22 -> 26627.219 | AN22: =AM22-AK22 -> 26627.219 | AO22: =IF(AV22 = 0, I22 * ( 'Lifestyle Strategy'!$B$2 + ('Lifestyle Strategy'!$C$2 - 'Lifestyle Strategy'!$B$2) * _xlfn.BETA.INV(RAND(), 'Lifestyle Strategy'!$F$2, 'Lifestyle Strategy'!$G$2) ),IF(AV22 = "", "",0)) -> 0 | AP22: =I22 * ( 'Lifestyle Strategy'!$B$3 + ('Lifestyle Strategy'!$C$3 - 'Lifestyle Strategy'!$B$3) * _xlfn.BETA.INV(RAND(), 'Lifestyle Strategy'!$F$3, 'Lifestyle Strategy'!$G$3) ) * IF(MOD(B22,5)=0, 1 + 'Lifestyle Strategy'!$M$4, 1 + 0.025) -> 10305.332 | AQ22: =I22 * ( 'Lifestyle Strategy'!$B$4 + ('Lifestyle Strategy'!$C$4 - 'Lifestyle Strategy'!$B$4) * _xlfn.BETA.INV(RAND(), 'Lifestyle Strategy'!$F$4, 'Lifestyle Strategy'!$G$4) ) * IF(MOD(B22,5)=0, 1 + 'Lifestyle Strategy'!$M$4, 1 + 0.025) -> 4939.1489 | AR22: =I22 * ( 'Lifestyle Strategy'!$B$5 + ('Lifestyle Strategy'!$C$5 - 'Lifestyle Strategy'!$B$5) * _xlfn.BETA.INV(RAND(), 'Lifestyle Strategy'!$F$5, 'Lifestyle Strategy'!$G$5) ) * IF(MOD(B22,5)=0, 1 + 'Lifestyle Strategy'!$M$4, 1 + 0.025) -> 3910.2746 | AS22: =I22 * ( 'Lifestyle Strategy'!$B$6 + ('Lifestyle Strategy'!$C$6 - 'Lifestyle Strategy'!$B$6) * _xlfn.BETA.INV(RAND(), 'Lifestyle Strategy'!$F$6, 'Lifestyle Strategy'!$G$6) ) * IF(MOD(B22,5)=0, 1 + 'Lifestyle Strategy'!$M$4, 1 + 0.025) -> 3744.2983 | AT22: =I22 * ( 'Lifestyle Strategy'!$B$7 + ('Lifestyle Strategy'!$C$7 - 'Lifestyle Strategy'!$B$7) * _xlfn.BETA.INV(RAND(), 'Lifestyle Strategy'!$F$7, 'Lifestyle Strategy'!$G$7) ) * IF(MOD(B22,5)=0, 1 + 'Lifestyle Strategy'!$M$4, 1 + 0.025) -> 6723.1014 | AU22: =I22 * ( 'Lifestyle Strategy'!$B$8 + ('Lifestyle Strategy'!$C$8 - 'Lifestyle Strategy'!$B$8) * _xlfn.BETA.INV(RAND(), 'Lifestyle Strategy'!$F$8, 'Lifestyle Strategy'!$G$8) ) * IF(MOD(B22,5)=0, 1 + 'Lifestyle Strategy'!$M$4, 1 + 0.025) -> 2989.7758 | AV22: =IF('Lifestyle Strategy'!$B$14 = "Yes", IF(AND(B22>='Lifestyle Strategy'!$B$15, B22<'Lifestyle Strategy'!$B$16), 'Lifestyle Strategy'!$B$25, IF(B22>='Lifestyle Strategy'!$B$16, "", 0) ), 0 ) -> 17163.2 | AW22: =IF('Lifestyle Strategy'!$Q$4="No", 0, IF(AND(B22>='Lifestyle Strategy'!$Q$5, B22<'Lifestyle Strategy'!$Q$6), 'Lifestyle Strategy'!$Q$8 * (1.025^(B22-'Lifestyle Strategy'!$Q$5)) * (1.12^INT((B22-'Lifestyle Strategy'!$Q$5)/5)), 0 ) ) -> 0 | AX22: =IF(AO22 = "",0,AO22)+AP22+AQ22+AR22+AS22+AT22+AU22+AW22+IF(AV22 = "",0,AV22) -> 49775.131 | AY22: =IF(B22='Lifestyle Strategy'!$Q$10, MIN(AN22, 'Lifestyle Strategy'!$Q$11), 0) -> 0 | AZ22: =IF(B22='Lifestyle Strategy'!$Q$10, 'Lifestyle Strategy'!$Q$11, 0) -> 0 | BA22: =IF(B22='Lifestyle Strategy'!$Q$10, MAX(AZ22 - AY22, 0), 0) -> 0 | BB22: =U22+Y22+AC22+AJ22+AN22-AY22 -> 80182.645 | BC22: =TEXT(BB22/1000000, "[$$-en-US]0.00") & "M" -> $0.08M | BR22: 7 | BS22: 72 | BT22: =IF(BS22<'Lifestyle Strategy'!$M$14, 0, 'Lifestyle Strategy'!$M$15 * (1 + 'Lifestyle Strategy'!$M$16)^(BS22-'Lifestyle Strategy'!$M$14) * (1 + IF(RAND() < (0.08 - 0.06) / (0.1 - 0.06), 0.06 + SQRT(RAND() * (0.08 - 0.06) * (0.1 - 0.06)), 0.1 - SQRT((1 - RAND()) * (0.1 - 0.08) * (0.1 - 0.06)) ))^INT((BS22-'Lifestyle Strategy'!$M$14)/5) ) -> 179954.16 | BU22: =BT22/CA22 -> 0.03638597 | BV22: ='Lifestyle Strategy'!$M$22*(1+'Lifestyle Strategy'!$M$16)^('Lifestyle Strategy'!$M$23 + BR22-1) -> 63300.38 | BW22: =BT22-BV22 -> 116653.78 | BX22: =BW22/CA22 -> 0.023586901 | BY22: =IFERROR(_xlfn.NORM.INV(RAND(),'Lifestyle Strategy'!$M$27,'Lifestyle Strategy'!$M$28),0) -> -0.04317198 | BZ22: =CA21*BY22 -> -228412.95 | CA22: =(CA21+BZ22)-BW22 -> 4945701.8 | CB22: =IF('Post-Retirement_Cal'!$K22<0, ABS('Post-Retirement_Cal'!$K22),0) -> 0
B23: 10 | C23: 40 | D23: =IF(B23<>$B$5,D22*(1+_xlfn.NORM.INV(RAND(),$B$3,$B$4)),D22*(1+_xlfn.NORM.INV(RAND(),$B$3,$B$4))+D22*(1+_xlfn.NORM.INV(RAND(),$B$3,$B$4))) -> 198732.6 | E23: =D23-D22 -> 102531.2 | F23: =E23/D22 -> 1.0657975 | G23: ='Tax rate cal'!C20 -> 56060.15 | H23: =$B$6*D23 -> 3318.8343 | I23: =D23-G23-H23 -> 139353.61 | J23: =MIN($E$2 + INT(B23/$E$3)*$E$4, $E$5) -> 0.08 | K23: 0.03 | L23: =IF(O23 = 0,0,'Lifestyle Strategy'!$Q$9) -> 0 | M23: =I23*J23 -> 11148.289 | N23: =I23*K23 -> 4180.6083 | O23: =IF(AND('Lifestyle Strategy'!$Q$2="Yes", B23 >='Lifestyle Strategy'!$Q$3), I23 * 'Lifestyle Strategy'!$Q$9, 0 ) -> 0 | P23: =IF(B23<10,0,IF(MOD(B23, $E$6) = 0, $E$7, 0)) -> 10000 | Q23: =M23+N23+O23+P23 -> 25328.897 | R23: =IF(B23<=5, Q23*'Fund Allocation Strategy'!$B$2, IF(B23<=10, Q23*'Fund Allocation Strategy'!$B$3, IF(B23<=15, Q23*'Fund Allocation Strategy'!$B$4, IF(B23<=20, Q23*'Fund Allocation Strategy'!$B$5, IF(B23<=25, Q23*'Fund Allocation Strategy'!$B$6, IF(B23<=30, Q23*'Fund Allocation Strategy'!$B$7, Q23*'Fund Allocation Strategy'!$B$8)))))) -> 2532.8897 | S23: =_xlfn.NORM.INV(RAND(),'Fund Allocation Strategy'!$B$11,'Fund Allocation Strategy'!$C$11) -> 0.036272626 | T23: =U22*S23+(R23*S23*0.5) -> 208.14949 | U23: =U22+R23+T23 -> 7213.0676 | V23: =IF(B23<=5, Q23*'Fund Allocation Strategy'!$C$2, IF(B23<=10, Q23*'Fund Allocation Strategy'!$C$3, IF(B23<=15, Q23*'Fund Allocation Strategy'!$C$4, IF(B23<=20, Q23*'Fund Allocation Strategy'!$C$5, IF(B23<=25, Q23*'Fund Allocation Strategy'!$C$6, IF(B23<=30, Q23*'Fund Allocation Strategy'!$C$7, Q23*'Fund Allocation Strategy'!$C$8)))))) -> 3166.1122 | W23: =_xlfn.NORM.INV(RAND(),'Fund Allocation Strategy'!$B$12,'Fund Allocation Strategy'!$C$12) -> 0.070376812 | X23: =Y22*W23 + (V23*W23*0.5) -> 519.53101 | Y23: =Y22+V23+X23 -> 9484.7204 | Z23: =IF(B23<=5, Q23*'Fund Allocation Strategy'!$D$2, IF(B23<=10, Q23*'Fund Allocation Strategy'!$D$3, IF(B23<=15, Q23*'Fund Allocation Strategy'!$D$4, IF(B23<=20, Q23*'Fund Allocation Strategy'!$D$5, IF(B23<=25, Q23*'Fund Allocation Strategy'!$D$6, IF(B23<=30, Q23*'Fund Allocation Strategy'!$D$7, Q23*'Fund Allocation Strategy'!$D$8)))))) -> 10131.559 | AA23: =_xlfn.NORM.INV(RAND(),'Fund Allocation Strategy'!$B$13,'Fund Allocation Strategy'!$C$13) -> 0.1019035 | AB23: =AC22*AA23+(Z23*AA23*0.5) -> 4112.1614 | AC23: =AC22+Z23+AB23 -> 49531.426 | AD23: =IF(B23<=5, Q23*'Fund Allocation Strategy'!$E$2, IF(B23<=10, Q23*'Fund Allocation Strategy'!$E$3, IF(B23<=15, Q23*'Fund Allocation Strategy'!$E$4, IF(B23<=20, Q23*'Fund Allocation Strategy'!$E$5, IF(B23<=25, Q23*'Fund Allocation Strategy'!$E$6, IF(B23<=30, Q23*'Fund Allocation Strategy'!$E$7, Q23*'Fund Allocation Strategy'!$E$8)))))) -> 6332.2243 | AE23: =_xlfn.NORM.INV(RAND(), 'Fund Allocation Strategy'!$B$14, 'Fund Allocation Strategy'!$C$14) + _xlfn.NORM.INV(RAND(), 'Fund Allocation Strategy'!$D$14,'Fund Allocation Strategy'!$E$14) -> -0.21507914 | AF23: =AM22*AE23+(AD23*AE23*0.5) -> -6407.924 | AG23: =IF(B23<=5, Q23*'Fund Allocation Strategy'!$F$2, IF(B23<=10, Q23*'Fund Allocation Strategy'!$F$3, IF(B23<=15, Q23*'Fund Allocation Strategy'!$F$4, IF(B23<=20, Q23*'Fund Allocation Strategy'!$F$5, IF(B23<=25, Q23*'Fund Allocation Strategy'!$F$6, IF(B23<=30, Q23*'Fund Allocation Strategy'!$F$7, Q23*'Fund Allocation Strategy'!$F$8)))))) -> 3166.1122 | AH23: =_xlfn.NORM.INV(RAND(),'Fund Allocation Strategy'!$B$15,'Fund Allocation Strategy'!$C$15) -> 0.22188487 | AI23: =AI22*AH23+(AG23*AH23*0.5) -> 377.83726 | AJ23: =AJ22+AG23+AI23 -> 11540.564 | AK23: =IF(AM23<50000,0, AM23*0.015) -> 0 | AL23: =IF(AM23<50000,0,0.015) -> 0 | AM23: =AM22+AD23+AF23 -> 26551.519 | AN23: =AM23-AK23 -> 26551.519 | AO23: =IF(AV23 = 0, I23 * ( 'Lifestyle Strategy'!$B$2 + ('Lifestyle Strategy'!$C$2 - 'Lifestyle Strategy'!$B$2) * _xlfn.BETA.INV(RAND(), 'Lifestyle Strategy'!$F$2, 'Lifestyle Strategy'!$G$2) ),IF(AV23 = "", "",0)) -> 0 | AP23: =I23 * ( 'Lifestyle Strategy'!$B$3 + ('Lifestyle Strategy'!$C$3 - 'Lifestyle Strategy'!$B$3) * _xlfn.BETA.INV(RAND(), 'Lifestyle Strategy'!$F$3, 'Lifestyle Strategy'!$G$3) ) * IF(MOD(B23,5)=0, 1 + 'Lifestyle Strategy'!$M$4, 1 + 0.025) -> 19074.484 | AQ23: =I23 * ( 'Lifestyle Strategy'!$B$4 + ('Lifestyle Strategy'!$C$4 - 'Lifestyle Strategy'!$B$4) * _xlfn.BETA.INV(RAND(), 'Lifestyle Strategy'!$F$4, 'Lifestyle Strategy'!$G$4) ) * IF(MOD(B23,5)=0, 1 + 'Lifestyle Strategy'!$M$4, 1 + 0.025) -> 14329.113 | AR23: =I23 * ( 'Lifestyle Strategy'!$B$5 + ('Lifestyle Strategy'!$C$5 - 'Lifestyle Strategy'!$B$5) * _xlfn.BETA.INV(RAND(), 'Lifestyle Strategy'!$F$5, 'Lifestyle Strategy'!$G$5) ) * IF(MOD(B23,5)=0, 1 + 'Lifestyle Strategy'!$M$4, 1 + 0.025) -> 8219.248 | AS23: =I23 * ( 'Lifestyle Strategy'!$B$6 + ('Lifestyle Strategy'!$C$6 - 'Lifestyle Strategy'!$B$6) * _xlfn.BETA.INV(RAND(), 'Lifestyle Strategy'!$F$6, 'Lifestyle Strategy'!$G$6) ) * IF(MOD(B23,5)=0, 1 + 'Lifestyle Strategy'!$M$4, 1 + 0.025) -> 7369.579 | AT23: =I23 * ( 'Lifestyle Strategy'!$B$7 + ('Lifestyle Strategy'!$C$7 - 'Lifestyle Strategy'!$B$7) * _xlfn.BETA.INV(RAND(), 'Lifestyle Strategy'!$F$7, 'Lifestyle Strategy'!$G$7) ) * IF(MOD(B23,5)=0, 1 + 'Lifestyle Strategy'!$M$4, 1 + 0.025) -> 16500.515 | AU23: =I23 * ( 'Lifestyle Strategy'!$B$8 + ('Lifestyle Strategy'!$C$8 - 'Lifestyle Strategy'!$B$8) * _xlfn.BETA.INV(RAND(), 'Lifestyle Strategy'!$F$8, 'Lifestyle Strategy'!$G$8) ) * IF(MOD(B23,5)=0, 1 + 'Lifestyle Strategy'!$M$4, 1 + 0.025) -> 6149.0804 | AV23: =IF('Lifestyle Strategy'!$B$14 = "Yes", IF(AND(B23>='Lifestyle Strategy'!$B$15, B23<'Lifestyle Strategy'!$B$16), 'Lifestyle Strategy'!$B$25, IF(B23>='Lifestyle Strategy'!$B$16, "", 0) ), 0 ) -> 17163.2 | AW23: =IF('Lifestyle Strategy'!$Q$4="No", 0, IF(AND(B23>='Lifestyle Strategy'!$Q$5, B23<'Lifestyle Strategy'!$Q$6), 'Lifestyle Strategy'!$Q$8 * (1.025^(B23-'Lifestyle Strategy'!$Q$5)) * (1.12^INT((B23-'Lifestyle Strategy'!$Q$5)/5)), 0 ) ) -> 0 | AX23: =IF(AO23 = "",0,AO23)+AP23+AQ23+AR23+AS23+AT23+AU23+AW23+IF(AV23 = "",0,AV23) -> 88805.219 | AY23: =IF(B23='Lifestyle Strategy'!$Q$10, MIN(AN23, 'Lifestyle Strategy'!$Q$11), 0) -> 0 | AZ23: =IF(B23='Lifestyle Strategy'!$Q$10, 'Lifestyle Strategy'!$Q$11, 0) -> 0 | BA23: =IF(B23='Lifestyle Strategy'!$Q$10, MAX(AZ23 - AY23, 0), 0) -> 0 | BB23: =U23+Y23+AC23+AJ23+AN23-AY23 -> 104321.3 | BC23: =TEXT(BB23/1000000, "[$$-en-US]0.00") & "M" -> $0.10M | BR23: 8 | BS23: 73 | BT23: =IF(BS23<'Lifestyle Strategy'!$M$14, 0, 'Lifestyle Strategy'!$M$15 * (1 + 'Lifestyle Strategy'!$M$16)^(BS23-'Lifestyle Strategy'!$M$14) * (1 + IF(RAND() < (0.08 - 0.06) / (0.1 - 0.06), 0.06 + SQRT(RAND() * (0.08 - 0.06) * (0.1 - 0.06)), 0.1 - SQRT((1 - RAND()) * (0.1 - 0.08) * (0.1 - 0.06)) ))^INT((BS23-'Lifestyle Strategy'!$M$14)/5) ) -> 183239.97 | BU23: =BT23/CA23 -> 0.036407345 | BV23: ='Lifestyle Strategy'!$M$22*(1+'Lifestyle Strategy'!$M$16)^('Lifestyle Strategy'!$M$23 + BR23-1) -> 64882.889 | BW23: =BT23-BV23 -> 118357.08 | BX23: =BW23/CA23 -> 0.023515978 | BY23: =IFERROR(_xlfn.NORM.INV(RAND(),'Lifestyle Strategy'!$M$27,'Lifestyle Strategy'!$M$28),0) -> 0.041592622 | BZ23: =CA22*BY23 -> 205704.7 | CA23: =(CA22+BZ23)-BW23 -> 5033049.4 | CB23: =IF('Post-Retirement_Cal'!$K23<0, ABS('Post-Retirement_Cal'!$K23),0) -> 0
B24: 11 | C24: 41 | D24: =IF(B24<>$B$5,D23*(1+_xlfn.NORM.INV(RAND(),$B$3,$B$4)),D23*(1+_xlfn.NORM.INV(RAND(),$B$3,$B$4))+D23*(1+_xlfn.NORM.INV(RAND(),$B$3,$B$4))) -> 205504.8 | E24: =D24-D23 -> 6772.2059 | F24: =E24/D23 -> 0.034076976 | G24: ='Tax rate cal'!C21 -> 58701.31 | H24: =$B$6*D24 -> 3431.9302 | I24: =D24-G24-H24 -> 143371.56 | J24: =MIN($E$2 + INT(B24/$E$3)*$E$4, $E$5) -> 0.08 | K24: 0.03 | L24: =IF(O24 = 0,0,'Lifestyle Strategy'!$Q$9) -> 0 | M24: =I24*J24 -> 11469.725 | N24: =I24*K24 -> 4301.1468 | O24: =IF(AND('Lifestyle Strategy'!$Q$2="Yes", B24 >='Lifestyle Strategy'!$Q$3), I24 * 'Lifestyle Strategy'!$Q$9, 0 ) -> 0 | P24: =IF(B24<10,0,IF(MOD(B24, $E$6) = 0, $E$7, 0)) -> 0 | Q24: =M24+N24+O24+P24 -> 15770.872 | R24: =IF(B24<=5, Q24*'Fund Allocation Strategy'!$B$2, IF(B24<=10, Q24*'Fund Allocation Strategy'!$B$3, IF(B24<=15, Q24*'Fund Allocation Strategy'!$B$4, IF(B24<=20, Q24*'Fund Allocation Strategy'!$B$5, IF(B24<=25, Q24*'Fund Allocation Strategy'!$B$6, IF(B24<=30, Q24*'Fund Allocation Strategy'!$B$7, Q24*'Fund Allocation Strategy'!$B$8)))))) -> 2365.6308 | S24: =_xlfn.NORM.INV(RAND(),'Fund Allocation Strategy'!$B$11,'Fund Allocation Strategy'!$C$11) -> 0.037414347 | T24: =U23*S24+(R24*S24*0.5) -> 314.12648 | U24: =U23+R24+T24 -> 9892.8248 | V24: =IF(B24<=5, Q24*'Fund Allocation Strategy'!$C$2, IF(B24<=10, Q24*'Fund Allocation Strategy'!$C$3, IF(B24<=15, Q24*'Fund Allocation Strategy'!$C$4, IF(B24<=20, Q24*'Fund Allocation Strategy'!$C$5, IF(B24<=25, Q24*'Fund Allocation Strategy'!$C$6, IF(B24<=30, Q24*'Fund Allocation Strategy'!$C$7, Q24*'Fund Allocation Strategy'!$C$8)))))) -> 3154.1743 | W24: =_xlfn.NORM.INV(RAND(),'Fund Allocation Strategy'!$B$12,'Fund Allocation Strategy'!$C$12) -> 0.07270075 | X24: =Y23*W24 + (V24*W24*0.5) -> 804.2017 | Y24: =Y23+V24+X24 -> 13443.096 | Z24: =IF(B24<=5, Q24*'Fund Allocation Strategy'!$D$2, IF(B24<=10, Q24*'Fund Allocation Strategy'!$D$3, IF(B24<=15, Q24*'Fund Allocation Strategy'!$D$4, IF(B24<=20, Q24*'Fund Allocation Strategy'!$D$5, IF(B24<=25, Q24*'Fund Allocation Strategy'!$D$6, IF(B24<=30, Q24*'Fund Allocation Strategy'!$D$7, Q24*'Fund Allocation Strategy'!$D$8)))))) -> 5519.8051 | AA24: =_xlfn.NORM.INV(RAND(),'Fund Allocation Strategy'!$B$13,'Fund Allocation Strategy'!$C$13) -> 0.10314727 | AB24: =AC23*AA24+(Z24*AA24*0.5) -> 5393.7076 | AC24: =AC23+Z24+AB24 -> 60444.939 | AD24: =IF(B24<=5, Q24*'Fund Allocation Strategy'!$E$2, IF(B24<=10, Q24*'Fund Allocation Strategy'!$E$3, IF(B24<=15, Q24*'Fund Allocation Strategy'!$E$4, IF(B24<=20, Q24*'Fund Allocation Strategy'!$E$5, IF(B24<=25, Q24*'Fund Allocation Strategy'!$E$6, IF(B24<=30, Q24*'Fund Allocation Strategy'!$E$7, Q24*'Fund Allocation Strategy'!$E$8)))))) -> 3154.1743 | AE24: =_xlfn.NORM.INV(RAND(), 'Fund Allocation Strategy'!$B$14, 'Fund Allocation Strategy'!$C$14) + _xlfn.NORM.INV(RAND(), 'Fund Allocation Strategy'!$D$14,'Fund Allocation Strategy'!$E$14) -> 0.36657354 | AF24: =AM23*AE24+(AD24*AE24*0.5) -> 10311.203 | AG24: =IF(B24<=5, Q24*'Fund Allocation Strategy'!$F$2, IF(B24<=10, Q24*'Fund Allocation Strategy'!$F$3, IF(B24<=15, Q24*'Fund Allocation Strategy'!$F$4, IF(B24<=20, Q24*'Fund Allocation Strategy'!$F$5, IF(B24<=25, Q24*'Fund Allocation Strategy'!$F$6, IF(B24<=30, Q24*'Fund Allocation Strategy'!$F$7, Q24*'Fund Allocation Strategy'!$F$8)))))) -> 1577.0872 | AH24: =_xlfn.NORM.INV(RAND(),'Fund Allocation Strategy'!$B$15,'Fund Allocation Strategy'!$C$15) -> 0.20546912 | AI24: =AI23*AH24+(AG24*AH24*0.5) -> 239.65525 | AJ24: =AJ23+AG24+AI24 -> 13357.306 | AK24: =IF(AM24<50000,0, AM24*0.015) -> 0 | AL24: =IF(AM24<50000,0,0.015) -> 0 | AM24: =AM23+AD24+AF24 -> 40016.896 | AN24: =AM24-AK24 -> 40016.896 | AO24: =IF(AV24 = 0, I24 * ( 'Lifestyle Strategy'!$B$2 + ('Lifestyle Strategy'!$C$2 - 'Lifestyle Strategy'!$B$2) * _xlfn.BETA.INV(RAND(), 'Lifestyle Strategy'!$F$2, 'Lifestyle Strategy'!$G$2) ),IF(AV24 = "", "",0)) -> 0 | AP24: =I24 * ( 'Lifestyle Strategy'!$B$3 + ('Lifestyle Strategy'!$C$3 - 'Lifestyle Strategy'!$B$3) * _xlfn.BETA.INV(RAND(), 'Lifestyle Strategy'!$F$3, 'Lifestyle Strategy'!$G$3) ) * IF(MOD(B24,5)=0, 1 + 'Lifestyle Strategy'!$M$4, 1 + 0.025) -> 18441.111 | AQ24: =I24 * ( 'Lifestyle Strategy'!$B$4 + ('Lifestyle Strategy'!$C$4 - 'Lifestyle Strategy'!$B$4) * _xlfn.BETA.INV(RAND(), 'Lifestyle Strategy'!$F$4, 'Lifestyle Strategy'!$G$4) ) * IF(MOD(B24,5)=0, 1 + 'Lifestyle Strategy'!$M$4, 1 + 0.025) -> 12254.285 | AR24: =I24 * ( 'Lifestyle Strategy'!$B$5 + ('Lifestyle Strategy'!$C$5 - 'Lifestyle Strategy'!$B$5) * _xlfn.BETA.INV(RAND(), 'Lifestyle Strategy'!$F$5, 'Lifestyle Strategy'!$G$5) ) * IF(MOD(B24,5)=0, 1 + 'Lifestyle Strategy'!$M$4, 1 + 0.025) -> 7319.2194 | AS24: =I24 * ( 'Lifestyle Strategy'!$B$6 + ('Lifestyle Strategy'!$C$6 - 'Lifestyle Strategy'!$B$6) * _xlfn.BETA.INV(RAND(), 'Lifestyle Strategy'!$F$6, 'Lifestyle Strategy'!$G$6) ) * IF(MOD(B24,5)=0, 1 + 'Lifestyle Strategy'!$M$4, 1 + 0.025) -> 6973.3277 | AT24: =I24 * ( 'Lifestyle Strategy'!$B$7 + ('Lifestyle Strategy'!$C$7 - 'Lifestyle Strategy'!$B$7) * _xlfn.BETA.INV(RAND(), 'Lifestyle Strategy'!$F$7, 'Lifestyle Strategy'!$G$7) ) * IF(MOD(B24,5)=0, 1 + 'Lifestyle Strategy'!$M$4, 1 + 0.025) -> 15802.85 | AU24: =I24 * ( 'Lifestyle Strategy'!$B$8 + ('Lifestyle Strategy'!$C$8 - 'Lifestyle Strategy'!$B$8) * _xlfn.BETA.INV(RAND(), 'Lifestyle Strategy'!$F$8, 'Lifestyle Strategy'!$G$8) ) * IF(MOD(B24,5)=0, 1 + 'Lifestyle Strategy'!$M$4, 1 + 0.025) -> 5701.1946 | AV24: =IF('Lifestyle Strategy'!$B$14 = "Yes", IF(AND(B24>='Lifestyle Strategy'!$B$15, B24<'Lifestyle Strategy'!$B$16), 'Lifestyle Strategy'!$B$25, IF(B24>='Lifestyle Strategy'!$B$16, "", 0) ), 0 ) -> 17163.2 | AW24: =IF('Lifestyle Strategy'!$Q$4="No", 0, IF(AND(B24>='Lifestyle Strategy'!$Q$5, B24<'Lifestyle Strategy'!$Q$6), 'Lifestyle Strategy'!$Q$8 * (1.025^(B24-'Lifestyle Strategy'!$Q$5)) * (1.12^INT((B24-'Lifestyle Strategy'!$Q$5)/5)), 0 ) ) -> 0 | AX24: =IF(AO24 = "",0,AO24)+AP24+AQ24+AR24+AS24+AT24+AU24+AW24+IF(AV24 = "",0,AV24) -> 83655.187 | AY24: =IF(B24='Lifestyle Strategy'!$Q$10, MIN(AN24, 'Lifestyle Strategy'!$Q$11), 0) -> 0 | AZ24: =IF(B24='Lifestyle Strategy'!$Q$10, 'Lifestyle Strategy'!$Q$11, 0) -> 0 | BA24: =IF(B24='Lifestyle Strategy'!$Q$10, MAX(AZ24 - AY24, 0), 0) -> 0 | BB24: =U24+Y24+AC24+AJ24+AN24-AY24 -> 137155.06 | BC24: =TEXT(BB24/1000000, "[$$-en-US]0.00") & "M" -> $0.14M | BR24: 9 | BS24: 74 | BT24: =IF(BS24<'Lifestyle Strategy'!$M$14, 0, 'Lifestyle Strategy'!$M$15 * (1 + 'Lifestyle Strategy'!$M$16)^(BS24-'Lifestyle Strategy'!$M$14) * (1 + IF(RAND() < (0.08 - 0.06) / (0.1 - 0.06), 0.06 + SQRT(RAND() * (0.08 - 0.06) * (0.1 - 0.06)), 0.1 - SQRT((1 - RAND()) * (0.1 - 0.08) * (0.1 - 0.06)) ))^INT((BS24-'Lifestyle Strategy'!$M$14)/5) ) -> 189750.74 | BU24: =BT24/CA24 -> 0.037238801 | BV24: ='Lifestyle Strategy'!$M$22*(1+'Lifestyle Strategy'!$M$16)^('Lifestyle Strategy'!$M$23 + BR24-1) -> 66504.962 | BW24: =BT24-BV24 -> 123245.78 | BX24: =BW24/CA24 -> 0.024187126 | BY24: =IFERROR(_xlfn.NORM.INV(RAND(),'Lifestyle Strategy'!$M$27,'Lifestyle Strategy'!$M$28),0) -> 0.036897686 | BZ24: =CA23*BY24 -> 185707.88 | CA24: =(CA23+BZ24)-BW24 -> 5095511.5 | CB24: =IF('Post-Retirement_Cal'!$K24<0, ABS('Post-Retirement_Cal'!$K24),0) -> 0
B25: 12 | C25: 42 | D25: =IF(B25<>$B$5,D24*(1+_xlfn.NORM.INV(RAND(),$B$3,$B$4)),D24*(1+_xlfn.NORM.INV(RAND(),$B$3,$B$4))+D24*(1+_xlfn.NORM.INV(RAND(),$B$3,$B$4))) -> 215082.48 | E25: =D25-D24 -> 9577.6792 | F25: =E25/D24 -> 0.046605623 | G25: ='Tax rate cal'!C22 -> 62436.605 | H25: =$B$6*D25 -> 3591.8774 | I25: =D25-G25-H25 -> 149054 | J25: =MIN($E$2 + INT(B25/$E$3)*$E$4, $E$5) -> 0.09 | K25: 0.03 | L25: =IF(O25 = 0,0,'Lifestyle Strategy'!$Q$9) -> 0 | M25: =I25*J25 -> 13414.86 | N25: =I25*K25 -> 4471.6199 | O25: =IF(AND('Lifestyle Strategy'!$Q$2="Yes", B25 >='Lifestyle Strategy'!$Q$3), I25 * 'Lifestyle Strategy'!$Q$9, 0 ) -> 0 | P25: =IF(B25<10,0,IF(MOD(B25, $E$6) = 0, $E$7, 0)) -> 0 | Q25: =M25+N25+O25+P25 -> 17886.48 | R25: =IF(B25<=5, Q25*'Fund Allocation Strategy'!$B$2, IF(B25<=10, Q25*'Fund Allocation Strategy'!$B$3, IF(B25<=15, Q25*'Fund Allocation Strategy'!$B$4, IF(B25<=20, Q25*'Fund Allocation Strategy'!$B$5, IF(B25<=25, Q25*'Fund Allocation Strategy'!$B$6, IF(B25<=30, Q25*'Fund Allocation Strategy'!$B$7, Q25*'Fund Allocation Strategy'!$B$8)))))) -> 2682.972 | S25: =_xlfn.NORM.INV(RAND(),'Fund Allocation Strategy'!$B$11,'Fund Allocation Strategy'!$C$11) -> 0.037550834 | T25: =U24*S25+(R25*S25*0.5) -> 421.85774 | U25: =U24+R25+T25 -> 12997.655 | V25: =IF(B25<=5, Q25*'Fund Allocation Strategy'!$C$2, IF(B25<=10, Q25*'Fund Allocation Strategy'!$C$3, IF(B25<=15, Q25*'Fund Allocation Strategy'!$C$4, IF(B25<=20, Q25*'Fund Allocation Strategy'!$C$5, IF(B25<=25, Q25*'Fund Allocation Strategy'!$C$6, IF(B25<=30, Q25*'Fund Allocation Strategy'!$C$7, Q25*'Fund Allocation Strategy'!$C$8)))))) -> 3577.296 | W25: =_xlfn.NORM.INV(RAND(),'Fund Allocation Strategy'!$B$12,'Fund Allocation Strategy'!$C$12) -> 0.069498048 | X25: =Y24*W25 + (V25*W25*0.5) -> 1058.5765 | Y25: =Y24+V25+X25 -> 18078.969 | Z25: =IF(B25<=5, Q25*'Fund Allocation Strategy'!$D$2, IF(B25<=10, Q25*'Fund Allocation Strategy'!$D$3, IF(B25<=15, Q25*'Fund Allocation Strategy'!$D$4, IF(B25<=20, Q25*'Fund Allocation Strategy'!$D$5, IF(B25<=25, Q25*'Fund Allocation Strategy'!$D$6, IF(B25<=30, Q25*'Fund Allocation Strategy'!$D$7, Q25*'Fund Allocation Strategy'!$D$8)))))) -> 6260.2679 | AA25: =_xlfn.NORM.INV(RAND(),'Fund Allocation Strategy'!$B$13,'Fund Allocation Strategy'!$C$13) -> 0.1057706 | AB25: =AC24*AA25+(Z25*AA25*0.5) -> 6724.3739 | AC25: =AC24+Z25+AB25 -> 73429.581 | AD25: =IF(B25<=5, Q25*'Fund Allocation Strategy'!$E$2, IF(B25<=10, Q25*'Fund Allocation Strategy'!$E$3, IF(B25<=15, Q25*'Fund Allocation Strategy'!$E$4, IF(B25<=20, Q25*'Fund Allocation Strategy'!$E$5, IF(B25<=25, Q25*'Fund Allocation Strategy'!$E$6, IF(B25<=30, Q25*'Fund Allocation Strategy'!$E$7, Q25*'Fund Allocation Strategy'!$E$8)))))) -> 3577.296 | AE25: =_xlfn.NORM.INV(RAND(), 'Fund Allocation Strategy'!$B$14, 'Fund Allocation Strategy'!$C$14) + _xlfn.NORM.INV(RAND(), 'Fund Allocation Strategy'!$D$14,'Fund Allocation Strategy'!$E$14) -> 0.34769535 | AF25: =AM24*AE25+(AD25*AE25*0.5) -> 14535.593 | AG25: =IF(B25<=5, Q25*'Fund Allocation Strategy'!$F$2, IF(B25<=10, Q25*'Fund Allocation Strategy'!$F$3, IF(B25<=15, Q25*'Fund Allocation Strategy'!$F$4, IF(B25<=20, Q25*'Fund Allocation Strategy'!$F$5, IF(B25<=25, Q25*'Fund Allocation Strategy'!$F$6, IF(B25<=30, Q25*'Fund Allocation Strategy'!$F$7, Q25*'Fund Allocation Strategy'!$F$8)))))) -> 1788.648 | AH25: =_xlfn.NORM.INV(RAND(),'Fund Allocation Strategy'!$B$15,'Fund Allocation Strategy'!$C$15) -> 0.20677811 | AI25: =AI24*AH25+(AG25*AH25*0.5) -> 234.48208 | AJ25: =AJ24+AG25+AI25 -> 15380.436 | AK25: =IF(AM25<50000,0, AM25*0.015) -> 871.94678 | AL25: =IF(AM25<50000,0,0.015) -> 0.015 | AM25: =AM24+AD25+AF25 -> 58129.785 | AN25: =AM25-AK25 -> 57257.839 | AO25: =IF(AV25 = 0, I25 * ( 'Lifestyle Strategy'!$B$2 + ('Lifestyle Strategy'!$C$2 - 'Lifestyle Strategy'!$B$2) * _xlfn.BETA.INV(RAND(), 'Lifestyle Strategy'!$F$2, 'Lifestyle Strategy'!$G$2) ),IF(AV25 = "", "",0)) -> 0 | AP25: =I25 * ( 'Lifestyle Strategy'!$B$3 + ('Lifestyle Strategy'!$C$3 - 'Lifestyle Strategy'!$B$3) * _xlfn.BETA.INV(RAND(), 'Lifestyle Strategy'!$F$3, 'Lifestyle Strategy'!$G$3) ) * IF(MOD(B25,5)=0, 1 + 'Lifestyle Strategy'!$M$4, 1 + 0.025) -> 17027.376 | AQ25: =I25 * ( 'Lifestyle Strategy'!$B$4 + ('Lifestyle Strategy'!$C$4 - 'Lifestyle Strategy'!$B$4) * _xlfn.BETA.INV(RAND(), 'Lifestyle Strategy'!$F$4, 'Lifestyle Strategy'!$G$4) ) * IF(MOD(B25,5)=0, 1 + 'Lifestyle Strategy'!$M$4, 1 + 0.025) -> 12440.547 | AR25: =I25 * ( 'Lifestyle Strategy'!$B$5 + ('Lifestyle Strategy'!$C$5 - 'Lifestyle Strategy'!$B$5) * _xlfn.BETA.INV(RAND(), 'Lifestyle Strategy'!$F$5, 'Lifestyle Strategy'!$G$5) ) * IF(MOD(B25,5)=0, 1 + 'Lifestyle Strategy'!$M$4, 1 + 0.025) -> 7075.1289 | AS25: =I25 * ( 'Lifestyle Strategy'!$B$6 + ('Lifestyle Strategy'!$C$6 - 'Lifestyle Strategy'!$B$6) * _xlfn.BETA.INV(RAND(), 'Lifestyle Strategy'!$F$6, 'Lifestyle Strategy'!$G$6) ) * IF(MOD(B25,5)=0, 1 + 'Lifestyle Strategy'!$M$4, 1 + 0.025) -> 7157.4316 | AT25: =I25 * ( 'Lifestyle Strategy'!$B$7 + ('Lifestyle Strategy'!$C$7 - 'Lifestyle Strategy'!$B$7) * _xlfn.BETA.INV(RAND(), 'Lifestyle Strategy'!$F$7, 'Lifestyle Strategy'!$G$7) ) * IF(MOD(B25,5)=0, 1 + 'Lifestyle Strategy'!$M$4, 1 + 0.025) -> 16304.069 | AU25: =I25 * ( 'Lifestyle Strategy'!$B$8 + ('Lifestyle Strategy'!$C$8 - 'Lifestyle Strategy'!$B$8) * _xlfn.BETA.INV(RAND(), 'Lifestyle Strategy'!$F$8, 'Lifestyle Strategy'!$G$8) ) * IF(MOD(B25,5)=0, 1 + 'Lifestyle Strategy'!$M$4, 1 + 0.025) -> 6458.9275 | AV25: =IF('Lifestyle Strategy'!$B$14 = "Yes", IF(AND(B25>='Lifestyle Strategy'!$B$15, B25<'Lifestyle Strategy'!$B$16), 'Lifestyle Strategy'!$B$25, IF(B25>='Lifestyle Strategy'!$B$16, "", 0) ), 0 ) -> 17163.2 | AW25: =IF('Lifestyle Strategy'!$Q$4="No", 0, IF(AND(B25>='Lifestyle Strategy'!$Q$5, B25<'Lifestyle Strategy'!$Q$6), 'Lifestyle Strategy'!$Q$8 * (1.025^(B25-'Lifestyle Strategy'!$Q$5)) * (1.12^INT((B25-'Lifestyle Strategy'!$Q$5)/5)), 0 ) ) -> 0 | AX25: =IF(AO25 = "",0,AO25)+AP25+AQ25+AR25+AS25+AT25+AU25+AW25+IF(AV25 = "",0,AV25) -> 83626.68 | AY25: =IF(B25='Lifestyle Strategy'!$Q$10, MIN(AN25, 'Lifestyle Strategy'!$Q$11), 0) -> 0 | AZ25: =IF(B25='Lifestyle Strategy'!$Q$10, 'Lifestyle Strategy'!$Q$11, 0) -> 0 | BA25: =IF(B25='Lifestyle Strategy'!$Q$10, MAX(AZ25 - AY25, 0), 0) -> 0 | BB25: =U25+Y25+AC25+AJ25+AN25-AY25 -> 177144.48 | BC25: =TEXT(BB25/1000000, "[$$-en-US]0.00") & "M" -> $0.18M | BR25: 10 | BS25: 75 | BT25: =IF(BS25<'Lifestyle Strategy'!$M$14, 0, 'Lifestyle Strategy'!$M$15 * (1 + 'Lifestyle Strategy'!$M$16)^(BS25-'Lifestyle Strategy'!$M$14) * (1 + IF(RAND() < (0.08 - 0.06) / (0.1 - 0.06), 0.06 + SQRT(RAND() * (0.08 - 0.06) * (0.1 - 0.06)), 0.1 - SQRT((1 - RAND()) * (0.1 - 0.08) * (0.1 - 0.06)) ))^INT((BS25-'Lifestyle Strategy'!$M$14)/5) ) -> 194824.36 | BU25: =BT25/CA25 -> 0.039303682 | BV25: ='Lifestyle Strategy'!$M$22*(1+'Lifestyle Strategy'!$M$16)^('Lifestyle Strategy'!$M$23 + BR25-1) -> 68167.586 | BW25: =BT25-BV25 -> 126656.77 | BX25: =BW25/CA25 -> 0.025551617 | BY25: =IFERROR(_xlfn.NORM.INV(RAND(),'Lifestyle Strategy'!$M$27,'Lifestyle Strategy'!$M$28),0) -> -0.0023464446 | BZ25: =CA24*BY25 -> -11956.335 | CA25: =(CA24+BZ25)-BW25 -> 4956898.4 | CB25: =IF('Post-Retirement_Cal'!$K25<0, ABS('Post-Retirement_Cal'!$K25),0) -> 0
B26: 13 | C26: 43 | D26: =IF(B26<>$B$5,D25*(1+_xlfn.NORM.INV(RAND(),$B$3,$B$4)),D25*(1+_xlfn.NORM.INV(RAND(),$B$3,$B$4))+D25*(1+_xlfn.NORM.INV(RAND(),$B$3,$B$4))) -> 221884.12 | E26: =D26-D25 -> 6801.6407 | F26: =E26/D25 -> 0.031623407 | G26: ='Tax rate cal'!C23 -> 65089.245 | H26: =$B$6*D26 -> 3705.4648 | I26: =D26-G26-H26 -> 153089.41 | J26: =MIN($E$2 + INT(B26/$E$3)*$E$4, $E$5) -> 0.09 | K26: 0.03 | L26: =IF(O26 = 0,0,'Lifestyle Strategy'!$Q$9) -> 0 | M26: =I26*J26 -> 13778.047 | N26: =I26*K26 -> 4592.6823 | O26: =IF(AND('Lifestyle Strategy'!$Q$2="Yes", B26 >='Lifestyle Strategy'!$Q$3), I26 * 'Lifestyle Strategy'!$Q$9, 0 ) -> 0 | P26: =IF(B26<10,0,IF(MOD(B26, $E$6) = 0, $E$7, 0)) -> 0 | Q26: =M26+N26+O26+P26 -> 18370.729 | R26: =IF(B26<=5, Q26*'Fund Allocation Strategy'!$B$2, IF(B26<=10, Q26*'Fund Allocation Strategy'!$B$3, IF(B26<=15, Q26*'Fund Allocation Strategy'!$B$4, IF(B26<=20, Q26*'Fund Allocation Strategy'!$B$5, IF(B26<=25, Q26*'Fund Allocation Strategy'!$B$6, IF(B26<=30, Q26*'Fund Allocation Strategy'!$B$7, Q26*'Fund Allocation Strategy'!$B$8)))))) -> 2755.6094 | S26: =_xlfn.NORM.INV(RAND(),'Fund Allocation Strategy'!$B$11,'Fund Allocation Strategy'!$C$11) -> 0.036577799 | T26: =U25*S26+(R26*S26*0.5) -> 525.82266 | U26: =U25+R26+T26 -> 16279.087 | V26: =IF(B26<=5, Q26*'Fund Allocation Strategy'!$C$2, IF(B26<=10, Q26*'Fund Allocation Strategy'!$C$3, IF(B26<=15, Q26*'Fund Allocation Strategy'!$C$4, IF(B26<=20, Q26*'Fund Allocation Strategy'!$C$5, IF(B26<=25, Q26*'Fund Allocation Strategy'!$C$6, IF(B26<=30, Q26*'Fund Allocation Strategy'!$C$7, Q26*'Fund Allocation Strategy'!$C$8)))))) -> 3674.1459 | W26: =_xlfn.NORM.INV(RAND(),'Fund Allocation Strategy'!$B$12,'Fund Allocation Strategy'!$C$12) -> 0.070329658 | X26: =Y25*W26 + (V26*W26*0.5) -> 1400.6884 | Y26: =Y25+V26+X26 -> 23153.803 | Z26: =IF(B26<=5, Q26*'Fund Allocation Strategy'!$D$2, IF(B26<=10, Q26*'Fund Allocation Strategy'!$D$3, IF(B26<=15, Q26*'Fund Allocation Strategy'!$D$4, IF(B26<=20, Q26*'Fund Allocation Strategy'!$D$5, IF(B26<=25, Q26*'Fund Allocation Strategy'!$D$6, IF(B26<=30, Q26*'Fund Allocation Strategy'!$D$7, Q26*'Fund Allocation Strategy'!$D$8)))))) -> 6429.7553 | AA26: =_xlfn.NORM.INV(RAND(),'Fund Allocation Strategy'!$B$13,'Fund Allocation Strategy'!$C$13) -> 0.10567987 | AB26: =AC25*AA26+(Z26*AA26*0.5) -> 8099.7767 | AC26: =AC25+Z26+AB26 -> 87959.113 | AD26: =IF(B26<=5, Q26*'Fund Allocation Strategy'!$E$2, IF(B26<=10, Q26*'Fund Allocation Strategy'!$E$3, IF(B26<=15, Q26*'Fund Allocation Strategy'!$E$4, IF(B26<=20, Q26*'Fund Allocation Strategy'!$E$5, IF(B26<=25, Q26*'Fund Allocation Strategy'!$E$6, IF(B26<=30, Q26*'Fund Allocation Strategy'!$E$7, Q26*'Fund Allocation Strategy'!$E$8)))))) -> 3674.1459 | AE26: =_xlfn.NORM.INV(RAND(), 'Fund Allocation Strategy'!$B$14, 'Fund Allocation Strategy'!$C$14) + _xlfn.NORM.INV(RAND(), 'Fund Allocation Strategy'!$D$14,'Fund Allocation Strategy'!$E$14) -> 0.032418528 | AF26: =AM25*AE26+(AD26*AE26*0.5) -> 1944.0373 | AG26: =IF(B26<=5, Q26*'Fund Allocation Strategy'!$F$2, IF(B26<=10, Q26*'Fund Allocation Strategy'!$F$3, IF(B26<=15, Q26*'Fund Allocation Strategy'!$F$4, IF(B26<=20, Q26*'Fund Allocation Strategy'!$F$5, IF(B26<=25, Q26*'Fund Allocation Strategy'!$F$6, IF(B26<=30, Q26*'Fund Allocation Strategy'!$F$7, Q26*'Fund Allocation Strategy'!$F$8)))))) -> 1837.0729 | AH26: =_xlfn.NORM.INV(RAND(),'Fund Allocation Strategy'!$B$15,'Fund Allocation Strategy'!$C$15) -> 0.20173994 | AI26: =AI25*AH26+(AG26*AH26*0.5) -> 232.60989 | AJ26: =AJ25+AG26+AI26 -> 17450.119 | AK26: =IF(AM26<50000,0, AM26*0.015) -> 956.21953 | AL26: =IF(AM26<50000,0,0.015) -> 0.015 | AM26: =AM25+AD26+AF26 -> 63747.969 | AN26: =AM26-AK26 -> 62791.749 | AO26: =IF(AV26 = 0, I26 * ( 'Lifestyle Strategy'!$B$2 + ('Lifestyle Strategy'!$C$2 - 'Lifestyle Strategy'!$B$2) * _xlfn.BETA.INV(RAND(), 'Lifestyle Strategy'!$F$2, 'Lifestyle Strategy'!$G$2) ),IF(AV26 = "", "",0)) -> 0 | AP26: =I26 * ( 'Lifestyle Strategy'!$B$3 + ('Lifestyle Strategy'!$C$3 - 'Lifestyle Strategy'!$B$3) * _xlfn.BETA.INV(RAND(), 'Lifestyle Strategy'!$F$3, 'Lifestyle Strategy'!$G$3) ) * IF(MOD(B26,5)=0, 1 + 'Lifestyle Strategy'!$M$4, 1 + 0.025) -> 18962.399 | AQ26: =I26 * ( 'Lifestyle Strategy'!$B$4 + ('Lifestyle Strategy'!$C$4 - 'Lifestyle Strategy'!$B$4) * _xlfn.BETA.INV(RAND(), 'Lifestyle Strategy'!$F$4, 'Lifestyle Strategy'!$G$4) ) * IF(MOD(B26,5)=0, 1 + 'Lifestyle Strategy'!$M$4, 1 + 0.025) -> 14726.985 | AR26: =I26 * ( 'Lifestyle Strategy'!$B$5 + ('Lifestyle Strategy'!$C$5 - 'Lifestyle Strategy'!$B$5) * _xlfn.BETA.INV(RAND(), 'Lifestyle Strategy'!$F$5, 'Lifestyle Strategy'!$G$5) ) * IF(MOD(B26,5)=0, 1 + 'Lifestyle Strategy'!$M$4, 1 + 0.025) -> 8357.2344 | AS26: =I26 * ( 'Lifestyle Strategy'!$B$6 + ('Lifestyle Strategy'!$C$6 - 'Lifestyle Strategy'!$B$6) * _xlfn.BETA.INV(RAND(), 'Lifestyle Strategy'!$F$6, 'Lifestyle Strategy'!$G$6) ) * IF(MOD(B26,5)=0, 1 + 'Lifestyle Strategy'!$M$4, 1 + 0.025) -> 7958.1218 | AT26: =I26 * ( 'Lifestyle Strategy'!$B$7 + ('Lifestyle Strategy'!$C$7 - 'Lifestyle Strategy'!$B$7) * _xlfn.BETA.INV(RAND(), 'Lifestyle Strategy'!$F$7, 'Lifestyle Strategy'!$G$7) ) * IF(MOD(B26,5)=0, 1 + 'Lifestyle Strategy'!$M$4, 1 + 0.025) -> 15144.086 | AU26: =I26 * ( 'Lifestyle Strategy'!$B$8 + ('Lifestyle Strategy'!$C$8 - 'Lifestyle Strategy'!$B$8) * _xlfn.BETA.INV(RAND(), 'Lifestyle Strategy'!$F$8, 'Lifestyle Strategy'!$G$8) ) * IF(MOD(B26,5)=0, 1 + 'Lifestyle Strategy'!$M$4, 1 + 0.025) -> 7809.2522 | AV26: =IF('Lifestyle Strategy'!$B$14 = "Yes", IF(AND(B26>='Lifestyle Strategy'!$B$15, B26<'Lifestyle Strategy'!$B$16), 'Lifestyle Strategy'!$B$25, IF(B26>='Lifestyle Strategy'!$B$16, "", 0) ), 0 ) -> 17163.2 | AW26: =IF('Lifestyle Strategy'!$Q$4="No", 0, IF(AND(B26>='Lifestyle Strategy'!$Q$5, B26<'Lifestyle Strategy'!$Q$6), 'Lifestyle Strategy'!$Q$8 * (1.025^(B26-'Lifestyle Strategy'!$Q$5)) * (1.12^INT((B26-'Lifestyle Strategy'!$Q$5)/5)), 0 ) ) -> 0 | AX26: =IF(AO26 = "",0,AO26)+AP26+AQ26+AR26+AS26+AT26+AU26+AW26+IF(AV26 = "",0,AV26) -> 90121.279 | AY26: =IF(B26='Lifestyle Strategy'!$Q$10, MIN(AN26, 'Lifestyle Strategy'!$Q$11), 0) -> 0 | AZ26: =IF(B26='Lifestyle Strategy'!$Q$10, 'Lifestyle Strategy'!$Q$11, 0) -> 0 | BA26: =IF(B26='Lifestyle Strategy'!$Q$10, MAX(AZ26 - AY26, 0), 0) -> 0 | BB26: =U26+Y26+AC26+AJ26+AN26-AY26 -> 207633.87 | BC26: =TEXT(BB26/1000000, "[$$-en-US]0.00") & "M" -> $0.21M | BR26: 11 | BS26: 76 | BT26: =IF(BS26<'Lifestyle Strategy'!$M$14, 0, 'Lifestyle Strategy'!$M$15 * (1 + 'Lifestyle Strategy'!$M$16)^(BS26-'Lifestyle Strategy'!$M$14) * (1 + IF(RAND() < (0.08 - 0.06) / (0.1 - 0.06), 0.06 + SQRT(RAND() * (0.08 - 0.06) * (0.1 - 0.06)), 0.1 - SQRT((1 - RAND()) * (0.1 - 0.08) * (0.1 - 0.06)) ))^INT((BS26-'Lifestyle Strategy'!$M$14)/5) ) -> 215322.26 | BU26: =BT26/CA26 -> 0.045012053 | BV26: ='Lifestyle Strategy'!$M$22*(1+'Lifestyle Strategy'!$M$16)^('Lifestyle Strategy'!$M$23 + BR26-1) -> 69871.775 | BW26: =BT26-BV26 -> 145450.48 | BX26: =BW26/CA26 -> 0.030405704 | BY26: =IFERROR(_xlfn.NORM.INV(RAND(),'Lifestyle Strategy'!$M$27,'Lifestyle Strategy'!$M$28),0) -> -0.0056063758 | BZ26: =CA25*BY26 -> -27790.236 | CA26: =(CA25+BZ26)-BW26 -> 4783657.7 | CB26: =IF('Post-Retirement_Cal'!$K26<0, ABS('Post-Retirement_Cal'!$K26),0) -> 0
B27: 14 | C27: 44 | D27: =IF(B27<>$B$5,D26*(1+_xlfn.NORM.INV(RAND(),$B$3,$B$4)),D26*(1+_xlfn.NORM.INV(RAND(),$B$3,$B$4))+D26*(1+_xlfn.NORM.INV(RAND(),$B$3,$B$4))) -> 230338.17 | E27: =D27-D26 -> 8454.0501 | F27: =E27/D26 -> 0.038101195 | G27: ='Tax rate cal'!C24 -> 68386.324 | H27: =$B$6*D27 -> 3846.6475 | I27: =D27-G27-H27 -> 158105.2 | J27: =MIN($E$2 + INT(B27/$E$3)*$E$4, $E$5) -> 0.1 | K27: 0.03 | L27: =IF(O27 = 0,0,'Lifestyle Strategy'!$Q$9) -> 0 | M27: =I27*J27 -> 15810.52 | N27: =I27*K27 -> 4743.156 | O27: =IF(AND('Lifestyle Strategy'!$Q$2="Yes", B27 >='Lifestyle Strategy'!$Q$3), I27 * 'Lifestyle Strategy'!$Q$9, 0 ) -> 0 | P27: =IF(B27<10,0,IF(MOD(B27, $E$6) = 0, $E$7, 0)) -> 0 | Q27: =M27+N27+O27+P27 -> 20553.676 | R27: =IF(B27<=5, Q27*'Fund Allocation Strategy'!$B$2, IF(B27<=10, Q27*'Fund Allocation Strategy'!$B$3, IF(B27<=15, Q27*'Fund Allocation Strategy'!$B$4, IF(B27<=20, Q27*'Fund Allocation Strategy'!$B$5, IF(B27<=25, Q27*'Fund Allocation Strategy'!$B$6, IF(B27<=30, Q27*'Fund Allocation Strategy'!$B$7, Q27*'Fund Allocation Strategy'!$B$8)))))) -> 3083.0514 | S27: =_xlfn.NORM.INV(RAND(),'Fund Allocation Strategy'!$B$11,'Fund Allocation Strategy'!$C$11) -> 0.037053448 | T27: =U26*S27+(R27*S27*0.5) -> 660.31513 | U27: =U26+R27+T27 -> 20022.453 | V27: =IF(B27<=5, Q27*'Fund Allocation Strategy'!$C$2, IF(B27<=10, Q27*'Fund Allocation Strategy'!$C$3, IF(B27<=15, Q27*'Fund Allocation Strategy'!$C$4, IF(B27<=20, Q27*'Fund Allocation Strategy'!$C$5, IF(B27<=25, Q27*'Fund Allocation Strategy'!$C$6, IF(B27<=30, Q27*'Fund Allocation Strategy'!$C$7, Q27*'Fund Allocation Strategy'!$C$8)))))) -> 4110.7352 | W27: =_xlfn.NORM.INV(RAND(),'Fund Allocation Strategy'!$B$12,'Fund Allocation Strategy'!$C$12) -> 0.069320662 | X27: =Y26*W27 + (V27*W27*0.5) -> 1747.5164 | Y27: =Y26+V27+X27 -> 29012.055 | Z27: =IF(B27<=5, Q27*'Fund Allocation Strategy'!$D$2, IF(B27<=10, Q27*'Fund Allocation Strategy'!$D$3, IF(B27<=15, Q27*'Fund Allocation Strategy'!$D$4, IF(B27<=20, Q27*'Fund Allocation Strategy'!$D$5, IF(B27<=25, Q27*'Fund Allocation Strategy'!$D$6, IF(B27<=30, Q27*'Fund Allocation Strategy'!$D$7, Q27*'Fund Allocation Strategy'!$D$8)))))) -> 7193.7866 | AA27: =_xlfn.NORM.INV(RAND(),'Fund Allocation Strategy'!$B$13,'Fund Allocation Strategy'!$C$13) -> 0.10300215 | AB27: =AC26*AA27+(Z27*AA27*0.5) -> 9430.4654 | AC27: =AC26+Z27+AB27 -> 104583.36 | AD27: =IF(B27<=5, Q27*'Fund Allocation Strategy'!$E$2, IF(B27<=10, Q27*'Fund Allocation Strategy'!$E$3, IF(B27<=15, Q27*'Fund Allocation Strategy'!$E$4, IF(B27<=20, Q27*'Fund Allocation Strategy'!$E$5, IF(B27<=25, Q27*'Fund Allocation Strategy'!$E$6, IF(B27<=30, Q27*'Fund Allocation Strategy'!$E$7, Q27*'Fund Allocation Strategy'!$E$8)))))) -> 4110.7352 | AE27: =_xlfn.NORM.INV(RAND(), 'Fund Allocation Strategy'!$B$14, 'Fund Allocation Strategy'!$C$14) + _xlfn.NORM.INV(RAND(), 'Fund Allocation Strategy'!$D$14,'Fund Allocation Strategy'!$E$14) -> 0.15904678 | AF27: =AM26*AE27+(AD27*AE27*0.5) -> 10465.808 | AG27: =IF(B27<=5, Q27*'Fund Allocation Strategy'!$F$2, IF(B27<=10, Q27*'Fund Allocation Strategy'!$F$3, IF(B27<=15, Q27*'Fund Allocation Strategy'!$F$4, IF(B27<=20, Q27*'Fund Allocation Strategy'!$F$5, IF(B27<=25, Q27*'Fund Allocation Strategy'!$F$6, IF(B27<=30, Q27*'Fund Allocation Strategy'!$F$7, Q27*'Fund Allocation Strategy'!$F$8)))))) -> 2055.3676 | AH27: =_xlfn.NORM.INV(RAND(),'Fund Allocation Strategy'!$B$15,'Fund Allocation Strategy'!$C$15) -> 0.2033202 | AI27: =AI26*AH27+(AG27*AH27*0.5) -> 256.24316 | AJ27: =AJ26+AG27+AI27 -> 19761.73 | AK27: =IF(AM27<50000,0, AM27*0.015) -> 1174.8677 | AL27: =IF(AM27<50000,0,0.015) -> 0.015 | AM27: =AM26+AD27+AF27 -> 78324.512 | AN27: =AM27-AK27 -> 77149.645 | AO27: =IF(AV27 = 0, I27 * ( 'Lifestyle Strategy'!$B$2 + ('Lifestyle Strategy'!$C$2 - 'Lifestyle Strategy'!$B$2) * _xlfn.BETA.INV(RAND(), 'Lifestyle Strategy'!$F$2, 'Lifestyle Strategy'!$G$2) ),IF(AV27 = "", "",0)) -> 0 | AP27: =I27 * ( 'Lifestyle Strategy'!$B$3 + ('Lifestyle Strategy'!$C$3 - 'Lifestyle Strategy'!$B$3) * _xlfn.BETA.INV(RAND(), 'Lifestyle Strategy'!$F$3, 'Lifestyle Strategy'!$G$3) ) * IF(MOD(B27,5)=0, 1 + 'Lifestyle Strategy'!$M$4, 1 + 0.025) -> 19525.915 | AQ27: =I27 * ( 'Lifestyle Strategy'!$B$4 + ('Lifestyle Strategy'!$C$4 - 'Lifestyle Strategy'!$B$4) * _xlfn.BETA.INV(RAND(), 'Lifestyle Strategy'!$F$4, 'Lifestyle Strategy'!$G$4) ) * IF(MOD(B27,5)=0, 1 + 'Lifestyle Strategy'!$M$4, 1 + 0.025) -> 13173.365 | AR27: =I27 * ( 'Lifestyle Strategy'!$B$5 + ('Lifestyle Strategy'!$C$5 - 'Lifestyle Strategy'!$B$5) * _xlfn.BETA.INV(RAND(), 'Lifestyle Strategy'!$F$5, 'Lifestyle Strategy'!$G$5) ) * IF(MOD(B27,5)=0, 1 + 'Lifestyle Strategy'!$M$4, 1 + 0.025) -> 7934.2326 | AS27: =I27 * ( 'Lifestyle Strategy'!$B$6 + ('Lifestyle Strategy'!$C$6 - 'Lifestyle Strategy'!$B$6) * _xlfn.BETA.INV(RAND(), 'Lifestyle Strategy'!$F$6, 'Lifestyle Strategy'!$G$6) ) * IF(MOD(B27,5)=0, 1 + 'Lifestyle Strategy'!$M$4, 1 + 0.025) -> 7707.8815 | AT27: =I27 * ( 'Lifestyle Strategy'!$B$7 + ('Lifestyle Strategy'!$C$7 - 'Lifestyle Strategy'!$B$7) * _xlfn.BETA.INV(RAND(), 'Lifestyle Strategy'!$F$7, 'Lifestyle Strategy'!$G$7) ) * IF(MOD(B27,5)=0, 1 + 'Lifestyle Strategy'!$M$4, 1 + 0.025) -> 15178.696 | AU27: =I27 * ( 'Lifestyle Strategy'!$B$8 + ('Lifestyle Strategy'!$C$8 - 'Lifestyle Strategy'!$B$8) * _xlfn.BETA.INV(RAND(), 'Lifestyle Strategy'!$F$8, 'Lifestyle Strategy'!$G$8) ) * IF(MOD(B27,5)=0, 1 + 'Lifestyle Strategy'!$M$4, 1 + 0.025) -> 5113.0425 | AV27: =IF('Lifestyle Strategy'!$B$14 = "Yes", IF(AND(B27>='Lifestyle Strategy'!$B$15, B27<'Lifestyle Strategy'!$B$16), 'Lifestyle Strategy'!$B$25, IF(B27>='Lifestyle Strategy'!$B$16, "", 0) ), 0 ) -> 17163.2 | AW27: =IF('Lifestyle Strategy'!$Q$4="No", 0, IF(AND(B27>='Lifestyle Strategy'!$Q$5, B27<'Lifestyle Strategy'!$Q$6), 'Lifestyle Strategy'!$Q$8 * (1.025^(B27-'Lifestyle Strategy'!$Q$5)) * (1.12^INT((B27-'Lifestyle Strategy'!$Q$5)/5)), 0 ) ) -> 0 | AX27: =IF(AO27 = "",0,AO27)+AP27+AQ27+AR27+AS27+AT27+AU27+AW27+IF(AV27 = "",0,AV27) -> 85796.333 | AY27: =IF(B27='Lifestyle Strategy'!$Q$10, MIN(AN27, 'Lifestyle Strategy'!$Q$11), 0) -> 0 | AZ27: =IF(B27='Lifestyle Strategy'!$Q$10, 'Lifestyle Strategy'!$Q$11, 0) -> 0 | BA27: =IF(B27='Lifestyle Strategy'!$Q$10, MAX(AZ27 - AY27, 0), 0) -> 0 | BB27: =U27+Y27+AC27+AJ27+AN27-AY27 -> 250529.25 | BC27: =TEXT(BB27/1000000, "[$$-en-US]0.00") & "M" -> $0.25M | BR27: 12 | BS27: 77 | BT27: =IF(BS27<'Lifestyle Strategy'!$M$14, 0, 'Lifestyle Strategy'!$M$15 * (1 + 'Lifestyle Strategy'!$M$16)^(BS27-'Lifestyle Strategy'!$M$14) * (1 + IF(RAND() < (0.08 - 0.06) / (0.1 - 0.06), 0.06 + SQRT(RAND() * (0.08 - 0.06) * (0.1 - 0.06)), 0.1 - SQRT((1 - RAND()) * (0.1 - 0.08) * (0.1 - 0.06)) ))^INT((BS27-'Lifestyle Strategy'!$M$14)/5) ) -> 222550.47 | BU27: =BT27/CA27 -> 0.043385427 | BV27: ='Lifestyle Strategy'!$M$22*(1+'Lifestyle Strategy'!$M$16)^('Lifestyle Strategy'!$M$23 + BR27-1) -> 71618.57 | BW27: =BT27-BV27 -> 150931.9 | BX27: =BW27/CA27 -> 0.02942364 | BY27: =IFERROR(_xlfn.NORM.INV(RAND(),'Lifestyle Strategy'!$M$27,'Lifestyle Strategy'!$M$28),0) -> 0.10387192 | BZ27: =CA26*BY27 -> 496887.72 | CA27: =(CA26+BZ27)-BW27 -> 5129613.5 | CB27: =IF('Post-Retirement_Cal'!$K27<0, ABS('Post-Retirement_Cal'!$K27),0) -> 0
B28: 15 | C28: 45 | D28: =IF(B28<>$B$5,D27*(1+_xlfn.NORM.INV(RAND(),$B$3,$B$4)),D27*(1+_xlfn.NORM.INV(RAND(),$B$3,$B$4))+D27*(1+_xlfn.NORM.INV(RAND(),$B$3,$B$4))) -> 237156.64 | E28: =D28-D27 -> 6818.4706 | F28: =E28/D27 -> 0.029602 | G28: ='Tax rate cal'!C25 -> 71045.528 | H28: =$B$6*D28 -> 3960.5159 | I28: =D28-G28-H28 -> 162150.6 | J28: =MIN($E$2 + INT(B28/$E$3)*$E$4, $E$5) -> 0.1 | K28: 0.03 | L28: =IF(O28 = 0,0,'Lifestyle Strategy'!$Q$9) -> 0 | M28: =I28*J28 -> 16215.06 | N28: =I28*K28 -> 4864.5179 | O28: =IF(AND('Lifestyle Strategy'!$Q$2="Yes", B28 >='Lifestyle Strategy'!$Q$3), I28 * 'Lifestyle Strategy'!$Q$9, 0 ) -> 0 | P28: =IF(B28<10,0,IF(MOD(B28, $E$6) = 0, $E$7, 0)) -> 10000 | Q28: =M28+N28+O28+P28 -> 31079.578 | R28: =IF(B28<=5, Q28*'Fund Allocation Strategy'!$B$2, IF(B28<=10, Q28*'Fund Allocation Strategy'!$B$3, IF(B28<=15, Q28*'Fund Allocation Strategy'!$B$4, IF(B28<=20, Q28*'Fund Allocation Strategy'!$B$5, IF(B28<=25, Q28*'Fund Allocation Strategy'!$B$6, IF(B28<=30, Q28*'Fund Allocation Strategy'!$B$7, Q28*'Fund Allocation Strategy'!$B$8)))))) -> 4661.9367 | S28: =_xlfn.NORM.INV(RAND(),'Fund Allocation Strategy'!$B$11,'Fund Allocation Strategy'!$C$11) -> 0.03754135 | T28: =U27*S28+(R28*S28*0.5) -> 839.17762 | U28: =U27+R28+T28 -> 25523.567 | V28: =IF(B28<=5, Q28*'Fund Allocation Strategy'!$C$2, IF(B28<=10, Q28*'Fund Allocation Strategy'!$C$3, IF(B28<=15, Q28*'Fund Allocation Strategy'!$C$4, IF(B28<=20, Q28*'Fund Allocation Strategy'!$C$5, IF(B28<=25, Q28*'Fund Allocation Strategy'!$C$6, IF(B28<=30, Q28*'Fund Allocation Strategy'!$C$7, Q28*'Fund Allocation Strategy'!$C$8)))))) -> 6215.9155 | W28: =_xlfn.NORM.INV(RAND(),'Fund Allocation Strategy'!$B$12,'Fund Allocation Strategy'!$C$12) -> 0.0698221 | X28: =Y27*W28 + (V28*W28*0.5) -> 2242.6867 | Y28: =Y27+V28+X28 -> 37470.657 | Z28: =IF(B28<=5, Q28*'Fund Allocation Strategy'!$D$2, IF(B28<=10, Q28*'Fund Allocation Strategy'!$D$3, IF(B28<=15, Q28*'Fund Allocation Strategy'!$D$4, IF(B28<=20, Q28*'Fund Allocation Strategy'!$D$5, IF(B28<=25, Q28*'Fund Allocation Strategy'!$D$6, IF(B28<=30, Q28*'Fund Allocation Strategy'!$D$7, Q28*'Fund Allocation Strategy'!$D$8)))))) -> 10877.852 | AA28: =_xlfn.NORM.INV(RAND(),'Fund Allocation Strategy'!$B$13,'Fund Allocation Strategy'!$C$13) -> 0.10369222 | AB28: =AC27*AA28+(Z28*AA28*0.5) -> 11408.456 | AC28: =AC27+Z28+AB28 -> 126869.67 | AD28: =IF(B28<=5, Q28*'Fund Allocation Strategy'!$E$2, IF(B28<=10, Q28*'Fund Allocation Strategy'!$E$3, IF(B28<=15, Q28*'Fund Allocation Strategy'!$E$4, IF(B28<=20, Q28*'Fund Allocation Strategy'!$E$5, IF(B28<=25, Q28*'Fund Allocation Strategy'!$E$6, IF(B28<=30, Q28*'Fund Allocation Strategy'!$E$7, Q28*'Fund Allocation Strategy'!$E$8)))))) -> 6215.9155 | AE28: =_xlfn.NORM.INV(RAND(), 'Fund Allocation Strategy'!$B$14, 'Fund Allocation Strategy'!$C$14) + _xlfn.NORM.INV(RAND(), 'Fund Allocation Strategy'!$D$14,'Fund Allocation Strategy'!$E$14) -> -0.0042225358 | AF28: =AM27*AE28+(AD28*AE28*0.5) -> -343.85152 | AG28: =IF(B28<=5, Q28*'Fund Allocation Strategy'!$F$2, IF(B28<=10, Q28*'Fund Allocation Strategy'!$F$3, IF(B28<=15, Q28*'Fund Allocation Strategy'!$F$4, IF(B28<=20, Q28*'Fund Allocation Strategy'!$F$5, IF(B28<=25, Q28*'Fund Allocation Strategy'!$F$6, IF(B28<=30, Q28*'Fund Allocation Strategy'!$F$7, Q28*'Fund Allocation Strategy'!$F$8)))))) -> 3107.9578 | AH28: =_xlfn.NORM.INV(RAND(),'Fund Allocation Strategy'!$B$15,'Fund Allocation Strategy'!$C$15) -> 0.20447432 | AI28: =AI27*AH28+(AG28*AH28*0.5) -> 370.14392 | AJ28: =AJ27+AG28+AI28 -> 23239.832 | AK28: =IF(AM28<50000,0, AM28*0.015) -> 1262.9486 | AL28: =IF(AM28<50000,0,0.015) -> 0.015 | AM28: =AM27+AD28+AF28 -> 84196.576 | AN28: =AM28-AK28 -> 82933.628 | AO28: =IF(AV28 = 0, I28 * ( 'Lifestyle Strategy'!$B$2 + ('Lifestyle Strategy'!$C$2 - 'Lifestyle Strategy'!$B$2) * _xlfn.BETA.INV(RAND(), 'Lifestyle Strategy'!$F$2, 'Lifestyle Strategy'!$G$2) ),IF(AV28 = "", "",0)) -> 0 | AP28: =I28 * ( 'Lifestyle Strategy'!$B$3 + ('Lifestyle Strategy'!$C$3 - 'Lifestyle Strategy'!$B$3) * _xlfn.BETA.INV(RAND(), 'Lifestyle Strategy'!$F$3, 'Lifestyle Strategy'!$G$3) ) * IF(MOD(B28,5)=0, 1 + 'Lifestyle Strategy'!$M$4, 1 + 0.025) -> 22310.061 | AQ28: =I28 * ( 'Lifestyle Strategy'!$B$4 + ('Lifestyle Strategy'!$C$4 - 'Lifestyle Strategy'!$B$4) * _xlfn.BETA.INV(RAND(), 'Lifestyle Strategy'!$F$4, 'Lifestyle Strategy'!$G$4) ) * IF(MOD(B28,5)=0, 1 + 'Lifestyle Strategy'!$M$4, 1 + 0.025) -> 14306.475 | AR28: =I28 * ( 'Lifestyle Strategy'!$B$5 + ('Lifestyle Strategy'!$C$5 - 'Lifestyle Strategy'!$B$5) * _xlfn.BETA.INV(RAND(), 'Lifestyle Strategy'!$F$5, 'Lifestyle Strategy'!$G$5) ) * IF(MOD(B28,5)=0, 1 + 'Lifestyle Strategy'!$M$4, 1 + 0.025) -> 8989.0055 | AS28: =I28 * ( 'Lifestyle Strategy'!$B$6 + ('Lifestyle Strategy'!$C$6 - 'Lifestyle Strategy'!$B$6) * _xlfn.BETA.INV(RAND(), 'Lifestyle Strategy'!$F$6, 'Lifestyle Strategy'!$G$6) ) * IF(MOD(B28,5)=0, 1 + 'Lifestyle Strategy'!$M$4, 1 + 0.025) -> 9232.0611 | AT28: =I28 * ( 'Lifestyle Strategy'!$B$7 + ('Lifestyle Strategy'!$C$7 - 'Lifestyle Strategy'!$B$7) * _xlfn.BETA.INV(RAND(), 'Lifestyle Strategy'!$F$7, 'Lifestyle Strategy'!$G$7) ) * IF(MOD(B28,5)=0, 1 + 'Lifestyle Strategy'!$M$4, 1 + 0.025) -> 18572.479 | AU28: =I28 * ( 'Lifestyle Strategy'!$B$8 + ('Lifestyle Strategy'!$C$8 - 'Lifestyle Strategy'!$B$8) * _xlfn.BETA.INV(RAND(), 'Lifestyle Strategy'!$F$8, 'Lifestyle Strategy'!$G$8) ) * IF(MOD(B28,5)=0, 1 + 'Lifestyle Strategy'!$M$4, 1 + 0.025) -> 6539.3661 | AV28: =IF('Lifestyle Strategy'!$B$14 = "Yes", IF(AND(B28>='Lifestyle Strategy'!$B$15, B28<'Lifestyle Strategy'!$B$16), 'Lifestyle Strategy'!$B$25, IF(B28>='Lifestyle Strategy'!$B$16, "", 0) ), 0 ) -> 17163.2 | AW28: =IF('Lifestyle Strategy'!$Q$4="No", 0, IF(AND(B28>='Lifestyle Strategy'!$Q$5, B28<'Lifestyle Strategy'!$Q$6), 'Lifestyle Strategy'!$Q$8 * (1.025^(B28-'Lifestyle Strategy'!$Q$5)) * (1.12^INT((B28-'Lifestyle Strategy'!$Q$5)/5)), 0 ) ) -> 0 | AX28: =IF(AO28 = "",0,AO28)+AP28+AQ28+AR28+AS28+AT28+AU28+AW28+IF(AV28 = "",0,AV28) -> 97112.648 | AY28: =IF(B28='Lifestyle Strategy'!$Q$10, MIN(AN28, 'Lifestyle Strategy'!$Q$11), 0) -> 0 | AZ28: =IF(B28='Lifestyle Strategy'!$Q$10, 'Lifestyle Strategy'!$Q$11, 0) -> 0 | BA28: =IF(B28='Lifestyle Strategy'!$Q$10, MAX(AZ28 - AY28, 0), 0) -> 0 | BB28: =U28+Y28+AC28+AJ28+AN28-AY28 -> 296037.36 | BC28: =TEXT(BB28/1000000, "[$$-en-US]0.00") & "M" -> $0.30M | BR28: 13 | BS28: 78 | BT28: =IF(BS28<'Lifestyle Strategy'!$M$14, 0, 'Lifestyle Strategy'!$M$15 * (1 + 'Lifestyle Strategy'!$M$16)^(BS28-'Lifestyle Strategy'!$M$14) * (1 + IF(RAND() < (0.08 - 0.06) / (0.1 - 0.06), 0.06 + SQRT(RAND() * (0.08 - 0.06) * (0.1 - 0.06)), 0.1 - SQRT((1 - RAND()) * (0.1 - 0.08) * (0.1 - 0.06)) ))^INT((BS28-'Lifestyle Strategy'!$M$14)/5) ) -> 221512.91 | BU28: =BT28/CA28 -> 0.042234682 | BV28: ='Lifestyle Strategy'!$M$22*(1+'Lifestyle Strategy'!$M$16)^('Lifestyle Strategy'!$M$23 + BR28-1) -> 73409.034 | BW28: =BT28-BV28 -> 148103.87 | BX28: =BW28/CA28 -> 0.028238174 | BY28: =IFERROR(_xlfn.NORM.INV(RAND(),'Lifestyle Strategy'!$M$27,'Lifestyle Strategy'!$M$28),0) -> 0.05132959 | BZ28: =CA27*BY28 -> 263300.96 | CA28: =(CA27+BZ28)-BW28 -> 5244810.6 | CB28: =IF('Post-Retirement_Cal'!$K28<0, ABS('Post-Retirement_Cal'!$K28),0) -> 0
... B35: 22 | C35: 52 | D35: =IF(B35<>$B$5,D34*(1+_xlfn.NORM.INV(RAND(),$B$3,$B$4)),D34*(1+_xlfn.NORM.INV(RAND(),$B$3,$B$4))+D34*(1+_xlfn.NORM.INV(RAND(),$B$3,$B$4))) -> 298653.11 | E35: =D35-D34 -> 12479.955 | F35: =E35/D34 -> 0.043609803 | G35: ='Tax rate cal'!C32 -> 95029.15 | H35: =$B$6*D35 -> 4987.5069 | I35: =D35-G35-H35 -> 198636.45 | J35: =MIN($E$2 + INT(B35/$E$3)*$E$4, $E$5) -> 0.12 | K35: 0.03 | L35: =IF(O35 = 0,0,'Lifestyle Strategy'!$Q$9) -> 0 | M35: =I35*J35 -> 23836.374 | N35: =I35*K35 -> 5959.0936 | O35: =IF(AND('Lifestyle Strategy'!$Q$2="Yes", B35 >='Lifestyle Strategy'!$Q$3), I35 * 'Lifestyle Strategy'!$Q$9, 0 ) -> 0 | P35: =IF(B35<10,0,IF(MOD(B35, $E$6) = 0, $E$7, 0)) -> 0 | Q35: =M35+N35+O35+P35 -> 29795.468 | R35: =IF(B35<=5, Q35*'Fund Allocation Strategy'!$B$2, IF(B35<=10, Q35*'Fund Allocation Strategy'!$B$3, IF(B35<=15, Q35*'Fund Allocation Strategy'!$B$4, IF(B35<=20, Q35*'Fund Allocation Strategy'!$B$5, IF(B35<=25, Q35*'Fund Allocation Strategy'!$B$6, IF(B35<=30, Q35*'Fund Allocation Strategy'!$B$7, Q35*'Fund Allocation Strategy'!$B$8)))))) -> 8938.6403 | S35: =_xlfn.NORM.INV(RAND(),'Fund Allocation Strategy'!$B$11,'Fund Allocation Strategy'!$C$11) -> 0.037561117 | T35: =U34*S35+(R35*S35*0.5) -> 3017.8706 | U35: =U34+R35+T35 -> 87832.795 | V35: =IF(B35<=5, Q35*'Fund Allocation Strategy'!$C$2, IF(B35<=10, Q35*'Fund Allocation Strategy'!$C$3, IF(B35<=15, Q35*'Fund Allocation Strategy'!$C$4, IF(B35<=20, Q35*'Fund Allocation Strategy'!$C$5, IF(B35<=25, Q35*'Fund Allocation Strategy'!$C$6, IF(B35<=30, Q35*'Fund Allocation Strategy'!$C$7, Q35*'Fund Allocation Strategy'!$C$8)))))) -> 8938.6403 | W35: =_xlfn.NORM.INV(RAND(),'Fund Allocation Strategy'!$B$12,'Fund Allocation Strategy'!$C$12) -> 0.070388593 | X35: =Y34*W35 + (V35*W35*0.5) -> 7969.8206 | Y35: =Y34+V35+X35 -> 125665.17 | Z35: =IF(B35<=5, Q35*'Fund Allocation Strategy'!$D$2, IF(B35<=10, Q35*'Fund Allocation Strategy'!$D$3, IF(B35<=15, Q35*'Fund Allocation Strategy'!$D$4, IF(B35<=20, Q35*'Fund Allocation Strategy'!$D$5, IF(B35<=25, Q35*'Fund Allocation Strategy'!$D$6, IF(B35<=30, Q35*'Fund Allocation Strategy'!$D$7, Q35*'Fund Allocation Strategy'!$D$8)))))) -> 7448.8669 | AA35: =_xlfn.NORM.INV(RAND(),'Fund Allocation Strategy'!$B$13,'Fund Allocation Strategy'!$C$13) -> 0.10215253 | AB35: =AC34*AA35+(Z35*AA35*0.5) -> 30563.611 | AC35: =AC34+Z35+AB35 -> 333483.87 | AD35: =IF(B35<=5, Q35*'Fund Allocation Strategy'!$E$2, IF(B35<=10, Q35*'Fund Allocation Strategy'!$E$3, IF(B35<=15, Q35*'Fund Allocation Strategy'!$E$4, IF(B35<=20, Q35*'Fund Allocation Strategy'!$E$5, IF(B35<=25, Q35*'Fund Allocation Strategy'!$E$6, IF(B35<=30, Q35*'Fund Allocation Strategy'!$E$7, Q35*'Fund Allocation Strategy'!$E$8)))))) -> 2979.5468 | AE35: =_xlfn.NORM.INV(RAND(), 'Fund Allocation Strategy'!$B$14, 'Fund Allocation Strategy'!$C$14) + _xlfn.NORM.INV(RAND(), 'Fund Allocation Strategy'!$D$14,'Fund Allocation Strategy'!$E$14) -> 0.17563191 | AF35: =AM34*AE35+(AD35*AE35*0.5) -> 31571.649 | AG35: =IF(B35<=5, Q35*'Fund Allocation Strategy'!$F$2, IF(B35<=10, Q35*'Fund Allocation Strategy'!$F$3, IF(B35<=15, Q35*'Fund Allocation Strategy'!$F$4, IF(B35<=20, Q35*'Fund Allocation Strategy'!$F$5, IF(B35<=25, Q35*'Fund Allocation Strategy'!$F$6, IF(B35<=30, Q35*'Fund Allocation Strategy'!$F$7, Q35*'Fund Allocation Strategy'!$F$8)))))) -> 1489.7734 | AH35: =_xlfn.NORM.INV(RAND(),'Fund Allocation Strategy'!$B$15,'Fund Allocation Strategy'!$C$15) -> 0.21170922 | AI35: =AI34*AH35+(AG35*AH35*0.5) -> 202.828 | AJ35: =AJ34+AG35+AI35 -> 38374.085 | AK35: =IF(AM35<50000,0, AM35*0.015) -> 3192.3262 | AL35: =IF(AM35<50000,0,0.015) -> 0.015 | AM35: =AM34+AD35+AF35 -> 212821.75 | AN35: =AM35-AK35 -> 209629.42 | AO35: =IF(AV35 = 0, I35 * ( 'Lifestyle Strategy'!$B$2 + ('Lifestyle Strategy'!$C$2 - 'Lifestyle Strategy'!$B$2) * _xlfn.BETA.INV(RAND(), 'Lifestyle Strategy'!$F$2, 'Lifestyle Strategy'!$G$2) ),IF(AV35 = "", "",0)) | AP35: =I35 * ( 'Lifestyle Strategy'!$B$3 + ('Lifestyle Strategy'!$C$3 - 'Lifestyle Strategy'!$B$3) * _xlfn.BETA.INV(RAND(), 'Lifestyle Strategy'!$F$3, 'Lifestyle Strategy'!$G$3) ) * IF(MOD(B35,5)=0, 1 + 'Lifestyle Strategy'!$M$4, 1 + 0.025) -> 27531.199 | AQ35: =I35 * ( 'Lifestyle Strategy'!$B$4 + ('Lifestyle Strategy'!$C$4 - 'Lifestyle Strategy'!$B$4) * _xlfn.BETA.INV(RAND(), 'Lifestyle Strategy'!$F$4, 'Lifestyle Strategy'!$G$4) ) * IF(MOD(B35,5)=0, 1 + 'Lifestyle Strategy'!$M$4, 1 + 0.025) -> 15665.923 | AR35: =I35 * ( 'Lifestyle Strategy'!$B$5 + ('Lifestyle Strategy'!$C$5 - 'Lifestyle Strategy'!$B$5) * _xlfn.BETA.INV(RAND(), 'Lifestyle Strategy'!$F$5, 'Lifestyle Strategy'!$G$5) ) * IF(MOD(B35,5)=0, 1 + 'Lifestyle Strategy'!$M$4, 1 + 0.025) -> 10655.942 | AS35: =I35 * ( 'Lifestyle Strategy'!$B$6 + ('Lifestyle Strategy'!$C$6 - 'Lifestyle Strategy'!$B$6) * _xlfn.BETA.INV(RAND(), 'Lifestyle Strategy'!$F$6, 'Lifestyle Strategy'!$G$6) ) * IF(MOD(B35,5)=0, 1 + 'Lifestyle Strategy'!$M$4, 1 + 0.025) -> 10006.192 | AT35: =I35 * ( 'Lifestyle Strategy'!$B$7 + ('Lifestyle Strategy'!$C$7 - 'Lifestyle Strategy'!$B$7) * _xlfn.BETA.INV(RAND(), 'Lifestyle Strategy'!$F$7, 'Lifestyle Strategy'!$G$7) ) * IF(MOD(B35,5)=0, 1 + 'Lifestyle Strategy'!$M$4, 1 + 0.025) -> 17721.741 | AU35: =I35 * ( 'Lifestyle Strategy'!$B$8 + ('Lifestyle Strategy'!$C$8 - 'Lifestyle Strategy'!$B$8) * _xlfn.BETA.INV(RAND(), 'Lifestyle Strategy'!$F$8, 'Lifestyle Strategy'!$G$8) ) * IF(MOD(B35,5)=0, 1 + 'Lifestyle Strategy'!$M$4, 1 + 0.025) -> 10245.429 | AV35: =IF('Lifestyle Strategy'!$B$14 = "Yes", IF(AND(B35>='Lifestyle Strategy'!$B$15, B35<'Lifestyle Strategy'!$B$16), 'Lifestyle Strategy'!$B$25, IF(B35>='Lifestyle Strategy'!$B$16, "", 0) ), 0 ) | AW35: =IF('Lifestyle Strategy'!$Q$4="No", 0, IF(AND(B35>='Lifestyle Strategy'!$Q$5, B35<'Lifestyle Strategy'!$Q$6), 'Lifestyle Strategy'!$Q$8 * (1.025^(B35-'Lifestyle Strategy'!$Q$5)) * (1.12^INT((B35-'Lifestyle Strategy'!$Q$5)/5)), 0 ) ) -> 0 | AX35: =IF(AO35 = "",0,AO35)+AP35+AQ35+AR35+AS35+AT35+AU35+AW35+IF(AV35 = "",0,AV35) -> 91826.426 | AY35: =IF(B35='Lifestyle Strategy'!$Q$10, MIN(AN35, 'Lifestyle Strategy'!$Q$11), 0) -> 0 | AZ35: =IF(B35='Lifestyle Strategy'!$Q$10, 'Lifestyle Strategy'!$Q$11, 0) -> 0 | BA35: =IF(B35='Lifestyle Strategy'!$Q$10, MAX(AZ35 - AY35, 0), 0) -> 0 | BB35: =U35+Y35+AC35+AJ35+AN35-AY35 -> 794985.33 | BC35: =TEXT(BB35/1000000, "[$$-en-US]0.00") & "M" -> $0.79M | BR35: 20 | BS35: 85 | BT35: =IF(BS35<'Lifestyle Strategy'!$M$14, 0, 'Lifestyle Strategy'!$M$15 * (1 + 'Lifestyle Strategy'!$M$16)^(BS35-'Lifestyle Strategy'!$M$14) * (1 + IF(RAND() < (0.08 - 0.06) / (0.1 - 0.06), 0.06 + SQRT(RAND() * (0.08 - 0.06) * (0.1 - 0.06)), 0.1 - SQRT((1 - RAND()) * (0.1 - 0.08) * (0.1 - 0.06)) ))^INT((BS35-'Lifestyle Strategy'!$M$14)/5) ) -> 294202.45 | BU35: =BT35/CA35 -> 0.063997721 | BV35: ='Lifestyle Strategy'!$M$22*(1+'Lifestyle Strategy'!$M$16)^('Lifestyle Strategy'!$M$23 + BR35-1) -> 87260.273 | BW35: =BT35-BV35 -> 206942.18 | BX35: =BW35/CA35 -> 0.045016035 | BY35: =IFERROR(_xlfn.NORM.INV(RAND(),'Lifestyle Strategy'!$M$27,'Lifestyle Strategy'!$M$28),0) -> 0.024594265 | BZ35: =CA34*BY35 -> 115315.23 | CA35: =(CA34+BZ35)-BW35 -> 4597077 | CB35: =IF('Post-Retirement_Cal'!$K35<0, ABS('Post-Retirement_Cal'!$K35),0) -> 0
B36: 23 | C36: 53 | D36: =IF(B36<>$B$5,D35*(1+_xlfn.NORM.INV(RAND(),$B$3,$B$4)),D35*(1+_xlfn.NORM.INV(RAND(),$B$3,$B$4))+D35*(1+_xlfn.NORM.INV(RAND(),$B$3,$B$4))) -> 312515.83 | E36: =D36-D35 -> 13862.726 | F36: =E36/D35 -> 0.046417484 | G36: ='Tax rate cal'!C33 -> 100435.61 | H36: =$B$6*D36 -> 5219.0144 | I36: =D36-G36-H36 -> 206861.21 | J36: =MIN($E$2 + INT(B36/$E$3)*$E$4, $E$5) -> 0.12 | K36: 0.03 | L36: =IF(O36 = 0,0,'Lifestyle Strategy'!$Q$9) -> 0 | M36: =I36*J36 -> 24823.345 | N36: =I36*K36 -> 6205.8362 | O36: =IF(AND('Lifestyle Strategy'!$Q$2="Yes", B36 >='Lifestyle Strategy'!$Q$3), I36 * 'Lifestyle Strategy'!$Q$9, 0 ) -> 0 | P36: =IF(B36<10,0,IF(MOD(B36, $E$6) = 0, $E$7, 0)) -> 0 | Q36: =M36+N36+O36+P36 -> 31029.181 | R36: =IF(B36<=5, Q36*'Fund Allocation Strategy'!$B$2, IF(B36<=10, Q36*'Fund Allocation Strategy'!$B$3, IF(B36<=15, Q36*'Fund Allocation Strategy'!$B$4, IF(B36<=20, Q36*'Fund Allocation Strategy'!$B$5, IF(B36<=25, Q36*'Fund Allocation Strategy'!$B$6, IF(B36<=30, Q36*'Fund Allocation Strategy'!$B$7, Q36*'Fund Allocation Strategy'!$B$8)))))) -> 9308.7543 | S36: =_xlfn.NORM.INV(RAND(),'Fund Allocation Strategy'!$B$11,'Fund Allocation Strategy'!$C$11) -> 0.03741882 | T36: =U35*S36+(R36*S36*0.5) -> 3460.7608 | U36: =U35+R36+T36 -> 100602.31 | V36: =IF(B36<=5, Q36*'Fund Allocation Strategy'!$C$2, IF(B36<=10, Q36*'Fund Allocation Strategy'!$C$3, IF(B36<=15, Q36*'Fund Allocation Strategy'!$C$4, IF(B36<=20, Q36*'Fund Allocation Strategy'!$C$5, IF(B36<=25, Q36*'Fund Allocation Strategy'!$C$6, IF(B36<=30, Q36*'Fund Allocation Strategy'!$C$7, Q36*'Fund Allocation Strategy'!$C$8)))))) -> 9308.7543 | W36: =_xlfn.NORM.INV(RAND(),'Fund Allocation Strategy'!$B$12,'Fund Allocation Strategy'!$C$12) -> 0.069727599 | X36: =Y35*W36 + (V36*W36*0.5) -> 9086.8688 | Y36: =Y35+V36+X36 -> 144060.79 | Z36: =IF(B36<=5, Q36*'Fund Allocation Strategy'!$D$2, IF(B36<=10, Q36*'Fund Allocation Strategy'!$D$3, IF(B36<=15, Q36*'Fund Allocation Strategy'!$D$4, IF(B36<=20, Q36*'Fund Allocation Strategy'!$D$5, IF(B36<=25, Q36*'Fund Allocation Strategy'!$D$6, IF(B36<=30, Q36*'Fund Allocation Strategy'!$D$7, Q36*'Fund Allocation Strategy'!$D$8)))))) -> 7757.2953 | AA36: =_xlfn.NORM.INV(RAND(),'Fund Allocation Strategy'!$B$13,'Fund Allocation Strategy'!$C$13) -> 0.10442154 | AB36: =AC35*AA36+(Z36*AA36*0.5) -> 35227.914 | AC36: =AC35+Z36+AB36 -> 376469.08 | AD36: =IF(B36<=5, Q36*'Fund Allocation Strategy'!$E$2, IF(B36<=10, Q36*'Fund Allocation Strategy'!$E$3, IF(B36<=15, Q36*'Fund Allocation Strategy'!$E$4, IF(B36<=20, Q36*'Fund Allocation Strategy'!$E$5, IF(B36<=25, Q36*'Fund Allocation Strategy'!$E$6, IF(B36<=30, Q36*'Fund Allocation Strategy'!$E$7, Q36*'Fund Allocation Strategy'!$E$8)))))) -> 3102.9181 | AE36: =_xlfn.NORM.INV(RAND(), 'Fund Allocation Strategy'!$B$14, 'Fund Allocation Strategy'!$C$14) + _xlfn.NORM.INV(RAND(), 'Fund Allocation Strategy'!$D$14,'Fund Allocation Strategy'!$E$14) -> 0.50961045 | AF36: =AM35*AE36+(AD36*AE36*0.5) -> 109246.82 | AG36: =IF(B36<=5, Q36*'Fund Allocation Strategy'!$F$2, IF(B36<=10, Q36*'Fund Allocation Strategy'!$F$3, IF(B36<=15, Q36*'Fund Allocation Strategy'!$F$4, IF(B36<=20, Q36*'Fund Allocation Strategy'!$F$5, IF(B36<=25, Q36*'Fund Allocation Strategy'!$F$6, IF(B36<=30, Q36*'Fund Allocation Strategy'!$F$7, Q36*'Fund Allocation Strategy'!$F$8)))))) -> 1551.4591 | AH36: =_xlfn.NORM.INV(RAND(),'Fund Allocation Strategy'!$B$15,'Fund Allocation Strategy'!$C$15) -> 0.22190108 | AI36: =AI35*AH36+(AG36*AH36*0.5) -> 217.14297 | AJ36: =AJ35+AG36+AI36 -> 40142.687 | AK36: =IF(AM36<50000,0, AM36*0.015) -> 4877.5723 | AL36: =IF(AM36<50000,0,0.015) -> 0.015 | AM36: =AM35+AD36+AF36 -> 325171.49 | AN36: =AM36-AK36 -> 320293.92 | AO36: =IF(AV36 = 0, I36 * ( 'Lifestyle Strategy'!$B$2 + ('Lifestyle Strategy'!$C$2 - 'Lifestyle Strategy'!$B$2) * _xlfn.BETA.INV(RAND(), 'Lifestyle Strategy'!$F$2, 'Lifestyle Strategy'!$G$2) ),IF(AV36 = "", "",0)) | AP36: =I36 * ( 'Lifestyle Strategy'!$B$3 + ('Lifestyle Strategy'!$C$3 - 'Lifestyle Strategy'!$B$3) * _xlfn.BETA.INV(RAND(), 'Lifestyle Strategy'!$F$3, 'Lifestyle Strategy'!$G$3) ) * IF(MOD(B36,5)=0, 1 + 'Lifestyle Strategy'!$M$4, 1 + 0.025) -> 29377.118 | AQ36: =I36 * ( 'Lifestyle Strategy'!$B$4 + ('Lifestyle Strategy'!$C$4 - 'Lifestyle Strategy'!$B$4) * _xlfn.BETA.INV(RAND(), 'Lifestyle Strategy'!$F$4, 'Lifestyle Strategy'!$G$4) ) * IF(MOD(B36,5)=0, 1 + 'Lifestyle Strategy'!$M$4, 1 + 0.025) -> 19043.76 | AR36: =I36 * ( 'Lifestyle Strategy'!$B$5 + ('Lifestyle Strategy'!$C$5 - 'Lifestyle Strategy'!$B$5) * _xlfn.BETA.INV(RAND(), 'Lifestyle Strategy'!$F$5, 'Lifestyle Strategy'!$G$5) ) * IF(MOD(B36,5)=0, 1 + 'Lifestyle Strategy'!$M$4, 1 + 0.025) -> 10884.751 | AS36: =I36 * ( 'Lifestyle Strategy'!$B$6 + ('Lifestyle Strategy'!$C$6 - 'Lifestyle Strategy'!$B$6) * _xlfn.BETA.INV(RAND(), 'Lifestyle Strategy'!$F$6, 'Lifestyle Strategy'!$G$6) ) * IF(MOD(B36,5)=0, 1 + 'Lifestyle Strategy'!$M$4, 1 + 0.025) -> 9875.1565 | AT36: =I36 * ( 'Lifestyle Strategy'!$B$7 + ('Lifestyle Strategy'!$C$7 - 'Lifestyle Strategy'!$B$7) * _xlfn.BETA.INV(RAND(), 'Lifestyle Strategy'!$F$7, 'Lifestyle Strategy'!$G$7) ) * IF(MOD(B36,5)=0, 1 + 'Lifestyle Strategy'!$M$4, 1 + 0.025) -> 22851.501 | AU36: =I36 * ( 'Lifestyle Strategy'!$B$8 + ('Lifestyle Strategy'!$C$8 - 'Lifestyle Strategy'!$B$8) * _xlfn.BETA.INV(RAND(), 'Lifestyle Strategy'!$F$8, 'Lifestyle Strategy'!$G$8) ) * IF(MOD(B36,5)=0, 1 + 'Lifestyle Strategy'!$M$4, 1 + 0.025) -> 6795.2815 | AV36: =IF('Lifestyle Strategy'!$B$14 = "Yes", IF(AND(B36>='Lifestyle Strategy'!$B$15, B36<'Lifestyle Strategy'!$B$16), 'Lifestyle Strategy'!$B$25, IF(B36>='Lifestyle Strategy'!$B$16, "", 0) ), 0 ) | AW36: =IF('Lifestyle Strategy'!$Q$4="No", 0, IF(AND(B36>='Lifestyle Strategy'!$Q$5, B36<'Lifestyle Strategy'!$Q$6), 'Lifestyle Strategy'!$Q$8 * (1.025^(B36-'Lifestyle Strategy'!$Q$5)) * (1.12^INT((B36-'Lifestyle Strategy'!$Q$5)/5)), 0 ) ) -> 0 | AX36: =IF(AO36 = "",0,AO36)+AP36+AQ36+AR36+AS36+AT36+AU36+AW36+IF(AV36 = "",0,AV36) -> 98827.568 | AY36: =IF(B36='Lifestyle Strategy'!$Q$10, MIN(AN36, 'Lifestyle Strategy'!$Q$11), 0) -> 0 | AZ36: =IF(B36='Lifestyle Strategy'!$Q$10, 'Lifestyle Strategy'!$Q$11, 0) -> 0 | BA36: =IF(B36='Lifestyle Strategy'!$Q$10, MAX(AZ36 - AY36, 0), 0) -> 0 | BB36: =U36+Y36+AC36+AJ36+AN36-AY36 -> 981568.78 | BC36: =TEXT(BB36/1000000, "[$$-en-US]0.00") & "M" -> $0.98M
B37: 24 | C37: 54 | D37: =IF(B37<>$B$5,D36*(1+_xlfn.NORM.INV(RAND(),$B$3,$B$4)),D36*(1+_xlfn.NORM.INV(RAND(),$B$3,$B$4))+D36*(1+_xlfn.NORM.INV(RAND(),$B$3,$B$4))) -> 323275.6 | E37: =D37-D36 -> 10759.762 | F37: =E37/D36 -> 0.034429495 | G37: ='Tax rate cal'!C34 -> 104631.92 | H37: =$B$6*D37 -> 5398.7025 | I37: =D37-G37-H37 -> 213244.97 | J37: =MIN($E$2 + INT(B37/$E$3)*$E$4, $E$5) -> 0.12 | K37: 0.03 | L37: =IF(O37 = 0,0,'Lifestyle Strategy'!$Q$9) -> 0 | M37: =I37*J37 -> 25589.397 | N37: =I37*K37 -> 6397.3492 | O37: =IF(AND('Lifestyle Strategy'!$Q$2="Yes", B37 >='Lifestyle Strategy'!$Q$3), I37 * 'Lifestyle Strategy'!$Q$9, 0 ) -> 0 | P37: =IF(B37<10,0,IF(MOD(B37, $E$6) = 0, $E$7, 0)) -> 0 | Q37: =M37+N37+O37+P37 -> 31986.746 | R37: =IF(B37<=5, Q37*'Fund Allocation Strategy'!$B$2, IF(B37<=10, Q37*'Fund Allocation Strategy'!$B$3, IF(B37<=15, Q37*'Fund Allocation Strategy'!$B$4, IF(B37<=20, Q37*'Fund Allocation Strategy'!$B$5, IF(B37<=25, Q37*'Fund Allocation Strategy'!$B$6, IF(B37<=30, Q37*'Fund Allocation Strategy'!$B$7, Q37*'Fund Allocation Strategy'!$B$8)))))) -> 9596.0238 | S37: =_xlfn.NORM.INV(RAND(),'Fund Allocation Strategy'!$B$11,'Fund Allocation Strategy'!$C$11) -> 0.036571673 | T37: =U36*S37+(R37*S37*0.5) -> 3854.6661 | U37: =U36+R37+T37 -> 114053 | V37: =IF(B37<=5, Q37*'Fund Allocation Strategy'!$C$2, IF(B37<=10, Q37*'Fund Allocation Strategy'!$C$3, IF(B37<=15, Q37*'Fund Allocation Strategy'!$C$4, IF(B37<=20, Q37*'Fund Allocation Strategy'!$C$5, IF(B37<=25, Q37*'Fund Allocation Strategy'!$C$6, IF(B37<=30, Q37*'Fund Allocation Strategy'!$C$7, Q37*'Fund Allocation Strategy'!$C$8)))))) -> 9596.0238 | W37: =_xlfn.NORM.INV(RAND(),'Fund Allocation Strategy'!$B$12,'Fund Allocation Strategy'!$C$12) -> 0.069244241 | X37: =Y36*W37 + (V37*W37*0.5) -> 10307.615 | Y37: =Y36+V37+X37 -> 163964.43 | Z37: =IF(B37<=5, Q37*'Fund Allocation Strategy'!$D$2, IF(B37<=10, Q37*'Fund Allocation Strategy'!$D$3, IF(B37<=15, Q37*'Fund Allocation Strategy'!$D$4, IF(B37<=20, Q37*'Fund Allocation Strategy'!$D$5, IF(B37<=25, Q37*'Fund Allocation Strategy'!$D$6, IF(B37<=30, Q37*'Fund Allocation Strategy'!$D$7, Q37*'Fund Allocation Strategy'!$D$8)))))) -> 7996.6865 | AA37: =_xlfn.NORM.INV(RAND(),'Fund Allocation Strategy'!$B$13,'Fund Allocation Strategy'!$C$13) -> 0.10111038 | AB37: =AC36*AA37+(Z37*AA37*0.5) -> 38469.206 | AC37: =AC36+Z37+AB37 -> 422934.97 | AD37: =IF(B37<=5, Q37*'Fund Allocation Strategy'!$E$2, IF(B37<=10, Q37*'Fund Allocation Strategy'!$E$3, IF(B37<=15, Q37*'Fund Allocation Strategy'!$E$4, IF(B37<=20, Q37*'Fund Allocation Strategy'!$E$5, IF(B37<=25, Q37*'Fund Allocation Strategy'!$E$6, IF(B37<=30, Q37*'Fund Allocation Strategy'!$E$7, Q37*'Fund Allocation Strategy'!$E$8)))))) -> 3198.6746 | AE37: =_xlfn.NORM.INV(RAND(), 'Fund Allocation Strategy'!$B$14, 'Fund Allocation Strategy'!$C$14) + _xlfn.NORM.INV(RAND(), 'Fund Allocation Strategy'!$D$14,'Fund Allocation Strategy'!$E$14) -> -0.12302498 | AF37: =AM36*AE37+(AD37*AE37*0.5) -> -40200.974 | AG37: =IF(B37<=5, Q37*'Fund Allocation Strategy'!$F$2, IF(B37<=10, Q37*'Fund Allocation Strategy'!$F$3, IF(B37<=15, Q37*'Fund Allocation Strategy'!$F$4, IF(B37<=20, Q37*'Fund Allocation Strategy'!$F$5, IF(B37<=25, Q37*'Fund Allocation Strategy'!$F$6, IF(B37<=30, Q37*'Fund Allocation Strategy'!$F$7, Q37*'Fund Allocation Strategy'!$F$8)))))) -> 1599.3373 | AH37: =_xlfn.NORM.INV(RAND(),'Fund Allocation Strategy'!$B$15,'Fund Allocation Strategy'!$C$15) -> 0.20719311 | AI37: =AI36*AH37+(AG37*AH37*0.5) -> 210.67636 | AJ37: =AJ36+AG37+AI37 -> 41952.701 | AK37: =IF(AM37<50000,0, AM37*0.015) -> 4322.5378 | AL37: =IF(AM37<50000,0,0.015) -> 0.015 | AM37: =AM36+AD37+AF37 -> 288169.19 | AN37: =AM37-AK37 -> 283846.65 | AO37: =IF(AV37 = 0, I37 * ( 'Lifestyle Strategy'!$B$2 + ('Lifestyle Strategy'!$C$2 - 'Lifestyle Strategy'!$B$2) * _xlfn.BETA.INV(RAND(), 'Lifestyle Strategy'!$F$2, 'Lifestyle Strategy'!$G$2) ),IF(AV37 = "", "",0)) | AP37: =I37 * ( 'Lifestyle Strategy'!$B$3 + ('Lifestyle Strategy'!$C$3 - 'Lifestyle Strategy'!$B$3) * _xlfn.BETA.INV(RAND(), 'Lifestyle Strategy'!$F$3, 'Lifestyle Strategy'!$G$3) ) * IF(MOD(B37,5)=0, 1 + 'Lifestyle Strategy'!$M$4, 1 + 0.025) -> 27420.435 | AQ37: =I37 * ( 'Lifestyle Strategy'!$B$4 + ('Lifestyle Strategy'!$C$4 - 'Lifestyle Strategy'!$B$4) * _xlfn.BETA.INV(RAND(), 'Lifestyle Strategy'!$F$4, 'Lifestyle Strategy'!$G$4) ) * IF(MOD(B37,5)=0, 1 + 'Lifestyle Strategy'!$M$4, 1 + 0.025) -> 17603.574 | AR37: =I37 * ( 'Lifestyle Strategy'!$B$5 + ('Lifestyle Strategy'!$C$5 - 'Lifestyle Strategy'!$B$5) * _xlfn.BETA.INV(RAND(), 'Lifestyle Strategy'!$F$5, 'Lifestyle Strategy'!$G$5) ) * IF(MOD(B37,5)=0, 1 + 'Lifestyle Strategy'!$M$4, 1 + 0.025) -> 10273.031 | AS37: =I37 * ( 'Lifestyle Strategy'!$B$6 + ('Lifestyle Strategy'!$C$6 - 'Lifestyle Strategy'!$B$6) * _xlfn.BETA.INV(RAND(), 'Lifestyle Strategy'!$F$6, 'Lifestyle Strategy'!$G$6) ) * IF(MOD(B37,5)=0, 1 + 'Lifestyle Strategy'!$M$4, 1 + 0.025) -> 10716.952 | AT37: =I37 * ( 'Lifestyle Strategy'!$B$7 + ('Lifestyle Strategy'!$C$7 - 'Lifestyle Strategy'!$B$7) * _xlfn.BETA.INV(RAND(), 'Lifestyle Strategy'!$F$7, 'Lifestyle Strategy'!$G$7) ) * IF(MOD(B37,5)=0, 1 + 'Lifestyle Strategy'!$M$4, 1 + 0.025) -> 22646.782 | AU37: =I37 * ( 'Lifestyle Strategy'!$B$8 + ('Lifestyle Strategy'!$C$8 - 'Lifestyle Strategy'!$B$8) * _xlfn.BETA.INV(RAND(), 'Lifestyle Strategy'!$F$8, 'Lifestyle Strategy'!$G$8) ) * IF(MOD(B37,5)=0, 1 + 'Lifestyle Strategy'!$M$4, 1 + 0.025) -> 7594.1109 | AV37: =IF('Lifestyle Strategy'!$B$14 = "Yes", IF(AND(B37>='Lifestyle Strategy'!$B$15, B37<'Lifestyle Strategy'!$B$16), 'Lifestyle Strategy'!$B$25, IF(B37>='Lifestyle Strategy'!$B$16, "", 0) ), 0 ) | AW37: =IF('Lifestyle Strategy'!$Q$4="No", 0, IF(AND(B37>='Lifestyle Strategy'!$Q$5, B37<'Lifestyle Strategy'!$Q$6), 'Lifestyle Strategy'!$Q$8 * (1.025^(B37-'Lifestyle Strategy'!$Q$5)) * (1.12^INT((B37-'Lifestyle Strategy'!$Q$5)/5)), 0 ) ) -> 0 | AX37: =IF(AO37 = "",0,AO37)+AP37+AQ37+AR37+AS37+AT37+AU37+AW37+IF(AV37 = "",0,AV37) -> 96254.884 | AY37: =IF(B37='Lifestyle Strategy'!$Q$10, MIN(AN37, 'Lifestyle Strategy'!$Q$11), 0) -> 0 | AZ37: =IF(B37='Lifestyle Strategy'!$Q$10, 'Lifestyle Strategy'!$Q$11, 0) -> 0 | BA37: =IF(B37='Lifestyle Strategy'!$Q$10, MAX(AZ37 - AY37, 0), 0) -> 0 | BB37: =U37+Y37+AC37+AJ37+AN37-AY37 -> 1026751.7 | BC37: =TEXT(BB37/1000000, "[$$-en-US]0.00") & "M" -> $1.03M
B38: 25 | C38: 55 | D38: =IF(B38<>$B$5,D37*(1+_xlfn.NORM.INV(RAND(),$B$3,$B$4)),D37*(1+_xlfn.NORM.INV(RAND(),$B$3,$B$4))+D37*(1+_xlfn.NORM.INV(RAND(),$B$3,$B$4))) -> 334118.38 | E38: =D38-D37 -> 10842.781 | F38: =E38/D37 -> 0.033540363 | G38: ='Tax rate cal'!C35 -> 108860.6 | H38: =$B$6*D38 -> 5579.7769 | I38: =D38-G38-H38 -> 219678 | J38: =MIN($E$2 + INT(B38/$E$3)*$E$4, $E$5) -> 0.12 | K38: 0.03 | L38: =IF(O38 = 0,0,'Lifestyle Strategy'!$Q$9) -> 0 | M38: =I38*J38 -> 26361.36 | N38: =I38*K38 -> 6590.3399 | O38: =IF(AND('Lifestyle Strategy'!$Q$2="Yes", B38 >='Lifestyle Strategy'!$Q$3), I38 * 'Lifestyle Strategy'!$Q$9, 0 ) -> 0 | P38: =IF(B38<10,0,IF(MOD(B38, $E$6) = 0, $E$7, 0)) -> 10000 | Q38: =M38+N38+O38+P38 -> 42951.699 | R38: =IF(B38<=5, Q38*'Fund Allocation Strategy'!$B$2, IF(B38<=10, Q38*'Fund Allocation Strategy'!$B$3, IF(B38<=15, Q38*'Fund Allocation Strategy'!$B$4, IF(B38<=20, Q38*'Fund Allocation Strategy'!$B$5, IF(B38<=25, Q38*'Fund Allocation Strategy'!$B$6, IF(B38<=30, Q38*'Fund Allocation Strategy'!$B$7, Q38*'Fund Allocation Strategy'!$B$8)))))) -> 12885.51 | S38: =_xlfn.NORM.INV(RAND(),'Fund Allocation Strategy'!$B$11,'Fund Allocation Strategy'!$C$11) -> 0.037456258 | T38: =U37*S38+(R38*S38*0.5) -> 4513.32 | U38: =U37+R38+T38 -> 131451.83 | V38: =IF(B38<=5, Q38*'Fund Allocation Strategy'!$C$2, IF(B38<=10, Q38*'Fund Allocation Strategy'!$C$3, IF(B38<=15, Q38*'Fund Allocation Strategy'!$C$4, IF(B38<=20, Q38*'Fund Allocation Strategy'!$C$5, IF(B38<=25, Q38*'Fund Allocation Strategy'!$C$6, IF(B38<=30, Q38*'Fund Allocation Strategy'!$C$7, Q38*'Fund Allocation Strategy'!$C$8)))))) -> 12885.51 | W38: =_xlfn.NORM.INV(RAND(),'Fund Allocation Strategy'!$B$12,'Fund Allocation Strategy'!$C$12) -> 0.069376255 | X38: =Y37*W38 + (V38*W38*0.5) -> 11822.212 | Y38: =Y37+V38+X38 -> 188672.15 | Z38: =IF(B38<=5, Q38*'Fund Allocation Strategy'!$D$2, IF(B38<=10, Q38*'Fund Allocation Strategy'!$D$3, IF(B38<=15, Q38*'Fund Allocation Strategy'!$D$4, IF(B38<=20, Q38*'Fund Allocation Strategy'!$D$5, IF(B38<=25, Q38*'Fund Allocation Strategy'!$D$6, IF(B38<=30, Q38*'Fund Allocation Strategy'!$D$7, Q38*'Fund Allocation Strategy'!$D$8)))))) -> 10737.925 | AA38: =_xlfn.NORM.INV(RAND(),'Fund Allocation Strategy'!$B$13,'Fund Allocation Strategy'!$C$13) -> 0.10060746 | AB38: =AC37*AA38+(Z38*AA38*0.5) -> 43090.572 | AC38: =AC37+Z38+AB38 -> 476763.47 | AD38: =IF(B38<=5, Q38*'Fund Allocation Strategy'!$E$2, IF(B38<=10, Q38*'Fund Allocation Strategy'!$E$3, IF(B38<=15, Q38*'Fund Allocation Strategy'!$E$4, IF(B38<=20, Q38*'Fund Allocation Strategy'!$E$5, IF(B38<=25, Q38*'Fund Allocation Strategy'!$E$6, IF(B38<=30, Q38*'Fund Allocation Strategy'!$E$7, Q38*'Fund Allocation Strategy'!$E$8)))))) -> 4295.1699 | AE38: =_xlfn.NORM.INV(RAND(), 'Fund Allocation Strategy'!$B$14, 'Fund Allocation Strategy'!$C$14) + _xlfn.NORM.INV(RAND(), 'Fund Allocation Strategy'!$D$14,'Fund Allocation Strategy'!$E$14) -> 0.17955687 | AF38: =AM37*AE38+(AD38*AE38*0.5) -> 52128.37 | AG38: =IF(B38<=5, Q38*'Fund Allocation Strategy'!$F$2, IF(B38<=10, Q38*'Fund Allocation Strategy'!$F$3, IF(B38<=15, Q38*'Fund Allocation Strategy'!$F$4, IF(B38<=20, Q38*'Fund Allocation Strategy'!$F$5, IF(B38<=25, Q38*'Fund Allocation Strategy'!$F$6, IF(B38<=30, Q38*'Fund Allocation Strategy'!$F$7, Q38*'Fund Allocation Strategy'!$F$8)))))) -> 2147.585 | AH38: =_xlfn.NORM.INV(RAND(),'Fund Allocation Strategy'!$B$15,'Fund Allocation Strategy'!$C$15) -> 0.20113267 | AI38: =AI37*AH38+(AG38*AH38*0.5) -> 258.34865 | AJ38: =AJ37+AG38+AI38 -> 44358.634 | AK38: =IF(AM38<50000,0, AM38*0.015) -> 5168.8909 | AL38: =IF(AM38<50000,0,0.015) -> 0.015 | AM38: =AM37+AD38+AF38 -> 344592.73 | AN38: =AM38-AK38 -> 339423.84 | AO38: =IF(AV38 = 0, I38 * ( 'Lifestyle Strategy'!$B$2 + ('Lifestyle Strategy'!$C$2 - 'Lifestyle Strategy'!$B$2) * _xlfn.BETA.INV(RAND(), 'Lifestyle Strategy'!$F$2, 'Lifestyle Strategy'!$G$2) ),IF(AV38 = "", "",0)) | AP38: =I38 * ( 'Lifestyle Strategy'!$B$3 + ('Lifestyle Strategy'!$C$3 - 'Lifestyle Strategy'!$B$3) * _xlfn.BETA.INV(RAND(), 'Lifestyle Strategy'!$F$3, 'Lifestyle Strategy'!$G$3) ) * IF(MOD(B38,5)=0, 1 + 'Lifestyle Strategy'!$M$4, 1 + 0.025) -> 28250.47 | AQ38: =I38 * ( 'Lifestyle Strategy'!$B$4 + ('Lifestyle Strategy'!$C$4 - 'Lifestyle Strategy'!$B$4) * _xlfn.BETA.INV(RAND(), 'Lifestyle Strategy'!$F$4, 'Lifestyle Strategy'!$G$4) ) * IF(MOD(B38,5)=0, 1 + 'Lifestyle Strategy'!$M$4, 1 + 0.025) -> 21614.531 | AR38: =I38 * ( 'Lifestyle Strategy'!$B$5 + ('Lifestyle Strategy'!$C$5 - 'Lifestyle Strategy'!$B$5) * _xlfn.BETA.INV(RAND(), 'Lifestyle Strategy'!$F$5, 'Lifestyle Strategy'!$G$5) ) * IF(MOD(B38,5)=0, 1 + 'Lifestyle Strategy'!$M$4, 1 + 0.025) -> 12443.969 | AS38: =I38 * ( 'Lifestyle Strategy'!$B$6 + ('Lifestyle Strategy'!$C$6 - 'Lifestyle Strategy'!$B$6) * _xlfn.BETA.INV(RAND(), 'Lifestyle Strategy'!$F$6, 'Lifestyle Strategy'!$G$6) ) * IF(MOD(B38,5)=0, 1 + 'Lifestyle Strategy'!$M$4, 1 + 0.025) -> 12988.661 | AT38: =I38 * ( 'Lifestyle Strategy'!$B$7 + ('Lifestyle Strategy'!$C$7 - 'Lifestyle Strategy'!$B$7) * _xlfn.BETA.INV(RAND(), 'Lifestyle Strategy'!$F$7, 'Lifestyle Strategy'!$G$7) ) * IF(MOD(B38,5)=0, 1 + 'Lifestyle Strategy'!$M$4, 1 + 0.025) -> 20741.631 | AU38: =I38 * ( 'Lifestyle Strategy'!$B$8 + ('Lifestyle Strategy'!$C$8 - 'Lifestyle Strategy'!$B$8) * _xlfn.BETA.INV(RAND(), 'Lifestyle Strategy'!$F$8, 'Lifestyle Strategy'!$G$8) ) * IF(MOD(B38,5)=0, 1 + 'Lifestyle Strategy'!$M$4, 1 + 0.025) -> 9825.0496 | AV38: =IF('Lifestyle Strategy'!$B$14 = "Yes", IF(AND(B38>='Lifestyle Strategy'!$B$15, B38<'Lifestyle Strategy'!$B$16), 'Lifestyle Strategy'!$B$25, IF(B38>='Lifestyle Strategy'!$B$16, "", 0) ), 0 ) | AW38: =IF('Lifestyle Strategy'!$Q$4="No", 0, IF(AND(B38>='Lifestyle Strategy'!$Q$5, B38<'Lifestyle Strategy'!$Q$6), 'Lifestyle Strategy'!$Q$8 * (1.025^(B38-'Lifestyle Strategy'!$Q$5)) * (1.12^INT((B38-'Lifestyle Strategy'!$Q$5)/5)), 0 ) ) -> 0 | AX38: =IF(AO38 = "",0,AO38)+AP38+AQ38+AR38+AS38+AT38+AU38+AW38+IF(AV38 = "",0,AV38) -> 105864.31 | AY38: =IF(B38='Lifestyle Strategy'!$Q$10, MIN(AN38, 'Lifestyle Strategy'!$Q$11), 0) -> 0 | AZ38: =IF(B38='Lifestyle Strategy'!$Q$10, 'Lifestyle Strategy'!$Q$11, 0) -> 0 | BA38: =IF(B38='Lifestyle Strategy'!$Q$10, MAX(AZ38 - AY38, 0), 0) -> 0 | BB38: =U38+Y38+AC38+AJ38+AN38-AY38 -> 1180669.9 | BC38: =TEXT(BB38/1000000, "[$$-en-US]0.00") & "M" -> $1.18M
B39: 26 | C39: 56 | D39: =IF(B39<>$B$5,D38*(1+_xlfn.NORM.INV(RAND(),$B$3,$B$4)),D38*(1+_xlfn.NORM.INV(RAND(),$B$3,$B$4))+D38*(1+_xlfn.NORM.INV(RAND(),$B$3,$B$4))) -> 345790.11 | E39: =D39-D38 -> 11671.731 | F39: =E39/D38 -> 0.034932923 | G39: ='Tax rate cal'!C36 -> 113412.58 | H39: =$B$6*D39 -> 5774.6948 | I39: =D39-G39-H39 -> 226602.83 | J39: =MIN($E$2 + INT(B39/$E$3)*$E$4, $E$5) -> 0.12 | K39: 0.03 | L39: =IF(O39 = 0,0,'Lifestyle Strategy'!$Q$9) -> 0 | M39: =I39*J39 -> 27192.34 | N39: =I39*K39 -> 6798.085 | O39: =IF(AND('Lifestyle Strategy'!$Q$2="Yes", B39 >='Lifestyle Strategy'!$Q$3), I39 * 'Lifestyle Strategy'!$Q$9, 0 ) -> 0 | P39: =IF(B39<10,0,IF(MOD(B39, $E$6) = 0, $E$7, 0)) -> 0 | Q39: =M39+N39+O39+P39 -> 33990.425 | R39: =IF(B39<=5, Q39*'Fund Allocation Strategy'!$B$2, IF(B39<=10, Q39*'Fund Allocation Strategy'!$B$3, IF(B39<=15, Q39*'Fund Allocation Strategy'!$B$4, IF(B39<=20, Q39*'Fund Allocation Strategy'!$B$5, IF(B39<=25, Q39*'Fund Allocation Strategy'!$B$6, IF(B39<=30, Q39*'Fund Allocation Strategy'!$B$7, Q39*'Fund Allocation Strategy'!$B$8)))))) -> 13596.17 | S39: =_xlfn.NORM.INV(RAND(),'Fund Allocation Strategy'!$B$11,'Fund Allocation Strategy'!$C$11) -> 0.037516345 | T39: =U38*S39+(R39*S39*0.5) -> 5186.6315 | U39: =U38+R39+T39 -> 150234.63 | V39: =IF(B39<=5, Q39*'Fund Allocation Strategy'!$C$2, IF(B39<=10, Q39*'Fund Allocation Strategy'!$C$3, IF(B39<=15, Q39*'Fund Allocation Strategy'!$C$4, IF(B39<=20, Q39*'Fund Allocation Strategy'!$C$5, IF(B39<=25, Q39*'Fund Allocation Strategy'!$C$6, IF(B39<=30, Q39*'Fund Allocation Strategy'!$C$7, Q39*'Fund Allocation Strategy'!$C$8)))))) -> 11896.649 | W39: =_xlfn.NORM.INV(RAND(),'Fund Allocation Strategy'!$B$12,'Fund Allocation Strategy'!$C$12) -> 0.068269307 | X39: =Y38*W39 + (V39*W39*0.5) -> 13286.605 | Y39: =Y38+V39+X39 -> 213855.4 | Z39: =IF(B39<=5, Q39*'Fund Allocation Strategy'!$D$2, IF(B39<=10, Q39*'Fund Allocation Strategy'!$D$3, IF(B39<=15, Q39*'Fund Allocation Strategy'!$D$4, IF(B39<=20, Q39*'Fund Allocation Strategy'!$D$5, IF(B39<=25, Q39*'Fund Allocation Strategy'!$D$6, IF(B39<=30, Q39*'Fund Allocation Strategy'!$D$7, Q39*'Fund Allocation Strategy'!$D$8)))))) -> 6798.085 | AA39: =_xlfn.NORM.INV(RAND(),'Fund Allocation Strategy'!$B$13,'Fund Allocation Strategy'!$C$13) -> 0.10173889 | AB39: =AC38*AA39+(Z39*AA39*0.5) -> 48851.203 | AC39: =AC38+Z39+AB39 -> 532412.76 | AD39: =IF(B39<=5, Q39*'Fund Allocation Strategy'!$E$2, IF(B39<=10, Q39*'Fund Allocation Strategy'!$E$3, IF(B39<=15, Q39*'Fund Allocation Strategy'!$E$4, IF(B39<=20, Q39*'Fund Allocation Strategy'!$E$5, IF(B39<=25, Q39*'Fund Allocation Strategy'!$E$6, IF(B39<=30, Q39*'Fund Allocation Strategy'!$E$7, Q39*'Fund Allocation Strategy'!$E$8)))))) -> 1699.5213 | AE39: =_xlfn.NORM.INV(RAND(), 'Fund Allocation Strategy'!$B$14, 'Fund Allocation Strategy'!$C$14) + _xlfn.NORM.INV(RAND(), 'Fund Allocation Strategy'!$D$14,'Fund Allocation Strategy'!$E$14) -> 0.12624019 | AF39: =AM38*AE39+(AD39*AE39*0.5) -> 43608.725 | AG39: =IF(B39<=5, Q39*'Fund Allocation Strategy'!$F$2, IF(B39<=10, Q39*'Fund Allocation Strategy'!$F$3, IF(B39<=15, Q39*'Fund Allocation Strategy'!$F$4, IF(B39<=20, Q39*'Fund Allocation Strategy'!$F$5, IF(B39<=25, Q39*'Fund Allocation Strategy'!$F$6, IF(B39<=30, Q39*'Fund Allocation Strategy'!$F$7, Q39*'Fund Allocation Strategy'!$F$8)))))) -> 0 | AH39: =_xlfn.NORM.INV(RAND(),'Fund Allocation Strategy'!$B$15,'Fund Allocation Strategy'!$C$15) -> 0.21250432 | AI39: =AI38*AH39+(AG39*AH39*0.5) -> 54.900203 | AJ39: =AJ38+AG39+AI39 -> 44413.534 | AK39: =IF(AM39<50000,0, AM39*0.015) -> 5848.5146 | AL39: =IF(AM39<50000,0,0.015) -> 0.015 | AM39: =AM38+AD39+AF39 -> 389900.97 | AN39: =AM39-AK39 -> 384052.46 | AO39: =IF(AV39 = 0, I39 * ( 'Lifestyle Strategy'!$B$2 + ('Lifestyle Strategy'!$C$2 - 'Lifestyle Strategy'!$B$2) * _xlfn.BETA.INV(RAND(), 'Lifestyle Strategy'!$F$2, 'Lifestyle Strategy'!$G$2) ),IF(AV39 = "", "",0)) | AP39: =I39 * ( 'Lifestyle Strategy'!$B$3 + ('Lifestyle Strategy'!$C$3 - 'Lifestyle Strategy'!$B$3) * _xlfn.BETA.INV(RAND(), 'Lifestyle Strategy'!$F$3, 'Lifestyle Strategy'!$G$3) ) * IF(MOD(B39,5)=0, 1 + 'Lifestyle Strategy'!$M$4, 1 + 0.025) -> 26833.205 | AQ39: =I39 * ( 'Lifestyle Strategy'!$B$4 + ('Lifestyle Strategy'!$C$4 - 'Lifestyle Strategy'!$B$4) * _xlfn.BETA.INV(RAND(), 'Lifestyle Strategy'!$F$4, 'Lifestyle Strategy'!$G$4) ) * IF(MOD(B39,5)=0, 1 + 'Lifestyle Strategy'!$M$4, 1 + 0.025) -> 15954.727 | AR39: =I39 * ( 'Lifestyle Strategy'!$B$5 + ('Lifestyle Strategy'!$C$5 - 'Lifestyle Strategy'!$B$5) * _xlfn.BETA.INV(RAND(), 'Lifestyle Strategy'!$F$5, 'Lifestyle Strategy'!$G$5) ) * IF(MOD(B39,5)=0, 1 + 'Lifestyle Strategy'!$M$4, 1 + 0.025) -> 11666.73 | AS39: =I39 * ( 'Lifestyle Strategy'!$B$6 + ('Lifestyle Strategy'!$C$6 - 'Lifestyle Strategy'!$B$6) * _xlfn.BETA.INV(RAND(), 'Lifestyle Strategy'!$F$6, 'Lifestyle Strategy'!$G$6) ) * IF(MOD(B39,5)=0, 1 + 'Lifestyle Strategy'!$M$4, 1 + 0.025) -> 12159.334 | AT39: =I39 * ( 'Lifestyle Strategy'!$B$7 + ('Lifestyle Strategy'!$C$7 - 'Lifestyle Strategy'!$B$7) * _xlfn.BETA.INV(RAND(), 'Lifestyle Strategy'!$F$7, 'Lifestyle Strategy'!$G$7) ) * IF(MOD(B39,5)=0, 1 + 'Lifestyle Strategy'!$M$4, 1 + 0.025) -> 25492.348 | AU39: =I39 * ( 'Lifestyle Strategy'!$B$8 + ('Lifestyle Strategy'!$C$8 - 'Lifestyle Strategy'!$B$8) * _xlfn.BETA.INV(RAND(), 'Lifestyle Strategy'!$F$8, 'Lifestyle Strategy'!$G$8) ) * IF(MOD(B39,5)=0, 1 + 'Lifestyle Strategy'!$M$4, 1 + 0.025) -> 7219.0919 | AV39: =IF('Lifestyle Strategy'!$B$14 = "Yes", IF(AND(B39>='Lifestyle Strategy'!$B$15, B39<'Lifestyle Strategy'!$B$16), 'Lifestyle Strategy'!$B$25, IF(B39>='Lifestyle Strategy'!$B$16, "", 0) ), 0 ) | AW39: =IF('Lifestyle Strategy'!$Q$4="No", 0, IF(AND(B39>='Lifestyle Strategy'!$Q$5, B39<'Lifestyle Strategy'!$Q$6), 'Lifestyle Strategy'!$Q$8 * (1.025^(B39-'Lifestyle Strategy'!$Q$5)) * (1.12^INT((B39-'Lifestyle Strategy'!$Q$5)/5)), 0 ) ) -> 0 | AX39: =IF(AO39 = "",0,AO39)+AP39+AQ39+AR39+AS39+AT39+AU39+AW39+IF(AV39 = "",0,AV39) -> 99325.436 | AY39: =IF(B39='Lifestyle Strategy'!$Q$10, MIN(AN39, 'Lifestyle Strategy'!$Q$11), 0) -> 0 | AZ39: =IF(B39='Lifestyle Strategy'!$Q$10, 'Lifestyle Strategy'!$Q$11, 0) -> 0 | BA39: =IF(B39='Lifestyle Strategy'!$Q$10, MAX(AZ39 - AY39, 0), 0) -> 0 | BB39: =U39+Y39+AC39+AJ39+AN39-AY39 -> 1324968.8 | BC39: =TEXT(BB39/1000000, "[$$-en-US]0.00") & "M" -> $1.32M | BT39: Total corpus | BU39: =SUM(BU40:BU41) -> 7377774.6
B40: 27 | C40: 57 | D40: =IF(B40<>$B$5,D39*(1+_xlfn.NORM.INV(RAND(),$B$3,$B$4)),D39*(1+_xlfn.NORM.INV(RAND(),$B$3,$B$4))+D39*(1+_xlfn.NORM.INV(RAND(),$B$3,$B$4))) -> 356329.72 | E40: =D40-D39 -> 10539.615 | F40: =E40/D39 -> 0.030479805 | G40: ='Tax rate cal'!C37 -> 117523.03 | H40: =$B$6*D40 -> 5950.7064 | I40: =D40-G40-H40 -> 232855.99 | J40: =MIN($E$2 + INT(B40/$E$3)*$E$4, $E$5) -> 0.12 | K40: 0.03 | L40: =IF(O40 = 0,0,'Lifestyle Strategy'!$Q$9) -> 0 | M40: =I40*J40 -> 27942.719 | N40: =I40*K40 -> 6985.6796 | O40: =IF(AND('Lifestyle Strategy'!$Q$2="Yes", B40 >='Lifestyle Strategy'!$Q$3), I40 * 'Lifestyle Strategy'!$Q$9, 0 ) -> 0 | P40: =IF(B40<10,0,IF(MOD(B40, $E$6) = 0, $E$7, 0)) -> 0 | Q40: =M40+N40+O40+P40 -> 34928.398 | R40: =IF(B40<=5, Q40*'Fund Allocation Strategy'!$B$2, IF(B40<=10, Q40*'Fund Allocation Strategy'!$B$3, IF(B40<=15, Q40*'Fund Allocation Strategy'!$B$4, IF(B40<=20, Q40*'Fund Allocation Strategy'!$B$5, IF(B40<=25, Q40*'Fund Allocation Strategy'!$B$6, IF(B40<=30, Q40*'Fund Allocation Strategy'!$B$7, Q40*'Fund Allocation Strategy'!$B$8)))))) -> 13971.359 | S40: =_xlfn.NORM.INV(RAND(),'Fund Allocation Strategy'!$B$11,'Fund Allocation Strategy'!$C$11) -> 0.036300093 | T40: =U39*S40+(R40*S40*0.5) -> 5707.1119 | U40: =U39+R40+T40 -> 169913.1 | V40: =IF(B40<=5, Q40*'Fund Allocation Strategy'!$C$2, IF(B40<=10, Q40*'Fund Allocation Strategy'!$C$3, IF(B40<=15, Q40*'Fund Allocation Strategy'!$C$4, IF(B40<=20, Q40*'Fund Allocation Strategy'!$C$5, IF(B40<=25, Q40*'Fund Allocation Strategy'!$C$6, IF(B40<=30, Q40*'Fund Allocation Strategy'!$C$7, Q40*'Fund Allocation Strategy'!$C$8)))))) -> 12224.939 | W40: =_xlfn.NORM.INV(RAND(),'Fund Allocation Strategy'!$B$12,'Fund Allocation Strategy'!$C$12) -> 0.070472627 | X40: =Y39*W40 + (V40*W40*0.5) -> 15501.714 | Y40: =Y39+V40+X40 -> 241582.06 | Z40: =IF(B40<=5, Q40*'Fund Allocation Strategy'!$D$2, IF(B40<=10, Q40*'Fund Allocation Strategy'!$D$3, IF(B40<=15, Q40*'Fund Allocation Strategy'!$D$4, IF(B40<=20, Q40*'Fund Allocation Strategy'!$D$5, IF(B40<=25, Q40*'Fund Allocation Strategy'!$D$6, IF(B40<=30, Q40*'Fund Allocation Strategy'!$D$7, Q40*'Fund Allocation Strategy'!$D$8)))))) -> 6985.6796 | AA40: =_xlfn.NORM.INV(RAND(),'Fund Allocation Strategy'!$B$13,'Fund Allocation Strategy'!$C$13) -> 0.099998137 | AB40: =AC39*AA40+(Z40*AA40*0.5) -> 53589.561 | AC40: =AC39+Z40+AB40 -> 592988 | AD40: =IF(B40<=5, Q40*'Fund Allocation Strategy'!$E$2, IF(B40<=10, Q40*'Fund Allocation Strategy'!$E$3, IF(B40<=15, Q40*'Fund Allocation Strategy'!$E$4, IF(B40<=20, Q40*'Fund Allocation Strategy'!$E$5, IF(B40<=25, Q40*'Fund Allocation Strategy'!$E$6, IF(B40<=30, Q40*'Fund Allocation Strategy'!$E$7, Q40*'Fund Allocation Strategy'!$E$8)))))) -> 1746.4199 | AE40: =_xlfn.NORM.INV(RAND(), 'Fund Allocation Strategy'!$B$14, 'Fund Allocation Strategy'!$C$14) + _xlfn.NORM.INV(RAND(), 'Fund Allocation Strategy'!$D$14,'Fund Allocation Strategy'!$E$14) -> 0.12778838 | AF40: =AM39*AE40+(AD40*AE40*0.5) -> 49936.402 | AG40: =IF(B40<=5, Q40*'Fund Allocation Strategy'!$F$2, IF(B40<=10, Q40*'Fund Allocation Strategy'!$F$3, IF(B40<=15, Q40*'Fund Allocation Strategy'!$F$4, IF(B40<=20, Q40*'Fund Allocation Strategy'!$F$5, IF(B40<=25, Q40*'Fund Allocation Strategy'!$F$6, IF(B40<=30, Q40*'Fund Allocation Strategy'!$F$7, Q40*'Fund Allocation Strategy'!$F$8)))))) -> 0 | AH40: =_xlfn.NORM.INV(RAND(),'Fund Allocation Strategy'!$B$15,'Fund Allocation Strategy'!$C$15) -> 0.20886265 | AI40: =AI39*AH40+(AG40*AH40*0.5) -> 11.466602 | AJ40: =AJ39+AG40+AI40 -> 44425.001 | AK40: =IF(AM40<50000,0, AM40*0.015) -> 6623.7569 | AL40: =IF(AM40<50000,0,0.015) -> 0.015 | AM40: =AM39+AD40+AF40 -> 441583.8 | AN40: =AM40-AK40 -> 434960.04 | AO40: =IF(AV40 = 0, I40 * ( 'Lifestyle Strategy'!$B$2 + ('Lifestyle Strategy'!$C$2 - 'Lifestyle Strategy'!$B$2) * _xlfn.BETA.INV(RAND(), 'Lifestyle Strategy'!$F$2, 'Lifestyle Strategy'!$G$2) ),IF(AV40 = "", "",0)) | AP40: =I40 * ( 'Lifestyle Strategy'!$B$3 + ('Lifestyle Strategy'!$C$3 - 'Lifestyle Strategy'!$B$3) * _xlfn.BETA.INV(RAND(), 'Lifestyle Strategy'!$F$3, 'Lifestyle Strategy'!$G$3) ) * IF(MOD(B40,5)=0, 1 + 'Lifestyle Strategy'!$M$4, 1 + 0.025) -> 33673.103 | AQ40: =I40 * ( 'Lifestyle Strategy'!$B$4 + ('Lifestyle Strategy'!$C$4 - 'Lifestyle Strategy'!$B$4) * _xlfn.BETA.INV(RAND(), 'Lifestyle Strategy'!$F$4, 'Lifestyle Strategy'!$G$4) ) * IF(MOD(B40,5)=0, 1 + 'Lifestyle Strategy'!$M$4, 1 + 0.025) -> 23262.102 | AR40: =I40 * ( 'Lifestyle Strategy'!$B$5 + ('Lifestyle Strategy'!$C$5 - 'Lifestyle Strategy'!$B$5) * _xlfn.BETA.INV(RAND(), 'Lifestyle Strategy'!$F$5, 'Lifestyle Strategy'!$G$5) ) * IF(MOD(B40,5)=0, 1 + 'Lifestyle Strategy'!$M$4, 1 + 0.025) -> 10745.671 | AS40: =I40 * ( 'Lifestyle Strategy'!$B$6 + ('Lifestyle Strategy'!$C$6 - 'Lifestyle Strategy'!$B$6) * _xlfn.BETA.INV(RAND(), 'Lifestyle Strategy'!$F$6, 'Lifestyle Strategy'!$G$6) ) * IF(MOD(B40,5)=0, 1 + 'Lifestyle Strategy'!$M$4, 1 + 0.025) -> 12439.805 | AT40: =I40 * ( 'Lifestyle Strategy'!$B$7 + ('Lifestyle Strategy'!$C$7 - 'Lifestyle Strategy'!$B$7) * _xlfn.BETA.INV(RAND(), 'Lifestyle Strategy'!$F$7, 'Lifestyle Strategy'!$G$7) ) * IF(MOD(B40,5)=0, 1 + 'Lifestyle Strategy'!$M$4, 1 + 0.025) -> 26765.287 | AU40: =I40 * ( 'Lifestyle Strategy'!$B$8 + ('Lifestyle Strategy'!$C$8 - 'Lifestyle Strategy'!$B$8) * _xlfn.BETA.INV(RAND(), 'Lifestyle Strategy'!$F$8, 'Lifestyle Strategy'!$G$8) ) * IF(MOD(B40,5)=0, 1 + 'Lifestyle Strategy'!$M$4, 1 + 0.025) -> 9264.8419 | AV40: =IF('Lifestyle Strategy'!$B$14 = "Yes", IF(AND(B40>='Lifestyle Strategy'!$B$15, B40<'Lifestyle Strategy'!$B$16), 'Lifestyle Strategy'!$B$25, IF(B40>='Lifestyle Strategy'!$B$16, "", 0) ), 0 ) | AW40: =IF('Lifestyle Strategy'!$Q$4="No", 0, IF(AND(B40>='Lifestyle Strategy'!$Q$5, B40<'Lifestyle Strategy'!$Q$6), 'Lifestyle Strategy'!$Q$8 * (1.025^(B40-'Lifestyle Strategy'!$Q$5)) * (1.12^INT((B40-'Lifestyle Strategy'!$Q$5)/5)), 0 ) ) -> 0 | AX40: =IF(AO40 = "",0,AO40)+AP40+AQ40+AR40+AS40+AT40+AU40+AW40+IF(AV40 = "",0,AV40) -> 116150.81 | AY40: =IF(B40='Lifestyle Strategy'!$Q$10, MIN(AN40, 'Lifestyle Strategy'!$Q$11), 0) -> 0 | AZ40: =IF(B40='Lifestyle Strategy'!$Q$10, 'Lifestyle Strategy'!$Q$11, 0) -> 0 | BA40: =IF(B40='Lifestyle Strategy'!$Q$10, MAX(AZ40 - AY40, 0), 0) -> 0 | BB40: =U40+Y40+AC40+AJ40+AN40-AY40 -> 1483868.2 | BC40: =TEXT(BB40/1000000, "[$$-en-US]0.00") & "M" -> $1.48M | BT40: Pre | BU40: =BB48 -> 4804031.4
B41: 28 | C41: 58 | D41: =IF(B41<>$B$5,D40*(1+_xlfn.NORM.INV(RAND(),$B$3,$B$4)),D40*(1+_xlfn.NORM.INV(RAND(),$B$3,$B$4))+D40*(1+_xlfn.NORM.INV(RAND(),$B$3,$B$4))) -> 362943.07 | E41: =D41-D40 -> 6613.3438 | F41: =E41/D40 -> 0.018559619 | G41: ='Tax rate cal'!C38 -> 120102.23 | H41: =$B$6*D41 -> 6061.1492 | I41: =D41-G41-H41 -> 236779.68 | J41: =MIN($E$2 + INT(B41/$E$3)*$E$4, $E$5) -> 0.12 | K41: 0.03 | L41: =IF(O41 = 0,0,'Lifestyle Strategy'!$Q$9) -> 0 | M41: =I41*J41 -> 28413.562 | N41: =I41*K41 -> 7103.3905 | O41: =IF(AND('Lifestyle Strategy'!$Q$2="Yes", B41 >='Lifestyle Strategy'!$Q$3), I41 * 'Lifestyle Strategy'!$Q$9, 0 ) -> 0 | P41: =IF(B41<10,0,IF(MOD(B41, $E$6) = 0, $E$7, 0)) -> 0 | Q41: =M41+N41+O41+P41 -> 35516.953 | R41: =IF(B41<=5, Q41*'Fund Allocation Strategy'!$B$2, IF(B41<=10, Q41*'Fund Allocation Strategy'!$B$3, IF(B41<=15, Q41*'Fund Allocation Strategy'!$B$4, IF(B41<=20, Q41*'Fund Allocation Strategy'!$B$5, IF(B41<=25, Q41*'Fund Allocation Strategy'!$B$6, IF(B41<=30, Q41*'Fund Allocation Strategy'!$B$7, Q41*'Fund Allocation Strategy'!$B$8)))))) -> 14206.781 | S41: =_xlfn.NORM.INV(RAND(),'Fund Allocation Strategy'!$B$11,'Fund Allocation Strategy'!$C$11) -> 0.03688517 | T41: =U40*S41+(R41*S41*0.5) -> 6529.2834 | U41: =U40+R41+T41 -> 190649.17 | V41: =IF(B41<=5, Q41*'Fund Allocation Strategy'!$C$2, IF(B41<=10, Q41*'Fund Allocation Strategy'!$C$3, IF(B41<=15, Q41*'Fund Allocation Strategy'!$C$4, IF(B41<=20, Q41*'Fund Allocation Strategy'!$C$5, IF(B41<=25, Q41*'Fund Allocation Strategy'!$C$6, IF(B41<=30, Q41*'Fund Allocation Strategy'!$C$7, Q41*'Fund Allocation Strategy'!$C$8)))))) -> 12430.933 | W41: =_xlfn.NORM.INV(RAND(),'Fund Allocation Strategy'!$B$12,'Fund Allocation Strategy'!$C$12) -> 0.068644118 | X41: =Y40*W41 + (V41*W41*0.5) -> 17009.842 | Y41: =Y40+V41+X41 -> 271022.83 | Z41: =IF(B41<=5, Q41*'Fund Allocation Strategy'!$D$2, IF(B41<=10, Q41*'Fund Allocation Strategy'!$D$3, IF(B41<=15, Q41*'Fund Allocation Strategy'!$D$4, IF(B41<=20, Q41*'Fund Allocation Strategy'!$D$5, IF(B41<=25, Q41*'Fund Allocation Strategy'!$D$6, IF(B41<=30, Q41*'Fund Allocation Strategy'!$D$7, Q41*'Fund Allocation Strategy'!$D$8)))))) -> 7103.3905 | AA41: =_xlfn.NORM.INV(RAND(),'Fund Allocation Strategy'!$B$13,'Fund Allocation Strategy'!$C$13) -> 0.1041464 | AB41: =AC40*AA41+(Z41*AA41*0.5) -> 62127.462 | AC41: =AC40+Z41+AB41 -> 662218.85 | AD41: =IF(B41<=5, Q41*'Fund Allocation Strategy'!$E$2, IF(B41<=10, Q41*'Fund Allocation Strategy'!$E$3, IF(B41<=15, Q41*'Fund Allocation Strategy'!$E$4, IF(B41<=20, Q41*'Fund Allocation Strategy'!$E$5, IF(B41<=25, Q41*'Fund Allocation Strategy'!$E$6, IF(B41<=30, Q41*'Fund Allocation Strategy'!$E$7, Q41*'Fund Allocation Strategy'!$E$8)))))) -> 1775.8476 | AE41: =_xlfn.NORM.INV(RAND(), 'Fund Allocation Strategy'!$B$14, 'Fund Allocation Strategy'!$C$14) + _xlfn.NORM.INV(RAND(), 'Fund Allocation Strategy'!$D$14,'Fund Allocation Strategy'!$E$14) -> 0.10484307 | AF41: =AM40*AE41+(AD41*AE41*0.5) -> 46390.096 | AG41: =IF(B41<=5, Q41*'Fund Allocation Strategy'!$F$2, IF(B41<=10, Q41*'Fund Allocation Strategy'!$F$3, IF(B41<=15, Q41*'Fund Allocation Strategy'!$F$4, IF(B41<=20, Q41*'Fund Allocation Strategy'!$F$5, IF(B41<=25, Q41*'Fund Allocation Strategy'!$F$6, IF(B41<=30, Q41*'Fund Allocation Strategy'!$F$7, Q41*'Fund Allocation Strategy'!$F$8)))))) -> 0 | AH41: =_xlfn.NORM.INV(RAND(),'Fund Allocation Strategy'!$B$15,'Fund Allocation Strategy'!$C$15) -> 0.20537215 | AI41: =AI40*AH41+(AG41*AH41*0.5) -> 2.3549207 | AJ41: =AJ40+AG41+AI41 -> 44427.356 | AK41: =IF(AM41<50000,0, AM41*0.015) -> 7346.2461 | AL41: =IF(AM41<50000,0,0.015) -> 0.015 | AM41: =AM40+AD41+AF41 -> 489749.74 | AN41: =AM41-AK41 -> 482403.49 | AO41: =IF(AV41 = 0, I41 * ( 'Lifestyle Strategy'!$B$2 + ('Lifestyle Strategy'!$C$2 - 'Lifestyle Strategy'!$B$2) * _xlfn.BETA.INV(RAND(), 'Lifestyle Strategy'!$F$2, 'Lifestyle Strategy'!$G$2) ),IF(AV41 = "", "",0)) | AP41: =I41 * ( 'Lifestyle Strategy'!$B$3 + ('Lifestyle Strategy'!$C$3 - 'Lifestyle Strategy'!$B$3) * _xlfn.BETA.INV(RAND(), 'Lifestyle Strategy'!$F$3, 'Lifestyle Strategy'!$G$3) ) * IF(MOD(B41,5)=0, 1 + 'Lifestyle Strategy'!$M$4, 1 + 0.025) -> 27587.08 | AQ41: =I41 * ( 'Lifestyle Strategy'!$B$4 + ('Lifestyle Strategy'!$C$4 - 'Lifestyle Strategy'!$B$4) * _xlfn.BETA.INV(RAND(), 'Lifestyle Strategy'!$F$4, 'Lifestyle Strategy'!$G$4) ) * IF(MOD(B41,5)=0, 1 + 'Lifestyle Strategy'!$M$4, 1 + 0.025) -> 22480.974 | AR41: =I41 * ( 'Lifestyle Strategy'!$B$5 + ('Lifestyle Strategy'!$C$5 - 'Lifestyle Strategy'!$B$5) * _xlfn.BETA.INV(RAND(), 'Lifestyle Strategy'!$F$5, 'Lifestyle Strategy'!$G$5) ) * IF(MOD(B41,5)=0, 1 + 'Lifestyle Strategy'!$M$4, 1 + 0.025) -> 11213.133 | AS41: =I41 * ( 'Lifestyle Strategy'!$B$6 + ('Lifestyle Strategy'!$C$6 - 'Lifestyle Strategy'!$B$6) * _xlfn.BETA.INV(RAND(), 'Lifestyle Strategy'!$F$6, 'Lifestyle Strategy'!$G$6) ) * IF(MOD(B41,5)=0, 1 + 'Lifestyle Strategy'!$M$4, 1 + 0.025) -> 11006.468 | AT41: =I41 * ( 'Lifestyle Strategy'!$B$7 + ('Lifestyle Strategy'!$C$7 - 'Lifestyle Strategy'!$B$7) * _xlfn.BETA.INV(RAND(), 'Lifestyle Strategy'!$F$7, 'Lifestyle Strategy'!$G$7) ) * IF(MOD(B41,5)=0, 1 + 'Lifestyle Strategy'!$M$4, 1 + 0.025) -> 26017.167 | AU41: =I41 * ( 'Lifestyle Strategy'!$B$8 + ('Lifestyle Strategy'!$C$8 - 'Lifestyle Strategy'!$B$8) * _xlfn.BETA.INV(RAND(), 'Lifestyle Strategy'!$F$8, 'Lifestyle Strategy'!$G$8) ) * IF(MOD(B41,5)=0, 1 + 'Lifestyle Strategy'!$M$4, 1 + 0.025) -> 9158.4464 | AV41: =IF('Lifestyle Strategy'!$B$14 = "Yes", IF(AND(B41>='Lifestyle Strategy'!$B$15, B41<'Lifestyle Strategy'!$B$16), 'Lifestyle Strategy'!$B$25, IF(B41>='Lifestyle Strategy'!$B$16, "", 0) ), 0 ) | AW41: =IF('Lifestyle Strategy'!$Q$4="No", 0, IF(AND(B41>='Lifestyle Strategy'!$Q$5, B41<'Lifestyle Strategy'!$Q$6), 'Lifestyle Strategy'!$Q$8 * (1.025^(B41-'Lifestyle Strategy'!$Q$5)) * (1.12^INT((B41-'Lifestyle Strategy'!$Q$5)/5)), 0 ) ) -> 0 | AX41: =IF(AO41 = "",0,AO41)+AP41+AQ41+AR41+AS41+AT41+AU41+AW41+IF(AV41 = "",0,AV41) -> 107463.27 | AY41: =IF(B41='Lifestyle Strategy'!$Q$10, MIN(AN41, 'Lifestyle Strategy'!$Q$11), 0) -> 0 | AZ41: =IF(B41='Lifestyle Strategy'!$Q$10, 'Lifestyle Strategy'!$Q$11, 0) -> 0 | BA41: =IF(B41='Lifestyle Strategy'!$Q$10, MAX(AZ41 - AY41, 0), 0) -> 0 | BB41: =U41+Y41+AC41+AJ41+AN41-AY41 -> 1650721.7 | BC41: =TEXT(BB41/1000000, "[$$-en-US]0.00") & "M" -> $1.65M | BT41: Post | BU41: =SUM(BZ16:BZ35) -> 2573743.2
B42: 29 | C42: 59 | D42: =IF(B42<>$B$5,D41*(1+_xlfn.NORM.INV(RAND(),$B$3,$B$4)),D41*(1+_xlfn.NORM.INV(RAND(),$B$3,$B$4))+D41*(1+_xlfn.NORM.INV(RAND(),$B$3,$B$4))) -> 378503.06 | E42: =D42-D41 -> 15559.988 | F42: =E42/D41 -> 0.042871704 | G42: ='Tax rate cal'!C39 -> 126170.63 | H42: =$B$6*D42 -> 6321.001 | I42: =D42-G42-H42 -> 246011.43 | J42: =MIN($E$2 + INT(B42/$E$3)*$E$4, $E$5) -> 0.12 | K42: 0.03 | L42: =IF(O42 = 0,0,'Lifestyle Strategy'!$Q$9) -> 0 | M42: =I42*J42 -> 29521.371 | N42: =I42*K42 -> 7380.3428 | O42: =IF(AND('Lifestyle Strategy'!$Q$2="Yes", B42 >='Lifestyle Strategy'!$Q$3), I42 * 'Lifestyle Strategy'!$Q$9, 0 ) -> 0 | P42: =IF(B42<10,0,IF(MOD(B42, $E$6) = 0, $E$7, 0)) -> 0 | Q42: =M42+N42+O42+P42 -> 36901.714 | R42: =IF(B42<=5, Q42*'Fund Allocation Strategy'!$B$2, IF(B42<=10, Q42*'Fund Allocation Strategy'!$B$3, IF(B42<=15, Q42*'Fund Allocation Strategy'!$B$4, IF(B42<=20, Q42*'Fund Allocation Strategy'!$B$5, IF(B42<=25, Q42*'Fund Allocation Strategy'!$B$6, IF(B42<=30, Q42*'Fund Allocation Strategy'!$B$7, Q42*'Fund Allocation Strategy'!$B$8)))))) -> 14760.686 | S42: =_xlfn.NORM.INV(RAND(),'Fund Allocation Strategy'!$B$11,'Fund Allocation Strategy'!$C$11) -> 0.037331937 | T42: =U41*S42+(R42*S42*0.5) -> 7392.8251 | U42: =U41+R42+T42 -> 212802.68 | V42: =IF(B42<=5, Q42*'Fund Allocation Strategy'!$C$2, IF(B42<=10, Q42*'Fund Allocation Strategy'!$C$3, IF(B42<=15, Q42*'Fund Allocation Strategy'!$C$4, IF(B42<=20, Q42*'Fund Allocation Strategy'!$C$5, IF(B42<=25, Q42*'Fund Allocation Strategy'!$C$6, IF(B42<=30, Q42*'Fund Allocation Strategy'!$C$7, Q42*'Fund Allocation Strategy'!$C$8)))))) -> 12915.6 | W42: =_xlfn.NORM.INV(RAND(),'Fund Allocation Strategy'!$B$12,'Fund Allocation Strategy'!$C$12) -> 0.070464744 | X42: =Y41*W42 + (V42*W42*0.5) -> 19552.602 | Y42: =Y41+V42+X42 -> 303491.03 | Z42: =IF(B42<=5, Q42*'Fund Allocation Strategy'!$D$2, IF(B42<=10, Q42*'Fund Allocation Strategy'!$D$3, IF(B42<=15, Q42*'Fund Allocation Strategy'!$D$4, IF(B42<=20, Q42*'Fund Allocation Strategy'!$D$5, IF(B42<=25, Q42*'Fund Allocation Strategy'!$D$6, IF(B42<=30, Q42*'Fund Allocation Strategy'!$D$7, Q42*'Fund Allocation Strategy'!$D$8)))))) -> 7380.3428 | AA42: =_xlfn.NORM.INV(RAND(),'Fund Allocation Strategy'!$B$13,'Fund Allocation Strategy'!$C$13) -> 0.10043195 | AB42: =AC41*AA42+(Z42*AA42*0.5) -> 66878.542 | AC42: =AC41+Z42+AB42 -> 736477.73 | AD42: =IF(B42<=5, Q42*'Fund Allocation Strategy'!$E$2, IF(B42<=10, Q42*'Fund Allocation Strategy'!$E$3, IF(B42<=15, Q42*'Fund Allocation Strategy'!$E$4, IF(B42<=20, Q42*'Fund Allocation Strategy'!$E$5, IF(B42<=25, Q42*'Fund Allocation Strategy'!$E$6, IF(B42<=30, Q42*'Fund Allocation Strategy'!$E$7, Q42*'Fund Allocation Strategy'!$E$8)))))) -> 1845.0857 | AE42: =_xlfn.NORM.INV(RAND(), 'Fund Allocation Strategy'!$B$14, 'Fund Allocation Strategy'!$C$14) + _xlfn.NORM.INV(RAND(), 'Fund Allocation Strategy'!$D$14,'Fund Allocation Strategy'!$E$14) -> 0.40021875 | AF42: =AM41*AE42+(AD42*AE42*0.5) -> 196376.25 | AG42: =IF(B42<=5, Q42*'Fund Allocation Strategy'!$F$2, IF(B42<=10, Q42*'Fund Allocation Strategy'!$F$3, IF(B42<=15, Q42*'Fund Allocation Strategy'!$F$4, IF(B42<=20, Q42*'Fund Allocation Strategy'!$F$5, IF(B42<=25, Q42*'Fund Allocation Strategy'!$F$6, IF(B42<=30, Q42*'Fund Allocation Strategy'!$F$7, Q42*'Fund Allocation Strategy'!$F$8)))))) -> 0 | AH42: =_xlfn.NORM.INV(RAND(),'Fund Allocation Strategy'!$B$15,'Fund Allocation Strategy'!$C$15) -> 0.20490742 | AI42: =AI41*AH42+(AG42*AH42*0.5) -> 0.48254074 | AJ42: =AJ41+AG42+AI42 -> 44427.838 | AK42: =IF(AM42<50000,0, AM42*0.015) -> 10319.566 | AL42: =IF(AM42<50000,0,0.015) -> 0.015 | AM42: =AM41+AD42+AF42 -> 687971.07 | AN42: =AM42-AK42 -> 677651.51 | AO42: =IF(AV42 = 0, I42 * ( 'Lifestyle Strategy'!$B$2 + ('Lifestyle Strategy'!$C$2 - 'Lifestyle Strategy'!$B$2) * _xlfn.BETA.INV(RAND(), 'Lifestyle Strategy'!$F$2, 'Lifestyle Strategy'!$G$2) ),IF(AV42 = "", "",0)) | AP42: =I42 * ( 'Lifestyle Strategy'!$B$3 + ('Lifestyle Strategy'!$C$3 - 'Lifestyle Strategy'!$B$3) * _xlfn.BETA.INV(RAND(), 'Lifestyle Strategy'!$F$3, 'Lifestyle Strategy'!$G$3) ) * IF(MOD(B42,5)=0, 1 + 'Lifestyle Strategy'!$M$4, 1 + 0.025) -> 29566.313 | AQ42: =I42 * ( 'Lifestyle Strategy'!$B$4 + ('Lifestyle Strategy'!$C$4 - 'Lifestyle Strategy'!$B$4) * _xlfn.BETA.INV(RAND(), 'Lifestyle Strategy'!$F$4, 'Lifestyle Strategy'!$G$4) ) * IF(MOD(B42,5)=0, 1 + 'Lifestyle Strategy'!$M$4, 1 + 0.025) -> 19063.109 | AR42: =I42 * ( 'Lifestyle Strategy'!$B$5 + ('Lifestyle Strategy'!$C$5 - 'Lifestyle Strategy'!$B$5) * _xlfn.BETA.INV(RAND(), 'Lifestyle Strategy'!$F$5, 'Lifestyle Strategy'!$G$5) ) * IF(MOD(B42,5)=0, 1 + 'Lifestyle Strategy'!$M$4, 1 + 0.025) -> 12882.976 | AS42: =I42 * ( 'Lifestyle Strategy'!$B$6 + ('Lifestyle Strategy'!$C$6 - 'Lifestyle Strategy'!$B$6) * _xlfn.BETA.INV(RAND(), 'Lifestyle Strategy'!$F$6, 'Lifestyle Strategy'!$G$6) ) * IF(MOD(B42,5)=0, 1 + 'Lifestyle Strategy'!$M$4, 1 + 0.025) -> 12592.407 | AT42: =I42 * ( 'Lifestyle Strategy'!$B$7 + ('Lifestyle Strategy'!$C$7 - 'Lifestyle Strategy'!$B$7) * _xlfn.BETA.INV(RAND(), 'Lifestyle Strategy'!$F$7, 'Lifestyle Strategy'!$G$7) ) * IF(MOD(B42,5)=0, 1 + 'Lifestyle Strategy'!$M$4, 1 + 0.025) -> 23485.583 | AU42: =I42 * ( 'Lifestyle Strategy'!$B$8 + ('Lifestyle Strategy'!$C$8 - 'Lifestyle Strategy'!$B$8) * _xlfn.BETA.INV(RAND(), 'Lifestyle Strategy'!$F$8, 'Lifestyle Strategy'!$G$8) ) * IF(MOD(B42,5)=0, 1 + 'Lifestyle Strategy'!$M$4, 1 + 0.025) -> 9454.4607 | AV42: =IF('Lifestyle Strategy'!$B$14 = "Yes", IF(AND(B42>='Lifestyle Strategy'!$B$15, B42<'Lifestyle Strategy'!$B$16), 'Lifestyle Strategy'!$B$25, IF(B42>='Lifestyle Strategy'!$B$16, "", 0) ), 0 ) | AW42: =IF('Lifestyle Strategy'!$Q$4="No", 0, IF(AND(B42>='Lifestyle Strategy'!$Q$5, B42<'Lifestyle Strategy'!$Q$6), 'Lifestyle Strategy'!$Q$8 * (1.025^(B42-'Lifestyle Strategy'!$Q$5)) * (1.12^INT((B42-'Lifestyle Strategy'!$Q$5)/5)), 0 ) ) -> 0 | AX42: =IF(AO42 = "",0,AO42)+AP42+AQ42+AR42+AS42+AT42+AU42+AW42+IF(AV42 = "",0,AV42) -> 107044.85 | AY42: =IF(B42='Lifestyle Strategy'!$Q$10, MIN(AN42, 'Lifestyle Strategy'!$Q$11), 0) -> 0 | AZ42: =IF(B42='Lifestyle Strategy'!$Q$10, 'Lifestyle Strategy'!$Q$11, 0) -> 0 | BA42: =IF(B42='Lifestyle Strategy'!$Q$10, MAX(AZ42 - AY42, 0), 0) -> 0 | BB42: =U42+Y42+AC42+AJ42+AN42-AY42 -> 1974850.8 | BC42: =TEXT(BB42/1000000, "[$$-en-US]0.00") & "M" -> $1.97M | BT42: Total Spend aft post ret. | BU42: =SUM(BT16:BT35) -> 4175020
B43: 30 | C43: 60 | D43: =IF(B43<>$B$5,D42*(1+_xlfn.NORM.INV(RAND(),$B$3,$B$4)),D42*(1+_xlfn.NORM.INV(RAND(),$B$3,$B$4))+D42*(1+_xlfn.NORM.INV(RAND(),$B$3,$B$4))) -> 391160.03 | E43: =D43-D42 -> 12656.969 | F43: =E43/D42 -> 0.033439543 | G43: ='Tax rate cal'!C40 -> 131106.85 | H43: =$B$6*D43 -> 6532.3724 | I43: =D43-G43-H43 -> 253520.81 | J43: =MIN($E$2 + INT(B43/$E$3)*$E$4, $E$5) -> 0.12 | K43: 0.03 | L43: =IF(O43 = 0,0,'Lifestyle Strategy'!$Q$9) -> 0 | M43: =I43*J43 -> 30422.497 | N43: =I43*K43 -> 7605.6242 | O43: =IF(AND('Lifestyle Strategy'!$Q$2="Yes", B43 >='Lifestyle Strategy'!$Q$3), I43 * 'Lifestyle Strategy'!$Q$9, 0 ) -> 0 | P43: =IF(B43<10,0,IF(MOD(B43, $E$6) = 0, $E$7, 0)) -> 10000 | Q43: =M43+N43+O43+P43 -> 48028.121 | R43: =IF(B43<=5, Q43*'Fund Allocation Strategy'!$B$2, IF(B43<=10, Q43*'Fund Allocation Strategy'!$B$3, IF(B43<=15, Q43*'Fund Allocation Strategy'!$B$4, IF(B43<=20, Q43*'Fund Allocation Strategy'!$B$5, IF(B43<=25, Q43*'Fund Allocation Strategy'!$B$6, IF(B43<=30, Q43*'Fund Allocation Strategy'!$B$7, Q43*'Fund Allocation Strategy'!$B$8)))))) -> 19211.248 | S43: =_xlfn.NORM.INV(RAND(),'Fund Allocation Strategy'!$B$11,'Fund Allocation Strategy'!$C$11) -> 0.036975835 | T43: =U42*S43+(R43*S43*0.5) -> 8223.7326 | U43: =U42+R43+T43 -> 240237.66 | V43: =IF(B43<=5, Q43*'Fund Allocation Strategy'!$C$2, IF(B43<=10, Q43*'Fund Allocation Strategy'!$C$3, IF(B43<=15, Q43*'Fund Allocation Strategy'!$C$4, IF(B43<=20, Q43*'Fund Allocation Strategy'!$C$5, IF(B43<=25, Q43*'Fund Allocation Strategy'!$C$6, IF(B43<=30, Q43*'Fund Allocation Strategy'!$C$7, Q43*'Fund Allocation Strategy'!$C$8)))))) -> 16809.842 | W43: =_xlfn.NORM.INV(RAND(),'Fund Allocation Strategy'!$B$12,'Fund Allocation Strategy'!$C$12) -> 0.068547053 | X43: =Y42*W43 + (V43*W43*0.5) -> 21379.549 | Y43: =Y42+V43+X43 -> 341680.43 | Z43: =IF(B43<=5, Q43*'Fund Allocation Strategy'!$D$2, IF(B43<=10, Q43*'Fund Allocation Strategy'!$D$3, IF(B43<=15, Q43*'Fund Allocation Strategy'!$D$4, IF(B43<=20, Q43*'Fund Allocation Strategy'!$D$5, IF(B43<=25, Q43*'Fund Allocation Strategy'!$D$6, IF(B43<=30, Q43*'Fund Allocation Strategy'!$D$7, Q43*'Fund Allocation Strategy'!$D$8)))))) -> 9605.6242 | AA43: =_xlfn.NORM.INV(RAND(),'Fund Allocation Strategy'!$B$13,'Fund Allocation Strategy'!$C$13) -> 0.10124598 | AB43: =AC42*AA43+(Z43*AA43*0.5) -> 75051.672 | AC43: =AC42+Z43+AB43 -> 821135.03 | AD43: =IF(B43<=5, Q43*'Fund Allocation Strategy'!$E$2, IF(B43<=10, Q43*'Fund Allocation Strategy'!$E$3, IF(B43<=15, Q43*'Fund Allocation Strategy'!$E$4, IF(B43<=20, Q43*'Fund Allocation Strategy'!$E$5, IF(B43<=25, Q43*'Fund Allocation Strategy'!$E$6, IF(B43<=30, Q43*'Fund Allocation Strategy'!$E$7, Q43*'Fund Allocation Strategy'!$E$8)))))) -> 2401.406 | AE43: =_xlfn.NORM.INV(RAND(), 'Fund Allocation Strategy'!$B$14, 'Fund Allocation Strategy'!$C$14) + _xlfn.NORM.INV(RAND(), 'Fund Allocation Strategy'!$D$14,'Fund Allocation Strategy'!$E$14) -> 0.34006018 | AF43: =AM42*AE43+(AD43*AE43*0.5) -> 234359.88 | AG43: =IF(B43<=5, Q43*'Fund Allocation Strategy'!$F$2, IF(B43<=10, Q43*'Fund Allocation Strategy'!$F$3, IF(B43<=15, Q43*'Fund Allocation Strategy'!$F$4, IF(B43<=20, Q43*'Fund Allocation Strategy'!$F$5, IF(B43<=25, Q43*'Fund Allocation Strategy'!$F$6, IF(B43<=30, Q43*'Fund Allocation Strategy'!$F$7, Q43*'Fund Allocation Strategy'!$F$8)))))) -> 0 | AH43: =_xlfn.NORM.INV(RAND(),'Fund Allocation Strategy'!$B$15,'Fund Allocation Strategy'!$C$15) -> 0.20773248 | AI43: =AI42*AH43+(AG43*AH43*0.5) -> 0.10023939 | AJ43: =AJ42+AG43+AI43 -> 44427.939 | AK43: =IF(AM43<50000,0, AM43*0.015) -> 13870.985 | AL43: =IF(AM43<50000,0,0.015) -> 0.015 | AM43: =AM42+AD43+AF43 -> 924732.36 | AN43: =AM43-AK43 -> 910861.37 | AO43: =IF(AV43 = 0, I43 * ( 'Lifestyle Strategy'!$B$2 + ('Lifestyle Strategy'!$C$2 - 'Lifestyle Strategy'!$B$2) * _xlfn.BETA.INV(RAND(), 'Lifestyle Strategy'!$F$2, 'Lifestyle Strategy'!$G$2) ),IF(AV43 = "", "",0)) | AP43: =I43 * ( 'Lifestyle Strategy'!$B$3 + ('Lifestyle Strategy'!$C$3 - 'Lifestyle Strategy'!$B$3) * _xlfn.BETA.INV(RAND(), 'Lifestyle Strategy'!$F$3, 'Lifestyle Strategy'!$G$3) ) * IF(MOD(B43,5)=0, 1 + 'Lifestyle Strategy'!$M$4, 1 + 0.025) -> 32564.219 | AQ43: =I43 * ( 'Lifestyle Strategy'!$B$4 + ('Lifestyle Strategy'!$C$4 - 'Lifestyle Strategy'!$B$4) * _xlfn.BETA.INV(RAND(), 'Lifestyle Strategy'!$F$4, 'Lifestyle Strategy'!$G$4) ) * IF(MOD(B43,5)=0, 1 + 'Lifestyle Strategy'!$M$4, 1 + 0.025) -> 19283.925 | AR43: =I43 * ( 'Lifestyle Strategy'!$B$5 + ('Lifestyle Strategy'!$C$5 - 'Lifestyle Strategy'!$B$5) * _xlfn.BETA.INV(RAND(), 'Lifestyle Strategy'!$F$5, 'Lifestyle Strategy'!$G$5) ) * IF(MOD(B43,5)=0, 1 + 'Lifestyle Strategy'!$M$4, 1 + 0.025) -> 13404.82 | AS43: =I43 * ( 'Lifestyle Strategy'!$B$6 + ('Lifestyle Strategy'!$C$6 - 'Lifestyle Strategy'!$B$6) * _xlfn.BETA.INV(RAND(), 'Lifestyle Strategy'!$F$6, 'Lifestyle Strategy'!$G$6) ) * IF(MOD(B43,5)=0, 1 + 'Lifestyle Strategy'!$M$4, 1 + 0.025) -> 13900.256 | AT43: =I43 * ( 'Lifestyle Strategy'!$B$7 + ('Lifestyle Strategy'!$C$7 - 'Lifestyle Strategy'!$B$7) * _xlfn.BETA.INV(RAND(), 'Lifestyle Strategy'!$F$7, 'Lifestyle Strategy'!$G$7) ) * IF(MOD(B43,5)=0, 1 + 'Lifestyle Strategy'!$M$4, 1 + 0.025) -> 25231.625 | AU43: =I43 * ( 'Lifestyle Strategy'!$B$8 + ('Lifestyle Strategy'!$C$8 - 'Lifestyle Strategy'!$B$8) * _xlfn.BETA.INV(RAND(), 'Lifestyle Strategy'!$F$8, 'Lifestyle Strategy'!$G$8) ) * IF(MOD(B43,5)=0, 1 + 'Lifestyle Strategy'!$M$4, 1 + 0.025) -> 9569.3459 | AV43: =IF('Lifestyle Strategy'!$B$14 = "Yes", IF(AND(B43>='Lifestyle Strategy'!$B$15, B43<'Lifestyle Strategy'!$B$16), 'Lifestyle Strategy'!$B$25, IF(B43>='Lifestyle Strategy'!$B$16, "", 0) ), 0 ) | AW43: =IF('Lifestyle Strategy'!$Q$4="No", 0, IF(AND(B43>='Lifestyle Strategy'!$Q$5, B43<'Lifestyle Strategy'!$Q$6), 'Lifestyle Strategy'!$Q$8 * (1.025^(B43-'Lifestyle Strategy'!$Q$5)) * (1.12^INT((B43-'Lifestyle Strategy'!$Q$5)/5)), 0 ) ) -> 0 | AX43: =IF(AO43 = "",0,AO43)+AP43+AQ43+AR43+AS43+AT43+AU43+AW43+IF(AV43 = "",0,AV43) -> 113954.19 | AY43: =IF(B43='Lifestyle Strategy'!$Q$10, MIN(AN43, 'Lifestyle Strategy'!$Q$11), 0) -> 0 | AZ43: =IF(B43='Lifestyle Strategy'!$Q$10, 'Lifestyle Strategy'!$Q$11, 0) -> 0 | BA43: =IF(B43='Lifestyle Strategy'!$Q$10, MAX(AZ43 - AY43, 0), 0) -> 0 | BB43: =U43+Y43+AC43+AJ43+AN43-AY43 -> 2358342.4 | BC43: =TEXT(BB43/1000000, "[$$-en-US]0.00") & "M" -> $2.36M
B44: 31 | C44: 61 | D44: =IF(B44<>$B$5,D43*(1+_xlfn.NORM.INV(RAND(),$B$3,$B$4)),D43*(1+_xlfn.NORM.INV(RAND(),$B$3,$B$4))+D43*(1+_xlfn.NORM.INV(RAND(),$B$3,$B$4))) -> 403011.19 | E44: =D44-D43 -> 11851.167 | F44: =E44/D43 -> 0.03029749 | G44: ='Tax rate cal'!C41 -> 135728.8 | H44: =$B$6*D44 -> 6730.2869 | I44: =D44-G44-H44 -> 260552.1 | J44: =MIN($E$2 + INT(B44/$E$3)*$E$4, $E$5) -> 0.12 | K44: 0.03 | L44: =IF(O44 = 0,0,'Lifestyle Strategy'!$Q$9) -> 0 | M44: =I44*J44 -> 31266.252 | N44: =I44*K44 -> 7816.5631 | O44: =IF(AND('Lifestyle Strategy'!$Q$2="Yes", B44 >='Lifestyle Strategy'!$Q$3), I44 * 'Lifestyle Strategy'!$Q$9, 0 ) -> 0 | P44: =IF(B44<10,0,IF(MOD(B44, $E$6) = 0, $E$7, 0)) -> 0 | Q44: =M44+N44+O44+P44 -> 39082.815 | R44: =IF(B44<=5, Q44*'Fund Allocation Strategy'!$B$2, IF(B44<=10, Q44*'Fund Allocation Strategy'!$B$3, IF(B44<=15, Q44*'Fund Allocation Strategy'!$B$4, IF(B44<=20, Q44*'Fund Allocation Strategy'!$B$5, IF(B44<=25, Q44*'Fund Allocation Strategy'!$B$6, IF(B44<=30, Q44*'Fund Allocation Strategy'!$B$7, Q44*'Fund Allocation Strategy'!$B$8)))))) -> 19541.408 | S44: =_xlfn.NORM.INV(RAND(),'Fund Allocation Strategy'!$B$11,'Fund Allocation Strategy'!$C$11) -> 0.037803965 | T44: =U43*S44+(R44*S44*0.5) -> 9451.3074 | U44: =U43+R44+T44 -> 269230.37 | V44: =IF(B44<=5, Q44*'Fund Allocation Strategy'!$C$2, IF(B44<=10, Q44*'Fund Allocation Strategy'!$C$3, IF(B44<=15, Q44*'Fund Allocation Strategy'!$C$4, IF(B44<=20, Q44*'Fund Allocation Strategy'!$C$5, IF(B44<=25, Q44*'Fund Allocation Strategy'!$C$6, IF(B44<=30, Q44*'Fund Allocation Strategy'!$C$7, Q44*'Fund Allocation Strategy'!$C$8)))))) -> 13678.985 | W44: =_xlfn.NORM.INV(RAND(),'Fund Allocation Strategy'!$B$12,'Fund Allocation Strategy'!$C$12) -> 0.070960069 | X44: =Y43*W44 + (V44*W44*0.5) -> 24730.998 | Y44: =Y43+V44+X44 -> 380090.41 | Z44: =IF(B44<=5, Q44*'Fund Allocation Strategy'!$D$2, IF(B44<=10, Q44*'Fund Allocation Strategy'!$D$3, IF(B44<=15, Q44*'Fund Allocation Strategy'!$D$4, IF(B44<=20, Q44*'Fund Allocation Strategy'!$D$5, IF(B44<=25, Q44*'Fund Allocation Strategy'!$D$6, IF(B44<=30, Q44*'Fund Allocation Strategy'!$D$7, Q44*'Fund Allocation Strategy'!$D$8)))))) -> 5862.4223 | AA44: =_xlfn.NORM.INV(RAND(),'Fund Allocation Strategy'!$B$13,'Fund Allocation Strategy'!$C$13) -> 0.10585552 | AB44: =AC43*AA44+(Z44*AA44*0.5) -> 87231.959 | AC44: =AC43+Z44+AB44 -> 914229.41 | AD44: =IF(B44<=5, Q44*'Fund Allocation Strategy'!$E$2, IF(B44<=10, Q44*'Fund Allocation Strategy'!$E$3, IF(B44<=15, Q44*'Fund Allocation Strategy'!$E$4, IF(B44<=20, Q44*'Fund Allocation Strategy'!$E$5, IF(B44<=25, Q44*'Fund Allocation Strategy'!$E$6, IF(B44<=30, Q44*'Fund Allocation Strategy'!$E$7, Q44*'Fund Allocation Strategy'!$E$8)))))) -> 0 | AE44: =_xlfn.NORM.INV(RAND(), 'Fund Allocation Strategy'!$B$14, 'Fund Allocation Strategy'!$C$14) + _xlfn.NORM.INV(RAND(), 'Fund Allocation Strategy'!$D$14,'Fund Allocation Strategy'!$E$14) -> 0.34627789 | AF44: =AM43*AE44+(AD44*AE44*0.5) -> 320214.37 | AG44: =IF(B44<=5, Q44*'Fund Allocation Strategy'!$F$2, IF(B44<=10, Q44*'Fund Allocation Strategy'!$F$3, IF(B44<=15, Q44*'Fund Allocation Strategy'!$F$4, IF(B44<=20, Q44*'Fund Allocation Strategy'!$F$5, IF(B44<=25, Q44*'Fund Allocation Strategy'!$F$6, IF(B44<=30, Q44*'Fund Allocation Strategy'!$F$7, Q44*'Fund Allocation Strategy'!$F$8)))))) -> 0 | AH44: =_xlfn.NORM.INV(RAND(),'Fund Allocation Strategy'!$B$15,'Fund Allocation Strategy'!$C$15) -> 0.2030753 | AI44: =AI43*AH44+(AG44*AH44*0.5) -> 0.020356144 | AJ44: =AJ43+AG44+AI44 -> 44427.959 | AK44: =IF(AM44<50000,0, AM44*0.015) -> 18674.201 | AL44: =IF(AM44<50000,0,0.015) -> 0.015 | AM44: =AM43+AD44+AF44 -> 1244946.7 | AN44: =AM44-AK44 -> 1226272.5 | AO44: =IF(AV44 = 0, I44 * ( 'Lifestyle Strategy'!$B$2 + ('Lifestyle Strategy'!$C$2 - 'Lifestyle Strategy'!$B$2) * _xlfn.BETA.INV(RAND(), 'Lifestyle Strategy'!$F$2, 'Lifestyle Strategy'!$G$2) ),IF(AV44 = "", "",0)) | AP44: =I44 * ( 'Lifestyle Strategy'!$B$3 + ('Lifestyle Strategy'!$C$3 - 'Lifestyle Strategy'!$B$3) * _xlfn.BETA.INV(RAND(), 'Lifestyle Strategy'!$F$3, 'Lifestyle Strategy'!$G$3) ) * IF(MOD(B44,5)=0, 1 + 'Lifestyle Strategy'!$M$4, 1 + 0.025) -> 38447.423 | AQ44: =I44 * ( 'Lifestyle Strategy'!$B$4 + ('Lifestyle Strategy'!$C$4 - 'Lifestyle Strategy'!$B$4) * _xlfn.BETA.INV(RAND(), 'Lifestyle Strategy'!$F$4, 'Lifestyle Strategy'!$G$4) ) * IF(MOD(B44,5)=0, 1 + 'Lifestyle Strategy'!$M$4, 1 + 0.025) -> 18303.267 | AR44: =I44 * ( 'Lifestyle Strategy'!$B$5 + ('Lifestyle Strategy'!$C$5 - 'Lifestyle Strategy'!$B$5) * _xlfn.BETA.INV(RAND(), 'Lifestyle Strategy'!$F$5, 'Lifestyle Strategy'!$G$5) ) * IF(MOD(B44,5)=0, 1 + 'Lifestyle Strategy'!$M$4, 1 + 0.025) -> 14135.788 | AS44: =I44 * ( 'Lifestyle Strategy'!$B$6 + ('Lifestyle Strategy'!$C$6 - 'Lifestyle Strategy'!$B$6) * _xlfn.BETA.INV(RAND(), 'Lifestyle Strategy'!$F$6, 'Lifestyle Strategy'!$G$6) ) * IF(MOD(B44,5)=0, 1 + 'Lifestyle Strategy'!$M$4, 1 + 0.025) -> 13077.863 | AT44: =I44 * ( 'Lifestyle Strategy'!$B$7 + ('Lifestyle Strategy'!$C$7 - 'Lifestyle Strategy'!$B$7) * _xlfn.BETA.INV(RAND(), 'Lifestyle Strategy'!$F$7, 'Lifestyle Strategy'!$G$7) ) * IF(MOD(B44,5)=0, 1 + 'Lifestyle Strategy'!$M$4, 1 + 0.025) -> 30572.123 | AU44: =I44 * ( 'Lifestyle Strategy'!$B$8 + ('Lifestyle Strategy'!$C$8 - 'Lifestyle Strategy'!$B$8) * _xlfn.BETA.INV(RAND(), 'Lifestyle Strategy'!$F$8, 'Lifestyle Strategy'!$G$8) ) * IF(MOD(B44,5)=0, 1 + 'Lifestyle Strategy'!$M$4, 1 + 0.025) -> 15209.777 | AV44: =IF('Lifestyle Strategy'!$B$14 = "Yes", IF(AND(B44>='Lifestyle Strategy'!$B$15, B44<'Lifestyle Strategy'!$B$16), 'Lifestyle Strategy'!$B$25, IF(B44>='Lifestyle Strategy'!$B$16, "", 0) ), 0 ) | AW44: =IF('Lifestyle Strategy'!$Q$4="No", 0, IF(AND(B44>='Lifestyle Strategy'!$Q$5, B44<'Lifestyle Strategy'!$Q$6), 'Lifestyle Strategy'!$Q$8 * (1.025^(B44-'Lifestyle Strategy'!$Q$5)) * (1.12^INT((B44-'Lifestyle Strategy'!$Q$5)/5)), 0 ) ) -> 0 | AX44: =IF(AO44 = "",0,AO44)+AP44+AQ44+AR44+AS44+AT44+AU44+AW44+IF(AV44 = "",0,AV44) -> 129746.24 | AY44: =IF(B44='Lifestyle Strategy'!$Q$10, MIN(AN44, 'Lifestyle Strategy'!$Q$11), 0) -> 0 | AZ44: =IF(B44='Lifestyle Strategy'!$Q$10, 'Lifestyle Strategy'!$Q$11, 0) -> 0 | BA44: =IF(B44='Lifestyle Strategy'!$Q$10, MAX(AZ44 - AY44, 0), 0) -> 0 | BB44: =U44+Y44+AC44+AJ44+AN44-AY44 -> 2834250.7 | BC44: =TEXT(BB44/1000000, "[$$-en-US]0.00") & "M" -> $2.83M | BT44: Column1 | BU44: Pre | BV44: Post Ret. Corpus | BW44: Tota Corpus | BX44: Post Spent Exp.
B45: 32 | C45: 62 | D45: =IF(B45<>$B$5,D44*(1+_xlfn.NORM.INV(RAND(),$B$3,$B$4)),D44*(1+_xlfn.NORM.INV(RAND(),$B$3,$B$4))+D44*(1+_xlfn.NORM.INV(RAND(),$B$3,$B$4))) -> 413199.49 | E45: =D45-D44 -> 10188.299 | F45: =E45/D44 -> 0.025280436 | G45: ='Tax rate cal'!C42 -> 139702.24 | H45: =$B$6*D45 -> 6900.4315 | I45: =D45-G45-H45 -> 266596.82 | J45: =MIN($E$2 + INT(B45/$E$3)*$E$4, $E$5) -> 0.12 | K45: 0.03 | L45: =IF(O45 = 0,0,'Lifestyle Strategy'!$Q$9) -> 0 | M45: =I45*J45 -> 31991.618 | N45: =I45*K45 -> 7997.9046 | O45: =IF(AND('Lifestyle Strategy'!$Q$2="Yes", B45 >='Lifestyle Strategy'!$Q$3), I45 * 'Lifestyle Strategy'!$Q$9, 0 ) -> 0 | P45: =IF(B45<10,0,IF(MOD(B45, $E$6) = 0, $E$7, 0)) -> 0 | Q45: =M45+N45+O45+P45 -> 39989.523 | R45: =IF(B45<=5, Q45*'Fund Allocation Strategy'!$B$2, IF(B45<=10, Q45*'Fund Allocation Strategy'!$B$3, IF(B45<=15, Q45*'Fund Allocation Strategy'!$B$4, IF(B45<=20, Q45*'Fund Allocation Strategy'!$B$5, IF(B45<=25, Q45*'Fund Allocation Strategy'!$B$6, IF(B45<=30, Q45*'Fund Allocation Strategy'!$B$7, Q45*'Fund Allocation Strategy'!$B$8)))))) -> 19994.762 | S45: =_xlfn.NORM.INV(RAND(),'Fund Allocation Strategy'!$B$11,'Fund Allocation Strategy'!$C$11) -> 0.03779822 | T45: =U44*S45+(R45*S45*0.5) -> 10554.312 | U45: =U44+R45+T45 -> 299779.45 | V45: =IF(B45<=5, Q45*'Fund Allocation Strategy'!$C$2, IF(B45<=10, Q45*'Fund Allocation Strategy'!$C$3, IF(B45<=15, Q45*'Fund Allocation Strategy'!$C$4, IF(B45<=20, Q45*'Fund Allocation Strategy'!$C$5, IF(B45<=25, Q45*'Fund Allocation Strategy'!$C$6, IF(B45<=30, Q45*'Fund Allocation Strategy'!$C$7, Q45*'Fund Allocation Strategy'!$C$8)))))) -> 13996.333 | W45: =_xlfn.NORM.INV(RAND(),'Fund Allocation Strategy'!$B$12,'Fund Allocation Strategy'!$C$12) -> 0.068382536 | X45: =Y44*W45 + (V45*W45*0.5) -> 26470.098 | Y45: =Y44+V45+X45 -> 420556.84 | Z45: =IF(B45<=5, Q45*'Fund Allocation Strategy'!$D$2, IF(B45<=10, Q45*'Fund Allocation Strategy'!$D$3, IF(B45<=15, Q45*'Fund Allocation Strategy'!$D$4, IF(B45<=20, Q45*'Fund Allocation Strategy'!$D$5, IF(B45<=25, Q45*'Fund Allocation Strategy'!$D$6, IF(B45<=30, Q45*'Fund Allocation Strategy'!$D$7, Q45*'Fund Allocation Strategy'!$D$8)))))) -> 5998.4285 | AA45: =_xlfn.NORM.INV(RAND(),'Fund Allocation Strategy'!$B$13,'Fund Allocation Strategy'!$C$13) -> 0.10340015 | AB45: =AC44*AA45+(Z45*AA45*0.5) -> 94841.575 | AC45: =AC44+Z45+AB45 -> 1015069.4 | AD45: =IF(B45<=5, Q45*'Fund Allocation Strategy'!$E$2, IF(B45<=10, Q45*'Fund Allocation Strategy'!$E$3, IF(B45<=15, Q45*'Fund Allocation Strategy'!$E$4, IF(B45<=20, Q45*'Fund Allocation Strategy'!$E$5, IF(B45<=25, Q45*'Fund Allocation Strategy'!$E$6, IF(B45<=30, Q45*'Fund Allocation Strategy'!$E$7, Q45*'Fund Allocation Strategy'!$E$8)))))) -> 0 | AE45: =_xlfn.NORM.INV(RAND(), 'Fund Allocation Strategy'!$B$14, 'Fund Allocation Strategy'!$C$14) + _xlfn.NORM.INV(RAND(), 'Fund Allocation Strategy'!$D$14,'Fund Allocation Strategy'!$E$14) -> 0.25331914 | AF45: =AM44*AE45+(AD45*AE45*0.5) -> 315368.83 | AG45: =IF(B45<=5, Q45*'Fund Allocation Strategy'!$F$2, IF(B45<=10, Q45*'Fund Allocation Strategy'!$F$3, IF(B45<=15, Q45*'Fund Allocation Strategy'!$F$4, IF(B45<=20, Q45*'Fund Allocation Strategy'!$F$5, IF(B45<=25, Q45*'Fund Allocation Strategy'!$F$6, IF(B45<=30, Q45*'Fund Allocation Strategy'!$F$7, Q45*'Fund Allocation Strategy'!$F$8)))))) -> 0 | AH45: =_xlfn.NORM.INV(RAND(),'Fund Allocation Strategy'!$B$15,'Fund Allocation Strategy'!$C$15) -> 0.21953088 | AI45: =AI44*AH45+(AG45*AH45*0.5) -> 0.0044688023 | AJ45: =AJ44+AG45+AI45 -> 44427.963 | AK45: =IF(AM45<50000,0, AM45*0.015) -> 23404.733 | AL45: =IF(AM45<50000,0,0.015) -> 0.015 | AM45: =AM44+AD45+AF45 -> 1560315.6 | AN45: =AM45-AK45 -> 1536910.8 | AO45: =IF(AV45 = 0, I45 * ( 'Lifestyle Strategy'!$B$2 + ('Lifestyle Strategy'!$C$2 - 'Lifestyle Strategy'!$B$2) * _xlfn.BETA.INV(RAND(), 'Lifestyle Strategy'!$F$2, 'Lifestyle Strategy'!$G$2) ),IF(AV45 = "", "",0)) | AP45: =I45 * ( 'Lifestyle Strategy'!$B$3 + ('Lifestyle Strategy'!$C$3 - 'Lifestyle Strategy'!$B$3) * _xlfn.BETA.INV(RAND(), 'Lifestyle Strategy'!$F$3, 'Lifestyle Strategy'!$G$3) ) * IF(MOD(B45,5)=0, 1 + 'Lifestyle Strategy'!$M$4, 1 + 0.025) -> 30264.398 | AQ45: =I45 * ( 'Lifestyle Strategy'!$B$4 + ('Lifestyle Strategy'!$C$4 - 'Lifestyle Strategy'!$B$4) * _xlfn.BETA.INV(RAND(), 'Lifestyle Strategy'!$F$4, 'Lifestyle Strategy'!$G$4) ) * IF(MOD(B45,5)=0, 1 + 'Lifestyle Strategy'!$M$4, 1 + 0.025) -> 17347.35 | AR45: =I45 * ( 'Lifestyle Strategy'!$B$5 + ('Lifestyle Strategy'!$C$5 - 'Lifestyle Strategy'!$B$5) * _xlfn.BETA.INV(RAND(), 'Lifestyle Strategy'!$F$5, 'Lifestyle Strategy'!$G$5) ) * IF(MOD(B45,5)=0, 1 + 'Lifestyle Strategy'!$M$4, 1 + 0.025) -> 14145.635 | AS45: =I45 * ( 'Lifestyle Strategy'!$B$6 + ('Lifestyle Strategy'!$C$6 - 'Lifestyle Strategy'!$B$6) * _xlfn.BETA.INV(RAND(), 'Lifestyle Strategy'!$F$6, 'Lifestyle Strategy'!$G$6) ) * IF(MOD(B45,5)=0, 1 + 'Lifestyle Strategy'!$M$4, 1 + 0.025) -> 14836.438 | AT45: =I45 * ( 'Lifestyle Strategy'!$B$7 + ('Lifestyle Strategy'!$C$7 - 'Lifestyle Strategy'!$B$7) * _xlfn.BETA.INV(RAND(), 'Lifestyle Strategy'!$F$7, 'Lifestyle Strategy'!$G$7) ) * IF(MOD(B45,5)=0, 1 + 'Lifestyle Strategy'!$M$4, 1 + 0.025) -> 25581.138 | AU45: =I45 * ( 'Lifestyle Strategy'!$B$8 + ('Lifestyle Strategy'!$C$8 - 'Lifestyle Strategy'!$B$8) * _xlfn.BETA.INV(RAND(), 'Lifestyle Strategy'!$F$8, 'Lifestyle Strategy'!$G$8) ) * IF(MOD(B45,5)=0, 1 + 'Lifestyle Strategy'!$M$4, 1 + 0.025) -> 9439.9374 | AV45: =IF('Lifestyle Strategy'!$B$14 = "Yes", IF(AND(B45>='Lifestyle Strategy'!$B$15, B45<'Lifestyle Strategy'!$B$16), 'Lifestyle Strategy'!$B$25, IF(B45>='Lifestyle Strategy'!$B$16, "", 0) ), 0 ) | AW45: =IF('Lifestyle Strategy'!$Q$4="No", 0, IF(AND(B45>='Lifestyle Strategy'!$Q$5, B45<'Lifestyle Strategy'!$Q$6), 'Lifestyle Strategy'!$Q$8 * (1.025^(B45-'Lifestyle Strategy'!$Q$5)) * (1.12^INT((B45-'Lifestyle Strategy'!$Q$5)/5)), 0 ) ) -> 0 | AX45: =IF(AO45 = "",0,AO45)+AP45+AQ45+AR45+AS45+AT45+AU45+AW45+IF(AV45 = "",0,AV45) -> 111614.9 | AY45: =IF(B45='Lifestyle Strategy'!$Q$10, MIN(AN45, 'Lifestyle Strategy'!$Q$11), 0) -> 0 | AZ45: =IF(B45='Lifestyle Strategy'!$Q$10, 'Lifestyle Strategy'!$Q$11, 0) -> 0 | BA45: =IF(B45='Lifestyle Strategy'!$Q$10, MAX(AZ45 - AY45, 0), 0) -> 0 | BB45: =U45+Y45+AC45+AJ45+AN45-AY45 -> 3316744.5 | BC45: =TEXT(BB45/1000000, "[$$-en-US]0.00") & "M" -> $3.32M | BT45: Count | BU45: =COUNT(BM50:BM5049) -> 5000 | BV45: =COUNT(BN50:BN5049) -> 5000 | BW45: =COUNT(BO50:BO5049) -> 5000 | BX45: =COUNT(BP50:BP5049) -> 5000
B46: 33 | C46: 63 | D46: =IF(B46<>$B$5,D45*(1+_xlfn.NORM.INV(RAND(),$B$3,$B$4)),D45*(1+_xlfn.NORM.INV(RAND(),$B$3,$B$4))+D45*(1+_xlfn.NORM.INV(RAND(),$B$3,$B$4))) -> 429242.97 | E46: =D46-D45 -> 16043.475 | F46: =E46/D45 -> 0.038827431 | G46: ='Tax rate cal'!C43 -> 145959.19 | H46: =$B$6*D46 -> 7168.3575 | I46: =D46-G46-H46 -> 276115.41 | J46: =MIN($E$2 + INT(B46/$E$3)*$E$4, $E$5) -> 0.12 | K46: 0.03 | L46: =IF(O46 = 0,0,'Lifestyle Strategy'!$Q$9) -> 0 | M46: =I46*J46 -> 33133.85 | N46: =I46*K46 -> 8283.4624 | O46: =IF(AND('Lifestyle Strategy'!$Q$2="Yes", B46 >='Lifestyle Strategy'!$Q$3), I46 * 'Lifestyle Strategy'!$Q$9, 0 ) -> 0 | P46: =IF(B46<10,0,IF(MOD(B46, $E$6) = 0, $E$7, 0)) -> 0 | Q46: =M46+N46+O46+P46 -> 41417.312 | R46: =IF(B46<=5, Q46*'Fund Allocation Strategy'!$B$2, IF(B46<=10, Q46*'Fund Allocation Strategy'!$B$3, IF(B46<=15, Q46*'Fund Allocation Strategy'!$B$4, IF(B46<=20, Q46*'Fund Allocation Strategy'!$B$5, IF(B46<=25, Q46*'Fund Allocation Strategy'!$B$6, IF(B46<=30, Q46*'Fund Allocation Strategy'!$B$7, Q46*'Fund Allocation Strategy'!$B$8)))))) -> 20708.656 | S46: =_xlfn.NORM.INV(RAND(),'Fund Allocation Strategy'!$B$11,'Fund Allocation Strategy'!$C$11) -> 0.036796254 | T46: =U45*S46+(R46*S46*0.5) -> 11411.761 | U46: =U45+R46+T46 -> 331899.86 | V46: =IF(B46<=5, Q46*'Fund Allocation Strategy'!$C$2, IF(B46<=10, Q46*'Fund Allocation Strategy'!$C$3, IF(B46<=15, Q46*'Fund Allocation Strategy'!$C$4, IF(B46<=20, Q46*'Fund Allocation Strategy'!$C$5, IF(B46<=25, Q46*'Fund Allocation Strategy'!$C$6, IF(B46<=30, Q46*'Fund Allocation Strategy'!$C$7, Q46*'Fund Allocation Strategy'!$C$8)))))) -> 14496.059 | W46: =_xlfn.NORM.INV(RAND(),'Fund Allocation Strategy'!$B$12,'Fund Allocation Strategy'!$C$12) -> 0.071023325 | X46: =Y45*W46 + (V46*W46*0.5) -> 30384.124 | Y46: =Y45+V46+X46 -> 465437.02 | Z46: =IF(B46<=5, Q46*'Fund Allocation Strategy'!$D$2, IF(B46<=10, Q46*'Fund Allocation Strategy'!$D$3, IF(B46<=15, Q46*'Fund Allocation Strategy'!$D$4, IF(B46<=20, Q46*'Fund Allocation Strategy'!$D$5, IF(B46<=25, Q46*'Fund Allocation Strategy'!$D$6, IF(B46<=30, Q46*'Fund Allocation Strategy'!$D$7, Q46*'Fund Allocation Strategy'!$D$8)))))) -> 6212.5968 | AA46: =_xlfn.NORM.INV(RAND(),'Fund Allocation Strategy'!$B$13,'Fund Allocation Strategy'!$C$13) -> 0.099005009 | AB46: =AC45*AA46+(Z46*AA46*0.5) -> 100804.5 | AC46: =AC45+Z46+AB46 -> 1122086.5 | AD46: =IF(B46<=5, Q46*'Fund Allocation Strategy'!$E$2, IF(B46<=10, Q46*'Fund Allocation Strategy'!$E$3, IF(B46<=15, Q46*'Fund Allocation Strategy'!$E$4, IF(B46<=20, Q46*'Fund Allocation Strategy'!$E$5, IF(B46<=25, Q46*'Fund Allocation Strategy'!$E$6, IF(B46<=30, Q46*'Fund Allocation Strategy'!$E$7, Q46*'Fund Allocation Strategy'!$E$8)))))) -> 0 | AE46: =_xlfn.NORM.INV(RAND(), 'Fund Allocation Strategy'!$B$14, 'Fund Allocation Strategy'!$C$14) + _xlfn.NORM.INV(RAND(), 'Fund Allocation Strategy'!$D$14,'Fund Allocation Strategy'!$E$14) -> 0.25211043 | AF46: =AM45*AE46+(AD46*AE46*0.5) -> 393371.83 | AG46: =IF(B46<=5, Q46*'Fund Allocation Strategy'!$F$2, IF(B46<=10, Q46*'Fund Allocation Strategy'!$F$3, IF(B46<=15, Q46*'Fund Allocation Strategy'!$F$4, IF(B46<=20, Q46*'Fund Allocation Strategy'!$F$5, IF(B46<=25, Q46*'Fund Allocation Strategy'!$F$6, IF(B46<=30, Q46*'Fund Allocation Strategy'!$F$7, Q46*'Fund Allocation Strategy'!$F$8)))))) -> 0 | AH46: =_xlfn.NORM.INV(RAND(),'Fund Allocation Strategy'!$B$15,'Fund Allocation Strategy'!$C$15) -> 0.20976426 | AI46: =AI45*AH46+(AG46*AH46*0.5) -> 0.00093739502 | AJ46: =AJ45+AG46+AI46 -> 44427.964 | AK46: =IF(AM46<50000,0, AM46*0.015) -> 29305.311 | AL46: =IF(AM46<50000,0,0.015) -> 0.015 | AM46: =AM45+AD46+AF46 -> 1953687.4 | AN46: =AM46-AK46 -> 1924382.1 | AO46: =IF(AV46 = 0, I46 * ( 'Lifestyle Strategy'!$B$2 + ('Lifestyle Strategy'!$C$2 - 'Lifestyle Strategy'!$B$2) * _xlfn.BETA.INV(RAND(), 'Lifestyle Strategy'!$F$2, 'Lifestyle Strategy'!$G$2) ),IF(AV46 = "", "",0)) | AP46: =I46 * ( 'Lifestyle Strategy'!$B$3 + ('Lifestyle Strategy'!$C$3 - 'Lifestyle Strategy'!$B$3) * _xlfn.BETA.INV(RAND(), 'Lifestyle Strategy'!$F$3, 'Lifestyle Strategy'!$G$3) ) * IF(MOD(B46,5)=0, 1 + 'Lifestyle Strategy'!$M$4, 1 + 0.025) -> 38117.164 | AQ46: =I46 * ( 'Lifestyle Strategy'!$B$4 + ('Lifestyle Strategy'!$C$4 - 'Lifestyle Strategy'!$B$4) * _xlfn.BETA.INV(RAND(), 'Lifestyle Strategy'!$F$4, 'Lifestyle Strategy'!$G$4) ) * IF(MOD(B46,5)=0, 1 + 'Lifestyle Strategy'!$M$4, 1 + 0.025) -> 23170.84 | AR46: =I46 * ( 'Lifestyle Strategy'!$B$5 + ('Lifestyle Strategy'!$C$5 - 'Lifestyle Strategy'!$B$5) * _xlfn.BETA.INV(RAND(), 'Lifestyle Strategy'!$F$5, 'Lifestyle Strategy'!$G$5) ) * IF(MOD(B46,5)=0, 1 + 'Lifestyle Strategy'!$M$4, 1 + 0.025) -> 13887.893 | AS46: =I46 * ( 'Lifestyle Strategy'!$B$6 + ('Lifestyle Strategy'!$C$6 - 'Lifestyle Strategy'!$B$6) * _xlfn.BETA.INV(RAND(), 'Lifestyle Strategy'!$F$6, 'Lifestyle Strategy'!$G$6) ) * IF(MOD(B46,5)=0, 1 + 'Lifestyle Strategy'!$M$4, 1 + 0.025) -> 13540.589 | AT46: =I46 * ( 'Lifestyle Strategy'!$B$7 + ('Lifestyle Strategy'!$C$7 - 'Lifestyle Strategy'!$B$7) * _xlfn.BETA.INV(RAND(), 'Lifestyle Strategy'!$F$7, 'Lifestyle Strategy'!$G$7) ) * IF(MOD(B46,5)=0, 1 + 'Lifestyle Strategy'!$M$4, 1 + 0.025) -> 26662.425 | AU46: =I46 * ( 'Lifestyle Strategy'!$B$8 + ('Lifestyle Strategy'!$C$8 - 'Lifestyle Strategy'!$B$8) * _xlfn.BETA.INV(RAND(), 'Lifestyle Strategy'!$F$8, 'Lifestyle Strategy'!$G$8) ) * IF(MOD(B46,5)=0, 1 + 'Lifestyle Strategy'!$M$4, 1 + 0.025) -> 13918.331 | AV46: =IF('Lifestyle Strategy'!$B$14 = "Yes", IF(AND(B46>='Lifestyle Strategy'!$B$15, B46<'Lifestyle Strategy'!$B$16), 'Lifestyle Strategy'!$B$25, IF(B46>='Lifestyle Strategy'!$B$16, "", 0) ), 0 ) | AW46: =IF('Lifestyle Strategy'!$Q$4="No", 0, IF(AND(B46>='Lifestyle Strategy'!$Q$5, B46<'Lifestyle Strategy'!$Q$6), 'Lifestyle Strategy'!$Q$8 * (1.025^(B46-'Lifestyle Strategy'!$Q$5)) * (1.12^INT((B46-'Lifestyle Strategy'!$Q$5)/5)), 0 ) ) -> 0 | AX46: =IF(AO46 = "",0,AO46)+AP46+AQ46+AR46+AS46+AT46+AU46+AW46+IF(AV46 = "",0,AV46) -> 129297.24 | AY46: =IF(B46='Lifestyle Strategy'!$Q$10, MIN(AN46, 'Lifestyle Strategy'!$Q$11), 0) -> 0 | AZ46: =IF(B46='Lifestyle Strategy'!$Q$10, 'Lifestyle Strategy'!$Q$11, 0) -> 0 | BA46: =IF(B46='Lifestyle Strategy'!$Q$10, MAX(AZ46 - AY46, 0), 0) -> 0 | BB46: =U46+Y46+AC46+AJ46+AN46-AY46 -> 3888233.4 | BC46: =TEXT(BB46/1000000, "[$$-en-US]0.00") & "M" -> $3.89M | BT46: Min | BU46: =MIN(BM50:BM5049) -> 1119930.8 | BV46: =MIN(BN50:BN5049) -> -645541.79 | BW46: =MIN(BO50:BO5049) -> 765529.23 | BX46: =MIN(BP50:BP5049) -> 1913123.5
